Workbook
Name liste: #REF!
Name liste: #REF!
Name liste: #REF!
Name liste: #REF!
Name liste: #REF!
Name Liste_caisses: '[1]LISTES POUR SIMULATEUR'!$L$14:$L$141
Name Liste_caisses: #REF!
Name Liste_caisses: #REF!
Name Liste_caisses: #REF!
Name Liste_caisses: #REF!
Name Liste_caisses: #REF!
Name Liste_communes: '[1]CODES COMMUNE & GRANDES VILLES'!$A$2:$A$5
Name Liste_communes: #REF!
Name Liste_communes: 'CODES COMMUNE & GRANDES VILLES'!$A$2:$A$5
Name liste_exos: '[1]LISTES POUR SIMULATEUR'!$A$28:$A$32
Name liste_exos: #REF!
Name liste_exos: #REF!
Name liste_exos: #REF!
Name liste_exos: #REF!
Name liste_exos: #REF!
Name Liste_motifs_exo: #REF!
Name Liste_motifs_exo: #REF!
Name Liste_motifs_exo: #REF!
Name Liste_motifs_exo: #REF!
Name Liste_motifs_exo: #REF!
Name Liste_nb_malades: '[1]LISTES POUR SIMULATEUR'!$L$2:$L$10
Name Liste_nb_malades: #REF!
Name Liste_nb_malades: #REF!
Name Liste_nb_malades: #REF!
Name Liste_nb_malades: #REF!
Name Liste_nb_malades: #REF!
Name Liste_prescripteur: #REF!
Name Liste_prescripteur: #REF!
Name Liste_prescripteur: #REF!
Name Liste_prescripteur: #REF!
Name Liste_prescripteur: #REF!
Name Liste_prescripteur: #REF!
Name Liste_prescripteur: #REF!
Name Liste_prescripteur: #REF!
Name Liste_prescripteur: #REF!
Name Liste_prescripteur: #REF!
Name Liste_prescripteur: #REF!
Name Liste_prescripteur: #REF!
Name Liste_prescripteur: #REF!
Name Liste_prescripteur: #REF!
Name Liste_prescripteur: #REF!
Name Liste_prescripteur: #REF!
Name Liste_prescripteur: #REF!
Name Liste_prescripteur: #REF!
Name Liste_prescripteur: #REF!
Name Liste_prescripteur: #REF!
Name Liste_prescripteur: #REF!
Name Liste_prescripteur: #REF!
Name Liste_prescripteur: #REF!
Name Liste_prescripteur: #REF!
Name Liste_prescripteur: #REF!
Name Liste_prescripteur: #REF!
Name Liste_prescripteur: #REF!
Name Liste_prescripteur: #REF!
Name Liste_prescripteur: #REF!

Sheet PREAMBULE
A1: DATE DE DERNIERE MISE A JOUR : 26/09/2025
A2: LE PRESENT FICHIER CONSTITUE L'ANNEXE 30 A LA NORME B2 POUR ILLUSTRER LES MODALITES DE FACTURATION EN NORME B2 VERS L'ASSURANCE MALADIE PAR LES SOCIETES DE TAXIS DANS LE CADRE DE LA NOUVELLE CONVENTION TAXIS 2025 - 2029 ET DU DECRET TIERS PAYANT CONTRE TRANSPORT PARTAGE CE DOCUMENT VIENT EN COMPLEMENT DU CAHIER DES CHARGES A L’ATTENTION DES EDITEURS DE LOGICIELS DE FACTURATION B2 TAXIS PUBLIE SUR AMELI.FR LES DONNEES ET VALEURS MENTIONNEES VISENT A ILLUSTRER LES MODALITES DE FACTURATION. IL CONVIENT DONC DE SE REFERER A LA CONVENTION ET A SES ANNEXES POUR DISPOSER DES VALEURS REELLES A APPLIQUER

Sheet Table matière
A1: PREAMBULE
A2: Table matière
A3: LISTE DES CAS ANNEXE 30
A4: CONVENTION CAS 1
A5: CONVENTION CAS 2
A6: CONVENTION CAS 3
A7: CONVENTION CAS 4
A8: CONVENTION CAS 5
A9: CONVENTION CAS 6
A10: CONVENTION CAS 7
A11: CONVENTION CAS 8
A12: CONVENTION CAS 9
... A42: B2 CODES ACTES TP TP

Sheet LISTE DES CAS ANNEXE 30
A1: SOCIETE DE TAXI DE N° AM : 422500009 SPECIALITE : 56 | D1: CARACTERISTIQUES PATIENT | I1: CARACTERISTIQUES FACTURE | K1: CARACTERISTIQUES TRAJETS
A2: N°CAS | B2: NOMBRE DE TRAJETS FACTURES | C2: TRAJET N° : | D2: NATURE D'ASSURANCE | E2: TAUX | F2: AME ? : O/N | G2: RLAM ? O/N | H2: C2S ? : O/N | I2: REFUS TRANSPORT PARTAGE | J2: TIERS PAYANT | K2: LIEU DEPART | L2: LIEU ARRIVEE | M2: DATE / HEURE DEPART | N2: DATE / HEURE ARRIVEE | O2: N° IMMATRICULATION VEHICULE | P2: COMMUNE D'ADS | Q2: DEPARTEMENT D'ADS | R2: ORGANISME LOCAL D'ADS | S2: DISTANCE PARCOURUE | T2: CONTEXTE : J, N , F | U2: NOMBRE DE MALADES | V2: SUPPLEMENT FORFAITAIRE ? : O / N | W2: PEAGES ? : O / N | X2: TPMR ? : O / N | Y2: TRAJET EN LIEN AVEC HOSPITALISATION ET RETOUR A VIDE ? : O/N | Z2: SI T PARTAGE : TRAJET SEUL > X KM ? : O/N
A3: CONVENTION CAS 1 | B3: 1 | C3: 1 | D3: MALADIE | E3: 0.55 | F3: NON | G3: NON | H3: NON | I3: Sans objet | J3: 05 - TP AMO SEUL | K3: 42-SAINT-ETIENNE | L3: 42-SAINT-ETIENNE | M3: 01/12/2025 à 10H00 | N3: 01/12/2025 à 10H11 | O3: AA-001-BB | P3: 42218 (SAINT-ETIENNE) | Q3: 042 | R3: 422 - CPAM DE LA LOIRE | S3: 3 | T3: JOUR | U3: 1 | V3: NON | W3: NON | X3: NON | Y3: NON | Z3: Sans objet
A5: CONVENTION CAS 2 | B5: 1 | C5: 1 | D5: MALADIE | E5: 0.55 | F5: NON | G5: NON | H5: NON | I5: Sans objet | J5: 05 - TP AMO SEUL | K5: 69-LYON | L5: 69-VILLEURBANNE | M5: 01/12/2025 à 10H00 | N5: 01/12/2025 à 10H11 | O5: EE-003-FF | P5: 69123 (LYON) | Q5: 069 | R5: 691 - CPAM DU RHONE | S5: 3 | T5: JOUR | U5: 1 | V5: NON | W5: NON | X5: NON | Y5: NON | Z5: Sans objet
A7: CONVENTION CAS 3 | B7: 1 | C7: 1 | D7: MALADIE | E7: 0.55 | F7: NON | G7: NON | H7: NON | I7: Sans objet | J7: 05 - TP AMO SEUL | K7: 69-LYON | L7: 42-SAINT-ETIENNE | M7: 01/12/2025 à 10H00 | N7: 01/12/2025 à 11h15 | O7: EE-003-FF | P7: 69123 (LYON) | Q7: 069 | R7: 691 - CPAM DU RHONE | S7: 63 | T7: JOUR | U7: 1 | V7: NON | W7: NON | X7: NON | Y7: NON | Z7: Sans objet
A9: CONVENTION CAS 4 | B9: 1 | C9: 1 | D9: MALADIE | E9: 0.55 | F9: NON | G9: NON | H9: NON | I9: Sans objet | J9: 05 - TP AMO SEUL | K9: 42-SAINT-ETIENNE | L9: 69-LYON | M9: 01/12/2025 à 10H00 | N9: 01/12/2025 à 11h15 | O9: AA-001-BB | P9: 42218 (SAINT-ETIENNE) | Q9: 042 | R9: 422 - CPAM DE LA LOIRE | S9: 63 | T9: JOUR | U9: 1 | V9: NON | W9: NON | X9: NON | Y9: OUI | Z9: Sans objet
A11: CONVENTION CAS 5 | B11: 1 | C11: 1 | D11: MALADIE | E11: 0.55 | F11: NON | G11: NON | H11: NON | I11: Sans objet | J11: 05 - TP AMO SEUL | K11: 42-SAINT-ETIENNE | L11: 42-MONTBRISON | M11: 01/12/2025 à 10H00 | N11: 01/12/2025 à 10h50 | O11: AA-001-BB | P11: 42218 (SAINT-ETIENNE) | Q11: 042 | R11: 422 - CPAM DE LA LOIRE | S11: 40 | T11: JOUR | U11: 1 | V11: OUI (TYPES 1 & 2) | W11: NON | X11: NON | Y11: NON | Z11: Sans objet
A13: CONVENTION CAS 6 | B13: 1 | C13: 1 | D13: MALADIE | E13: 0.55 | F13: NON | G13: NON | H13: NON | I13: Sans objet | J13: 05 - TP AMO SEUL | K13: 42-SAINT-ETIENNE | L13: 42-MONTBRISON | M13: 01/12/2025 à 10H00 | N13: 01/12/2025 à 10h40 | O13: AA-001-BB | P13: 42218 (SAINT-ETIENNE) | Q13: 042 | R13: 422 - CPAM DE LA LOIRE | S13: 43 | T13: JOUR | U13: 1 | V13: NON | W13: OUI (à 1,20€) | X13: NON | Y13: NON | Z13: Sans objet
A15: CONVENTION CAS 7 | B15: 2 | C15: 1 | D15: MALADIE | E15: 0.55 | F15: NON | G15: NON | H15: NON | I15: Sans objet | J15: 05 - TP AMO SEUL | K15: 42-SAINT-ETIENNE | L15: 42-MONTBRISON | M15: 01/12/2025 à 10H00 | N15: 01/12/2025 à 10h50 | O15: AA-001-BB | P15: 42218 (SAINT-ETIENNE) | Q15: 042 | R15: 422 - CPAM DE LA LOIRE | S15: 40 | T15: JOUR | U15: 1 | V15: NON | W15: NON | X15: OUI | Y15: NON | Z15: Sans objet
C16: 2 | D16: MALADIE | E16: 0.55 | F16: NON | G16: NON | H16: NON | I16: Sans objet | J16: 05 - TP AMO SEUL | K16: 42-MONTBRISON | L16: 42-SAINT-ETIENNE | M16: 01/12/2025 à 13H00 | N16: 01/12/2025 à 13h50 | O16: AA-001-BB | P16: 42218 (SAINT-ETIENNE) | Q16: 042 | R16: 422 - CPAM DE LA LOIRE | S16: 40 | T16: JOUR | U16: 1 | V16: NON | W16: NON | X16: OUI | Y16: NON | Z16: Sans objet
A18: CONVENTION CAS 8 | B18: 1 | C18: 1 | D18: MALADIE | E18: 0.55 | F18: NON | G18: NON | H18: NON | I18: Sans objet | J18: 05 - TP AMO SEUL | K18: 42-SAINT-ETIENNE | L18: 42-MONTBRISON | M18: 01/12/2025 à 20h00 | N18: 01/12/2025 à 20h40 | O18: AA-001-BB | P18: 42218 (SAINT-ETIENNE) | Q18: 042 | R18: 422 - CPAM DE LA LOIRE | S18: 43 | T18: NUIT | U18: 1 | V18: OUI (TYPES 1 & 2) | W18: OUI (à 1,20€) | X18: OUI | Y18: NON | Z18: Sans objet
A20: CONVENTION CAS 9 | B20: 1 | C20: 1 | D20: MALADIE | E20: 0.55 | F20: NON | G20: NON | H20: NON | I20: Sans objet | J20: 05 - TP AMO SEUL | K20: 42-SAINT-ETIENNE | L20: 42-MONTBRISON | M20: 11/11/2025 à 10h00 | N20: 11/11/10/2025 à 10h40 | O20: AA-001-BB | P20: 42218 (SAINT-ETIENNE) | Q20: 042 | R20: 422 - CPAM DE LA LOIRE | S20: 43 | T20: DIM / J FERIE | U20: 1 | V20: OUI (TYPES 1 & 2) | W20: OUI (à 1,20€) | X20: OUI | Y20: OUI | Z20: Sans objet
A22: CONVENTION CAS 10 | B22: 1 | C22: 1 | D22: MALADIE | E22: 0.55 | F22: NON | G22: NON | H22: NON | I22: NON | J22: 05 - TP AMO SEUL | K22: 42-SAINT-ETIENNE | L22: 42-MONTBRISON | M22: 01/12/2025 à 10H00 | N22: 01/12/2025 à 10h40 | O22: AA-001-BB | P22: 42218 (SAINT-ETIENNE) | Q22: 042 | R22: 422 - CPAM DE LA LOIRE | S22: 43 | T22: JOUR | U22: 2 | V22: OUI (TYPE 1) | W22: OUI (à 0,60€) | X22: OUI | Y22: NON | Z22: NON
A24: CONVENTION CAS 11 | B24: 1 | C24: 1 | D24: MALADIE | E24: 0.55 | F24: NON | G24: NON | H24: NON | I24: NON | J24: 05 - TP AMO SEUL | K24: 69-LYON | L24: 42-SAINT-ETIENNE | M24: 01/12/2025 à 10H00 | N24: 01/12/2025 à 11h15 | O24: EE-003-FF | P24: 69123 (LYON) | Q24: 069 | R24: 691 - CPAM DU RHONE | S24: 63 | T24: JOUR | U24: 4 | V24: OUI (TYPE 1) | W24: NON | X24: OUI | Y24: OUI | Z24: NON
A26: CONVENTION CAS 12 | B26: 1 | C26: 1 | D26: MALADIE | E26: 0.55 | F26: NON | G26: NON | H26: NON | I26: NON | J26: 05 - TP AMO SEUL | K26: 42-SAINT-ETIENNE | L26: 42-MONTBRISON | M26: 01/12/2025 à 10H00 | N26: 01/12/2025 à 10h40 | O26: AA-001-BB | P26: 42218 (SAINT-ETIENNE) | Q26: 042 | R26: 422 - CPAM DE LA LOIRE | S26: 43 | T26: JOUR | U26: 3 | V26: OUI (TYPE 1) | W26: OUI (à 0,40€) | X26: OUI | Y26: NON | Z26: OUI
A28: CONVENTION CAS 13 | B28: 1 | C28: 1 | D28: MALADIE | E28: 0.55 | F28: NON | G28: NON | H28: NON | I28: NON | J28: 05 - TP AMO SEUL | K28: 42-SAINT-ETIENNE | L28: 42-MONTBRISON | M28: 01/12/2025 à 20h00 | N28: 01/12/2025 à 20h40 | O28: AA-001-BB | P28: 42218 (SAINT-ETIENNE) | Q28: 042 | R28: 422 - CPAM DE LA LOIRE | S28: 43 | T28: NUIT | U28: 3 | V28: OUI (TYPE 1) | W28: OUI (à 0,40€) | X28: OUI | Y28: OUI | Z28: NON
A30: CONVENTION CAS 14 | B30: 1 | C30: 1 | D30: MALADIE | E30: 0.55 | F30: NON | G30: NON | H30: NON | I30: NON | J30: 05 - TP AMO SEUL | K30: 69-LYON | L30: 42-SAINT-ETIENNE | M30: 11/11/2025 à 10H00 | N30: 11/11/2025 à 11h15 | O30: EE-003-FF | P30: 69123 (LYON) | Q30: 069 | R30: 691 - CPAM DU RHONE | S30: 63 | T30: DIM / J FERIE | U30: 4 | V30: OUI (TYPE 1) | W30: NON | X30: OUI | Y30: OUI | Z30: OUI
A32: CONVENTION CAS 15 | B32: 3 | C32: 1 | D32: MALADIE | E32: 0.55 | F32: NON | G32: NON | H32: OUI | I32: Sans objet | J32: 15 - TP AMO & TP AMC | K32: 42-SAINT-ETIENNE | L32: 42-MONTBRISON | M32: 01/12/2025 à 10H00 | N32: 01/12/2025 à 10h50 | O32: AA-001-BB | P32: 42218 (SAINT-ETIENNE) | Q32: 042 | R32: 422 - CPAM DE LA LOIRE | S32: 40 | T32: JOUR | U32: 1 | V32: OUI (TYPES 1 & 2) | W32: NON | X32: OUI | Y32: NON | Z32: Sans objet
C33: 2 | D33: MALADIE | E33: 0.55 | F33: NON | G33: NON | H33: OUI | I33: NON | K33: 42-MONTBRISON | L33: 42-SAINT-ETIENNE | M33: 01/12/2025 à 20H00 | N33: 01/12/2025 à 20h50 | O33: AA-001-BB | P33: 42218 (SAINT-ETIENNE) | Q33: 042 | R33: 422 - CPAM DE LA LOIRE | S33: 40 | T33: NUIT | U33: 3 | V33: OUI (TYPES 1 & 2) | W33: NON | X33: OUI | Y33: NON | Z33: NON
C34: 3 | D34: MALADIE | E34: 0.55 | F34: NON | G34: NON | H34: OUI | I34: NON | K34: 42-SAINT-ETIENNE | L34: 42-MONTBRISON | M34: 25/12/2025 à 10H00 | N34: 25/12/2025 à 10h50 | O34: AA-001-BB | P34: 42218 (SAINT-ETIENNE) | Q34: 042 | R34: 422 - CPAM DE LA LOIRE | S34: 40 | T34: DIM / J FERIE | U34: 4 | V34: OUI (TYPE 1) | W34: NON | X34: OUI | Y34: OUI | Z34: NON
A36: CONVENTION CAS 16 | B36: 5 | C36: 1 | D36: MATERNITE | E36: 1 | F36: NON | G36: NON | H36: NON | I36: NON | J36: 05 - TP AMO SEUL | K36: 69-LYON | L36: 42-SAINT-ETIENNE | M36: 10/11/2025 à 10H00 | N36: 10/11/2025 à 11h15 | O36: EE-003-FF | P36: 69123 (LYON) | Q36: 069 | R36: 691 - CPAM DU RHONE | S36: 63 | T36: JOUR | U36: 2 | V36: OUI (TYPE 1) | W36: NON | X36: NON | Y36: NON | Z36: OUI
C37: 2 | D37: MATERNITE | E37: 1 | F37: NON | G37: NON | H37: NON | I37: NON | K37: 42-SAINT-ETIENNE | L37: 69-LYON | M37: 11/11/2025 à 11h00 | N37: 11/11/2025 à 12h15 | O37: AA-001-BB | P37: 42218 (SAINT-ETIENNE) | Q37: 042 | R37: 422 - CPAM DE LA LOIRE | S37: 63 | T37: DIM / J FERIE | U37: 2 | V37: OUI (TYPES 1 & 2 & 3) | W37: NON | X37: NON | Y37: NON | Z37: NON
C38: 3 | D38: MATERNITE | E38: 1 | F38: NON | G38: NON | H38: NON | I38: NON | K38: 69-LYON | L38: 42-SAINT-ETIENNE | M38: 25/12/2025 à 10H00 | N38: 25/12/2025 à 11h15 | O38: EE-003-FF | P38: 69123 (LYON) | Q38: 069 | R38: 691 - CPAM DU RHONE | S38: 63 | T38: DIM / J FERIE | U38: 2 | V38: OUI (TYPE 1) | W38: NON | X38: NON | Y38: OUI | Z38: NON
C39: 4 | D39: MATERNITE | E39: 1 | F39: NON | G39: NON | H39: NON | I39: NON | K39: 42-SAINT-ETIENNE | L39: 69-LYON | M39: 26/12/2025 à 09H00 | N39: 26/12/2025 à 10H15 | O39: AA-001-BB | P39: 42218 (SAINT-ETIENNE) | Q39: 042 | R39: 422 - CPAM DE LA LOIRE | S39: 63 | T39: JOUR | U39: 4 | V39: OUI (TYPE 2) | W39: NON | X39: NON | Y39: NON | Z39: OUI
C40: 5 | D40: MATERNITE | E40: 1 | F40: NON | G40: NON | H40: NON | I40: Sans objet | K40: 69-LYON | L40: 42-SAINT-ETIENNE | M40: 27/12/2025 à 20h00 | N40: 27/12/2025 à 21h15 | O40: EE-003-FF | P40: 69123 (LYON) | Q40: 069 | R40: 691 - CPAM DU RHONE | S40: 63 | T40: NUIT | U40: 1 | V40: OUI (TYPE 1) | W40: NON | X40: NON | Y40: OUI | Z40: Sans objet
A42: CONVENTION CAS 17 | B42: 4 | C42: 1 | D42: MALADIE | E42: 0.55 | F42: NON | G42: NON | H42: OUI | I42: so | J42: 15 - TP AMO & TP AMC | K42: 69-LYON | L42: 42-SAINT-ETIENNE | M42: Samedi 06/12/2025 à 19h00 | N42: Samedi 06/12/2025 à 20h15 | O42: EE-003-FF | P42: 69123 (LYON) | Q42: 069 | R42: 691 - CPAM DU RHONE | S42: 63 | T42: DIM / J FERIE | U42: 1 | V42: NON | W42: NON | X42: NON | Y42: NON | Z42: Sans objet
B43: 4 | C43: 2 | D43: MALADIE | E43: 0.55 | F43: NON | G43: NON | H43: OUI | I43: so | K43: 69-LYON | L43: 42-SAINT-ETIENNE | M43: Samedi 13/12/2025 à 19h30 | N43: Samedi 13/12/2025 à 20h45 | O43: EE-003-FF | P43: 69123 (LYON) | Q43: 069 | R43: 691 - CPAM DU RHONE | S43: 63 | T43: NUIT | U43: 1 | V43: NON | W43: NON | X43: NON | Y43: NON | Z43: Sans objet
B44: 4 | C44: 3 | D44: MALADIE | E44: 0.55 | F44: NON | G44: NON | H44: OUI | I44: so | K44: 69-LYON | L44: 42-SAINT-ETIENNE | M44: Dimanche 21/12/2025 à 7h00 | N44: Dimanche 21/12/2025 à 8h15 | O44: EE-003-FF | P44: 69123 (LYON) | Q44: 069 | R44: 691 - CPAM DU RHONE | S44: 63 | T44: NUIT | U44: 1 | V44: NON | W44: NON | X44: NON | Y44: NON | Z44: Sans objet
B45: 4 | C45: 4 | D45: MALADIE | E45: 0.55 | F45: NON | G45: NON | H45: OUI | I45: so | K45: 69-LYON | L45: 42-SAINT-ETIENNE | M45: Dimanche 28/12/2025 à 7h30 | N45: Dimanche 28/12/2025 à 8h45 | O45: EE-003-FF | P45: 69123 (LYON) | Q45: 069 | R45: 691 - CPAM DU RHONE | S45: 63 | T45: DIM / J FERIE | U45: 1 | V45: NON | W45: NON | X45: NON | Y45: NON | Z45: Sans objet
A47: CONVENTION CAS 18 | B47: 1 | C47: 1 | D47: MALADIE RLAM | E47: 1 | F47: NON | G47: OUI | H47: NON | I47: Sans objet | J47: 05 - TP AMO SEUL | K47: 69-LYON | L47: 42-SAINT-ETIENNE | M47: 01/12/2025 à 10H00 | N47: 01/12/2025 à 11h15 | O47: EE-003-FF | P47: 69123 (LYON) | Q47: 069 | R47: 691 - CPAM DU RHONE | S47: 63 | T47: JOUR | U47: 1 | V47: NON | W47: NON | X47: NON | Y47: NON | Z47: Sans objet
A49: CONVENTION CAS 19 | B49: 1 | C49: 1 | D49: MALADIE | E49: 0 | F49: OUI | G49: NON | H49: NON | I49: Sans objet | J49: 15 - TP AMO & TP AMC | K49: 69-LYON | L49: 42-SAINT-ETIENNE | M49: 01/12/2025 à 10H00 | N49: 01/12/2025 à 11h15 | O49: EE-003-FF | P49: 69123 (LYON) | Q49: 069 | R49: 691 - CPAM DU RHONE | S49: 63 | T49: JOUR | U49: 1 | V49: NON | W49: NON | X49: NON | Y49: NON | Z49: Sans objet
A51: CONVENTION CAS 20 | B51: 5 | C51: 1 | D51: AT / MP | E51: 1 | F51: NON | G51: NON | H51: NON | I51: NON | J51: 05 - TP AMO SEUL | K51: 69-LYON | L51: 42-SAINT-ETIENNE | M51: 10/11/2025 à 10H00 | N51: 10/11/2025 à 11h15 | O51: EE-003-FF | P51: 69123 (LYON) | Q51: 069 | R51: 691 - CPAM DU RHONE | S51: 63 | T51: JOUR | U51: 2 | V51: OUI (TYPE 1) | W51: NON | X51: NON | Y51: NON | Z51: OUI
C52: 2 | D52: AT / MP | E52: 1 | F52: NON | G52: NON | H52: NON | I52: NON | K52: 42-SAINT-ETIENNE | L52: 69-LYON | M52: 11/11/2025 à 11h00 | N52: 11/11/2025 à 12h15 | O52: AA-001-BB | P52: 42218 (SAINT-ETIENNE) | Q52: 042 | R52: 422 - CPAM DE LA LOIRE | S52: 63 | T52: DIM / J FERIE | U52: 2 | V52: OUI (TYPES 1 & 2 & 3) | W52: NON | X52: NON | Y52: NON | Z52: NON
C53: 3 | D53: AT / MP | E53: 1 | F53: NON | G53: NON | H53: NON | I53: NON | K53: 69-LYON | L53: 42-SAINT-ETIENNE | M53: 25/12/2025 à 10H00 | N53: 25/12/2025 à 11h15 | O53: EE-003-FF | P53: 69123 (LYON) | Q53: 069 | R53: 691 - CPAM DU RHONE | S53: 63 | T53: DIM / J FERIE | U53: 2 | V53: OUI (TYPE 1) | W53: NON | X53: NON | Y53: OUI | Z53: NON
C54: 4 | D54: AT / MP | E54: 1 | F54: NON | G54: NON | H54: NON | I54: NON | K54: 42-SAINT-ETIENNE | L54: 69-LYON | M54: 26/12/2025 à 09H00 | N54: 26/12/2025 à 10H15 | O54: AA-001-BB | P54: 42218 (SAINT-ETIENNE) | Q54: 042 | R54: 422 - CPAM DE LA LOIRE | S54: 63 | T54: JOUR | U54: 4 | V54: OUI (TYPE 2) | W54: NON | X54: NON | Y54: NON | Z54: OUI
C55: 5 | D55: AT / MP | E55: 1 | F55: NON | G55: NON | H55: NON | I55: Sans objet | K55: 69-LYON | L55: 42-SAINT-ETIENNE | M55: 27/12/2025 à 20h00 | N55: 27/12/2025 à 21h15 | O55: EE-003-FF | P55: 69123 (LYON) | Q55: 069 | R55: 691 - CPAM DU RHONE | S55: 63 | T55: NUIT | U55: 1 | V55: OUI (TYPE 1) | W55: NON | X55: NON | Y55: OUI | Z55: Sans objet
A57: TP CONTRE TP CAS 1 | B57: 1 | C57: 1 | D57: MALADIE | E57: 0.55 | F57: NON | G57: NON | H57: NON | I57: OUI | J57: 00 - HTP | K57: 69-LYON | L57: 42-SAINT-ETIENNE | M57: 01/12/2025 à 10H00 | N57: 01/12/2025 à 11H15 | O57: EE-003-FF | P57: 69123 (LYON) | Q57: 069 | R57: 691 - CPAM DU RHONE | S57: 63 | T57: JOUR | U57: 1 | V57: NON | W57: NON | X57: NON | Y57: NON | Z57: Sans objet
A59: TP CONTRE TP CAS 2 | B59: 1 | C59: 1 | D59: MALADIE | E59: 0.55 | F59: NON | G59: NON | H59: NON | I59: OUI | J59: 00 - HTP | K59: 42-SAINT-ETIENNE | L59: 69-LYON | M59: 01/12/2025 à 20H00 | N59: 01/12/2025 à 21H15 | O59: AA-001-BB | P59: 42218 (SAINT-ETIENNE) | Q59: 042 | R59: 422 - CPAM DE LA LOIRE | S59: 63 | T59: NUIT | U59: 1 | V59: OUI (TYPE 1) | W59: NON | X59: OUI | Y59: OUI | Z59: Sans objet
A61: TP CONTRE TP CAS 3 | B61: 2 | C61: 1 | D61: MALADIE | E61: 0.55 | F61: NON | G61: NON | H61: NON | I61: OUI | J61: 00 - HTP | K61: 69-LYON | L61: 42-SAINT-ETIENNE | M61: 10/11/2025 à 20H00 | N61: 10/11/2025 à 21H15 | O61: EE-003-FF | P61: 69123 (LYON) | Q61: 069 | R61: 691 - CPAM DU RHONE | S61: 63 | T61: NUIT | U61: 1 | V61: OUI (TYPE 1) | W61: NON | X61: OUI | Y61: OUI | Z61: Sans objet
C62: 2 | D62: MALADIE | E62: 0.55 | F62: NON | G62: NON | H62: NON | I62: OUI | J62: 00 - HTP | K62: 69-LYON | L62: 42-SAINT-ETIENNE | M62: 11/11/2025 à 16H00 | N62: 11/11/2025 à 17H15 | O62: EE-003-FF | P62: 69123 (LYON) | Q62: 069 | R62: 691 - CPAM DU RHONE | S62: 63 | T62: DIM / J FERIE | U62: 1 | V62: NON | W62: NON | X62: OUI | Y62: NON | Z62: Sans objet
A64: TP CONTRE TP CAS 4 | B64: 1 | C64: 1 | D64: MALADIE | E64: 0.55 | F64: NON | G64: NON | H64: NON | I64: NON | J64: 00 - HTP | K64: 42-SAINT-ETIENNE | L64: 69-LYON | M64: 01/12/2025 à 10H00 | N64: 01/12/2025 à 11H15 | O64: AA-001-BB | P64: 42218 (SAINT-ETIENNE) | Q64: 042 | R64: 422 - CPAM DE LA LOIRE | S64: 63 | T64: JOUR | U64: 1 | V64: NON | W64: NON | X64: NON | Y64: NON | Z64: Sans objet

Sheet CONVENTION CAS 1
A1: Table des matières | B1: CARACTERISTIQUES METIERS DU OU DES TRAJETS FACTURES
A3: SOCIETE DE TAXI DE N° AM : 422500009 SPECIALITE : 56 | D3: CARACTERISTIQUE PATIENT | G3: CARACTERISTIQUES FACTURE | I3: CARACTERISTIQUES TRAJETS | Z3: ASSURE | AG3: PRESCRIPTEUR
A4: N°CAS | B4: NOMBRE DE TRAJETS FACTURES | C4: TRAJET N° : | D4: NATURE D'ASSURANCE | E4: TAUX | F4: C2S ? : O/N | G4: REFUS TRANSPORT PARTAGE | H4: TIERS PAYANT | I4: LIEU DEPART | J4: LIEU ARRIVEE | K4: DATE / HEURE DEPART | L4: DATE / HEURE ARRIVEE | M4: N° IMMATRICULATION VEHICULE | N4: COMMUNE D'ADS | O4: DEPARTEMENT D'ADS | P4: ORGANISME LOCAL D'ADS | Q4: DISTANCE PARCOURUE | R4: CONTEXTE : J, N , F | S4: NOMBRE DE MALADES | T4: SUPPLEMENT FORFAITAIRE ? : O / N | U4: PEAGES ? : O / N | V4: TPMR ? : O / N | W4: TRAJET EN LIEN AVEC HOSPITALISATION ET RETOUR A VIDE ? : O/N | X4: SI T PARTAGE : TRAJET SEUL > X KM ? : O/N | Z4: NIR | AA4: DATE DE NAISSANCE | AB4: RANG | AC4: REGIME | AD4: CAISSE | AE4: CENTRE | AG4: N°AM | AH4: SPECIALITE | AI4: NN°RPPS
A5: ='LISTE DES CAS ANNEXE 30'!A3 -> CONVENTION CAS 1 | B5: ='LISTE DES CAS ANNEXE 30'!B3 -> 1 | C5: ='LISTE DES CAS ANNEXE 30'!C3 -> 1 | D5: ='LISTE DES CAS ANNEXE 30'!D3 -> MALADIE | E5: ='LISTE DES CAS ANNEXE 30'!E3 -> 0.55 | F5: ='LISTE DES CAS ANNEXE 30'!H3 -> NON | G5: ='LISTE DES CAS ANNEXE 30'!I3 -> Sans objet | H5: ='LISTE DES CAS ANNEXE 30'!J3 -> 05 - TP AMO SEUL | I5: ='LISTE DES CAS ANNEXE 30'!K3 -> 42-SAINT-ETIENNE | J5: ='LISTE DES CAS ANNEXE 30'!L3 -> 42-SAINT-ETIENNE | K5: ='LISTE DES CAS ANNEXE 30'!M3 -> 01/12/2025 à 10H00 | L5: ='LISTE DES CAS ANNEXE 30'!N3 -> 01/12/2025 à 10H11 | M5: ='LISTE DES CAS ANNEXE 30'!O3 -> AA-001-BB | ... X5: ='LISTE DES CAS ANNEXE 30'!Z3 -> Sans objet | Z5: 1500101001001 | AA5: 500101 | AB5: 1 | AC5: 01 | AD5: 422 | AE5: 0000 | AG5: 421000001 | AH5: 01 | AI5: 11111110118
A7: FACTURE B2 CORRESPONDANT
A9: TYPE 000 DEBUT FICHIER | B9: Type d’enregistrement | C9: Type d’émetteur | D9: Numéro d’émetteur | E9: FILLER | F9: Type de destinataire | G9: N° de destinataire | H9: Date de réception du flux sur le frontal | I9: Application | J9: Identification du fichier | K9: Date de création du fichier | L9: Norme | M9: Version de Norme | N9: FILLER | O9: FILLER | P9: FILLER | Q9: FILLER | R9: Longueur d’enregistrement | S9: FILLER | T9: Zone message
B10: 1-3 | C10: 4-5 | D10: 6-19 | E10: 20-25 | F10: 26-27 | G10: 28-41 | H10: 42-47 | I10: 48-49 | J10: 50-55 | K10: 56-61 | L10: 62-65 | M10: 66-67 | N10: 68 | O10: 69 | P10: 70-72 | Q10: 73-82 | R10: 83-85 | S10: 86-91 | T10: 92-128
B11: 3 | C11: 2 | D11: 14 | E11: 6 | F11: 2 | G11: 14 | H11: 6 | I11: 2 | J11: 6 | K11: 6 | L11: 4 | M11: 2 | N11: 1 | O11: 1 | P11: 3 | Q11: 10 | R11: 3 | S11: 6 | T11: 37
B12: N | C12: A | D12: N | E12: A | F12: A | G12: N | H12: A | I12: A | J12: A | K12: N | L12: A | M12: A | N12: A | O12: A | P12: A | Q12: A | R12: N | S12: A | T12: N
B13: O | C13: O | D13: O | E13: F | F13: O | G13: O | H13: O | I13: O | J13: O | K13: O | L13: O | M13: O | N13: F | O13: F | P13: F | Q13: F | R13: F | S13: F | T13: O
B14: 000 | C14: TP | D14: 00000422500009 | F14: CT | G14: 00000001000422 | H14: 251231 | I14: TR | J14: TESTB2 | K14: 251231 | L14: TA | M14: B2 | R14: 128
A16: TYPE 1 DEBUT LOT | B16: Type d’enregistrement | C16: N° partenaire de santé + clé | D16: Origine du fichier | E16: N° d’organisme destinataire | F16: N° de lot | G16: Catégorie | H16: Statut juridique | I16: Mode de fixation des tarifs | J16: Nom ou raison sociale du partenaire de santé | K16: Version de norme utilisée | L16: Date de création du lot | M16: Filler | N16: Code norme | O16: Top certification du lot | P16: Numéro de version de norme | Q16: Unité monétaire de facturation | R16: Grand régime de la caisse pivot ou de la caisse de paiement unique privés, ou pour les établissements publics et privés antérieurement sous DG | S16: N° de la caisse pivot ou de la caisse de paiement unique | T16: Indication de dispositif Caisse Centralisatrice des Paiements ou de dispositif Caisse de Paiement Unique | U16: FILLER
B17: 1 | C17: 2-10 | D17: 11-16 | E17: 17-19 | F17: 20-22 | G17: 23-25 | H17: 26-27 | I17: 28-29 | J17: 30-69 | K17: 70-71 | L17: 72-77 | M17: 78 | N17: 79-80 | O17: 81 | P17: 82-87 | Q17: 88 | R17: 89-90 | S17: 91-93 | T17: 94 | U17: 95-128
B18: 1 | C18: 9 | D18: 6 | E18: 3 | F18: 3 | G18: 3 | H18: 2 | I18: 2 | J18: 40 | K18: 2 | L18: 6 | M18: 1 | N18: 2 | O18: 1 | P18: 6 | Q18: 1 | R18: 2 | S18: 3 | T18: 1 | U18: 34
B19: N | C19: N | D19: A | E19: N | F19: N | G19: A | H19: A | I19: A | J19: A | K19: A | L19: N | M19: A | N19: A | O19: A | P19: N | Q19: A | R19: A | S19: A | T19: N | U19: A
B20: O | C20: O | D20: F | E20: O | F20: O | G20: F | H20: F | I20: F | J20: O | K20: O | L20: O | M20: F | N20: O | O20: F | P20: O | Q20: F | R20: F | S20: F | T20: F | U20: FILLER
B21: 1 | C21: 422500009 | E21: 422 | F21: 001 | J21: SIMULATEUR B2 NOUVELLE CONVENTION TAXI | K21: B2 | L21: 251231 | N21: TA | P21: 062007 | Q21: U
A23: TYPE 2 DEBUT FACTURE | B23: Type d’enregistrement | C23: N° partenaire de santé + clé | D23: FILLER | E23: N° immatriculation assuré | F23: Clé N° immatriculation | G23: N° facture | H23: Complément du type | I23: Marquage de la facture | J23: Indicateur de forçage de la tarification de la part AMO | K23: Nature d’opération | L23: Date de facturation | M23: Top éclatement des flux par le PS | N23: Type de facture | O23: Facture sécurisée sur un dispositif portable | P23: Code Grand Régime | Q23: N° Caisse gestionnaire | R23: N° Centre gestionnaire | S23: Nature de la pièce justificative des droits | T23: N° prescripteur + clé | U23: Date de prescription | V23: Régime de prestation de l’assuré | W23: Nature d’assurance | X23: Justification d’exonération ou de modulation du ticket modérateur | Y23: Date Maternité | Z23: Numéro accident du travail ou date d’accident de droit commun | AA23: Présence d’une CPS de remplaçant pour sécurisation de la facture | AB23: Date de naissance du bénéficiaire | AC23: Rang de naissance | AD23: Rang de bénéficiaire | AE23: N° d’adhérent | AF23: Spécialité de prescripteur | AG23: Destinataire du règlement | AH23: Type de contrat souscrit auprès d’un organisme complémentaire | AI23: N° d’organisme complémentaire
B24: 1 | C24: 2-10 | D24: 11 | E24: 12-24 | F24: 25-26 | G24: 27-35 | H24: 36 | I24: 37 | J24: 38 | K24: 39 | L24: 40-45 | M24: 46 | N24: 47 | O24: 48 | P24: 49-50 | Q24: 51-53 | R24: 54-57 | S24: 58 | T24: 59-67 | U24: 68-73 | V24: 74-76 | W24: 77-78 | X24: 79 | Y24: 80-85 | Z24: 86-94 | AA24: 95 | AB24: 96-101 | AC24: 102 | AD24: 103-104 | AE24: 105-112 | AF24: 113-114 | AG24: 115-116 | AH24: 117-118 | AI24: 119-128
B25: 1 | C25: 9 | D25: 1 | E25: 13 | F25: 2 | G25: 9 | H25: 1 | I25: 1 | J25: 1 | K25: 1 | L25: 6 | M25: 1 | N25: 1 | O25: 1 | P25: 2 | Q25: 3 | R25: 4 | S25: 1 | T25: 9 | U25: 6 | V25: 3 | W25: 2 | X25: 1 | Y25: 6 | Z25: 9 | AA25: 1 | AB25: 6 | AC25: 1 | AD25: 2 | AE25: 8 | AF25: 2 | AG25: 2 | AH25: 2 | AI25: 10
B26: N | C26: N | D26: A | E26: A | F26: N | G26: N | H26: A | I26: A | J26: A | K26: N | L26: N | M26: A | N26: A | O26: A | P26: N | Q26: N | R26: N | S26: N | T26: N | U26: N | V26: A | W26: N | X26: A | Y26: N | Z26: N | AA26: A | AB26: N | AC26: N | AD26: A | AE26: A | AF26: N | AG26: N | AH26: N | AI26: A
B27: O | C27: O | D27: F | E27: O | F27: O | G27: O | H27: F | I27: F | J27: F | K27: O | L27: O | M27: F | N27: F | O27: F | P27: O | Q27: O | R27: O | S27: O | T27: O | U27: O | V27: F | W27: F | X27: O | Y27: F | Z27: F | AA27: O | AB27: O | AC27: F | AD27: F | AE27: F | AF27: F | AG27: F | AH27: F | AI27: F
B28: 2 | C28: 422500009 | E28: 1500101001001 | F28: 77 | G28: 250000001 | H28: A | K28: 1 | L28: 251231 | P28: 01 | Q28: 422 | R28: 0000 | S28: 2 | T28: 421000001 | U28: 250701 | W28: 10 | X28: 0 | Y28: 000000 | Z28: 000000000 | AB28: 500101 | AC28: 1 | AF28: 01 | AG28: 05 | AH28: 00
A30: TYPE 2E RPPS PRESCRIPTEUR | B30: Type d’enregistrement | C30: N° partenaire de santé + clé | D30: FILLER | E30: N° immatriculation assuré | F30: Clé N° immatriculation | G30: N° de facture | H30: Complément de type | I30: Identfifiant RPPS du prescripteur | J30: N° de la structure dans laquelle le PS a exécuté l’acte | K30: FILLER
B31: 1 | C31: 2-10 | D31: 11 | E31: 12-24 | F31: 25-26 | G31: 27-35 | H31: 36 | I31: 37-47 | J31: 48-61 | K31: 62-128
B32: 1 | C32: 9 | D32: 1 | E32: 13 | F32: 2 | G32: 9 | H32: 1 | I32: 11 | J32: 14 | K32: 67
B33: N | C33: N | D33: A | E33: A | F33: N | G33: N | H33: A | I33: N | J33: N | K33: A
B34: O | C34: O | D34: F | E34: O | F34: O | G34: O | H34: F | I34: F | J34: F | K34: F
B35: 2 | C35: 422500009 | E35: 1500101001001 | F35: 77 | G35: 250000001 | H35: E | I35: 11111110118 | AG35: LIGNE A GENERER
A37: TYPE 4A COMPOSANTE FORFAIT | B37: Type d’enregistrement | C37: N° partenaire de santé + clé | D37: FILLER | E37: N° immatriculation assuré | F37: Clé N° immatriculation | G37: N° de facture | H37: Complément de type | I37: Séquence | J37: Mode de traitement | K37: Discipline de prestations (ex DMT) | L37: Date de la demande d’accord préalable ou date d’accord de prise en charge CMU. | M37: Code accord préalable | N37: Séquence de renouvellement | O37: Code Participation assuré | P37: Justification d’exonération du Ticket Modérateur au niveau de l’acte | Q37: N° exécutant + clé ayant effectué l’acte ou fourni le produit | R37: Zone tarif de l’exécutant | S37: Spécialité de l’exécutant | T37: Date de l’acte, de la délivrance du produit | U37: Code acte | V37: Quantité d'actes | W37: Coefficient | X37: Dénombrement | Y37: Prix unitaire | Z37: Base de remboursement | AA37: Taux applicable à la prestation- | AB37: Montant remboursable par l’organisme d’Assurance Maladie Obligatoire | AC37: Montant des honoraires ou de la dépense (dépassement compris ou après remise pour la norme FR) | AD37: Qualificatif de la dépense | AE37: Code lieu | AF37: Montant remboursable par l’organisme complémentaire
B38: 1 | C38: 2-10 | D38: 11 | E38: 12-24 | F38: 25-26 | G38: 27-35 | H38: 36 | I38: 37-38 | J38: 39-40 | K38: 41-43 | L38: 44-49 | M38: 50 | N38: 51-52 | O38: 53 | P38: 54 | Q38: 55-63 | R38: 64-65 | S38: 66-67 | T38: 68-73 | U38: 74-78 | V38: 79-80 | W38: 81-86 | X38: 87-88 | Y38: 89-95 | Z38: 96-102 | AA38: 103-105 | AB38: 106-112 | AC38: 113-119 | AD38: 120 | AE38: 121 | AF38: 122-128
B39: 1 | C39: 9 | D39: 1 | E39: 13 | F39: 2 | G39: 9 | H39: 1 | I39: 2 | J39: 2 | K39: 3 | L39: 6 | M39: 1 | N39: 2 | O39: 1 | P39: 1 | Q39: 9 | R39: 2 | S39: 2 | T39: 6 | U39: 5 | V39: 2 | W39: 6 | X39: 2 | Y39: 7 | Z39: 7 | AA39: 3 | AB39: 7 | AC39: 7 | AD39: 1 | AE39: 1 | AF39: 7
B40: N | C40: N | D40: A | E40: A | F40: N | G40: N | H40: A | I40: N | J40: N | K40: N | L40: N | M40: N | N40: A | O40: A | P40: A | Q40: N | R40: N | S40: N | T40: N | U40: A | V40: N | W40: N | X40: N | Y40: N | Z40: N | AA40: N | AB40: N | AC40: N | AD40: A | AE40: N | AF40: N
B41: O | C41: O | D41: F | E41: O | F41: O | G41: O | H41: F | I41: F | J41: F | K41: F | L41: F | M41: O | N41: F | O41: F | P41: F | Q41: F | R41: F | S41: OSIMO | T41: O | U41: O | V41: O | W41: O | X41: O | Y41: O | Z41: O | AA41: O | AB41: O | AC41: O | AD41: F | AE41: F | AF41: F
B42: 4 | C42: 422500009 | E42: 1500101001001 | F42: 77 | G42: 250000001 | H42: A | I42: 00 | J42: 00 | K42: 000 | L42: 000000 | M42: 9 | Q42: 422500009 | R42: 00 | S42: 00 | T42: 251201 | U42: FX1 | V42: 01 | W42: 000100 | X42: 01 | Y42: 0001300 | Z42: 0001300 | AA42: 055 | AB42: 0000715 | AC42: 0001300 | AE42: 1 | AF42: 0000000 | AG42: LIGNE A GENERER
A44: TYPE 4T | B44: Type d’enregistrement | C44: N° partenaire de santé + clé | D44: FILLER | E44: N° immatriculation assuré | F44: Clé N° immatriculation | G44: N° de facture | H44: Complément du type | I44: Séquence | J44: Filler | K44: Série (au sens du décret du 6/5/88) | L44: Transport lié à une hospitalisation | M44: Longue distance | N44: Filler | O44: Forfait type de forfait | P44: Prix unitaire du forfait non majoré | Q44: Quantité forfaits | R44: Quantité forfaits majoration de nuit | S44: Quantité forfaits majoration dimanche ou fériés | T44: Prix unitaire du kilomètre non réduit. | U44: SANS MAJORATION : Quantité <ou=150 km | V44: Quantité >150 km | W44: MAJORATION NUIT : Quantité <ou=150 km | X44: Quantité >150 km | Y44: MAJORATION DIMANCHE/FERIE : Quantité <ou=150 km | Z44: Quantité >150 km | AA44: SUPPLEMENT : Type supplément | AB44: Quantité | AC44: Montant | AD44: PEAGES ET VOIES D'EAU Quantité | AE44: Montant | AF44: Montant global des abattements | AG44: Montant global des majorations pour courte distance | AH44: Filler
B45: 1 | C45: 2-10 | D45: 11 | E45: 12-24 | F45: 25-26 | G45: 27-35 | H45: 36 | I45: 37-38 | J45: 39-45 | K45: 46 | L45: 47 | M45: 48 | N45: 49 | O45: 50 | P45: 51-56 | Q45: 57-58 | R45: 59-60 | S45: 61-62 | T45: 63-68 | U45: 69-72 | V45: 73-76 | W45: 77-80 | X45: 81-84 | Y45: 85-88 | Z45: 89-92 | AA45: 93 | AB45: 94-95 | AC45: 96-101 | AD45: 102-103, | AE45: 104-109 | AF45: 110-116 | AG45: 117-123 | AH45: 142-128
B46: 1 | C46: 9 | D46: 1 | E46: 13 | F46: 2 | G46: 9 | H46: 1 | I46: 2 | J46: 7 | K46: 1 | L46: 1 | M46: 1 | N46: 1 | O46: 1 | P46: 6 | Q46: 2 | R46: 2 | S46: 2 | T46: 6 | U46: 4 | V46: 4 | W46: 4 | X46: 4 | Y46: 4 | Z46: 4 | AA46: 1 | AB46: 2 | AC46: 6 | AD46: 2 | AE46: 6 | AF46: 7 | AG46: 7 | AH46: 5
B47: N | C47: N | D47: A | E47: A | F47: N | G47: N | H47: A | I47: N | J47: A | K47: N | L47: N | M47: N | N47: A | O47: N | P47: N | Q47: N | R47: N | S47: N | T47: N | U47: N | V47: N | W47: N | X47: N | Y47: N | Z47: N | AA47: N | AB47: N | AC47: N | AD47: N | AE47: N | AF47: N | AG47: N | AH47: A
B48: O | C48: O | D48: F | E48: O | F48: O | G48: O | H48: O | I48: F | J48: F | K48: O | L48: O | M48: O | N48: F | O48: O | P48: F | Q48: F | R48: F | S48: F | T48: F | U48: F | V48: F | W48: F | X48: F | Y48: F | Z48: F | AA48: F | AB48: F | AC48: F | AD48: F | AE48: F | AF48: F | AG48: F | AH48: F
B49: 4 | C49: 422500009 | E49: 1500101001001 | F49: 77 | G49: 250000001 | H49: T | I49: 01 | K49: 0 | L49: 0 | M49: 0 | O49: 0 | P49: 000000 | Q49: 00 | R49: 00 | S49: 00 | T49: 000000 | U49: 0000 | V49: 0000 | W49: 0000 | X49: 0000 | Y49: 0000 | Z49: 0000 | AA49: 0 | AB49: 00 | AC49: 000000 | AD49: 00 | AE49: 000000 | AF49: 0000000 | AG49: 0000000
A51: TYPE 4U | B51: Type d’enregistrement | C51: N° partenaire de santé + clé | D51: FILLER | E51: N° immatriculation assuré | F51: Clé N° immatriculation | G51: N° de facture | H51: Complément du type | I51: Séquence | J51: Date départ | K51: Heure départ | L51: Lieu départ département commune | M51: N° véhicule | N51: Nom conducteur | O51: Prénom conducteur | P51: Nom accompagnateur | Q51: Prénom accompagnateur | R51: Date arrivée | S51: Heure arrivée | T51: Lieu d’arrivée | U51: Nombre malades | V51: % abattement | W51: Montant abattement | X51: Nombre de km facturés | Y51: Distance réelle parcourue | Z51: Utilisation du distancier | AA51: Niveau de certification | AB51: Montant de la majoration pour courte distance | AC51: Indicateur de période de réalisation du trajet | AD51: Filler
B52: 1 | C52: 2-10 | D52: 11 | E52: 12-24 | F52: 25-26 | G52: 27-35 | H52: 36 | I52: 37-38 | J52: 39-44 | K52: 45-48 | L52: 49-53 | M52: 54-62 | N52: 63-70 | O52: 71-73 | P52: 74-81 | Q52: 82-84 | R52: 85-90 | S52: 91-94 | T52: 95-99 | U52: 100 | V52: 101-102 | W52: 103-108 | X52: 109-112 | Y52: 113-116 | Z52: 117 | AA52: 118 | AB52: 119-124 | AC52: 125 | AD52: 126-128
B53: 1 | C53: 9 | D53: 1 | E53: 13 | F53: 2 | G53: 9 | H53: 1 | I53: 2 | J53: 6 | K53: 4 | L53: 5 | M53: 9 | N53: 8 | O53: 3 | P53: 8 | Q53: 3 | R53: 6 | S53: 4 | T53: 5 | U53: 1 | V53: 2 | W53: 6 | X53: 4 | Y53: 4 | Z53: 1 | AA53: 1 | AB53: 6 | AC53: 1 | AD53: 3
B54: N | C54: N | D54: A | E54: A | F54: N | G54: N | H54: A | I54: N | J54: N | K54: N | L54: N | M54: A | N54: A | O54: A | P54: A | Q54: A | R54: N | S54: N | T54: N | U54: N | V54: N | W54: N | X54: N | Y54: N | Z54: A | AA54: A | AB54: N | AC54: A | AD54: A
B55: O | C55: O | D55: F | E55: O | F55: O | G55: O | H55: O | I55: O | J55: O | K55: P | L55: O | M55: O | N55: O | O55: O | P55: F | Q55: F | R55: O | S55: O | T55: O | U55: O | V55: F | W55: F | X55: F | Y55: O | Z55: F | AA55: F | AB55: F | AC55: F | AD55: F
B56: 4 | C56: 422500009 | E56: 1500101001001 | F56: 77 | G56: 250000001 | H56: U | I56: 01 | J56: 251201 | K56: 1000 | L56: 42218 | M56: AA-001-BB | N56: NCONDUCA | O56: PRA | R56: 251201 | S56: 1011 | T56: 42218 | U56: 1 | V56: 00 | W56: 000000 | X56: 0000 | Y56: 0003 | AB56: 000000 | AE56: LIGNE A GENERER
A58: TYPE 5 FIN FACTURE | B58: Type d’enregistrement | C58: N° partenaire de santé + clé | D58: FILLER | E58: N° immatriculation assuré | F58: Clé N° immatriculation | G58: N° de facture | H58: FILLER | I58: Nombre d’enregistrements de Type 4 | J58: Zone réservée SESAM | K58: Total des montants facturés | L58: Total remboursable par la Caisse | M58: Total participation assuré avant participation de l’organisme complémentaire | N58: Total remboursable par l’organisme complémentaire | O58: Top éclatement des flux par l’OCT | P58: Zone réservée SESAM | Q58: Liste d’opposition | R58: FILLER | S58: Zone de certification
B59: 1 | C59: 2-10 | D59: 11 | E59: 12-24 | F59: 25-26 | G59: 27-35 | H59: 36-38 | I59: 39-41 | J59: 42-57 | K59: 58-65 | L59: 66-73 | M59: 74-81 | N59: 82-89 | O59: 90 | P59: 91-93 | Q59: 94 | R59: 95-96 | S59: 97-128
B60: 1 | C60: 9 | D60: 1 | E60: 13 | F60: 2 | G60: 9 | H60: 3 | I60: 3 | J60: 16 | K60: 8 | L60: 8 | M60: 8 | N60: 8 | O60: 1 | P60: 3 | Q60: 1 | R60: 2 | S60: 32
B61: N | C61: N | D61: A | E61: A | F61: N | G61: N | H61: A | I61: N | J61: A | K61: N | L61: N | M61: N | N61: N | O61: A | P61: A | Q61: A | R61: A | S61: A
B62: O | C62: O | D62: F | E62: O | F62: O | G62: O | H62: F | I62: O | J62: O | K62: O | L62: O | M62: O | N62: F | O62: F | P62: O | Q62: O | R62: F | S62: F
B63: 5 | C63: 422500009 | E63: 1500101001001 | F63: 77 | G63: 250000001 | I63: 003 | K63: 00001300 | L63: 00000715 | M63: 00000585 | N63: 00000000
A65: TYPE 6 FIN LOT | B65: Type d’enregistrement | C65: N° partenaire de santé + clé | D65: Nombre de factures | E65: Nombre de lignes actes | F65: Comptabilisation des enregistrements des types 2 | G65: Total de tous les enregistrements de type 5 | H65: Montant total général du lot prestations facturées | I65: Montant total général du lot prestations remboursables par l’organisme d’Ass. Maladie | J65: Montant total général du lot prestations remboursables par les organismes complémentaires | K65: N° de lot | L65: indicateur de marquage des factures du lot. | M65: Type de facture | N65: FILLER | O65: N° agrément progiciel de santé ou n° de certificat pour les logiciels établissements ou raison sociale éditeur | P65: N° agrément du dispositif portable | Q65: FILLER | R65: N° d’identification du PS remplaçant | S65: Zone de certification
B66: 1 | C66: 2-10 | D66: 11-13 | E66: 14-17 | F66: 18-21 | G66: 22-24 | H66: 25-33 | I66: 34-42 | J66: 43-51 | K66: 52-54 | L66: 55 | M66: 56 | N66: 57-60 | O66: 61-72 | P66: 73-84 | Q66: 85-87 | R66: 88-96 | S66: 97-128
B67: 1 | C67: 9 | D67: 3 | E67: 4 | F67: 4 | G67: 3 | H67: 9 | I67: 9 | J67: 9 | K67: 3 | L67: 1 | M67: 1 | N67: 4 | O67: 12 | P67: 12 | Q67: 3 | R67: 9 | S67: 32
B68: N | C68: N | D68: N | E68: N | F68: N | G68: N | H68: N | I68: N | J68: N | K68: N | L68: A | M68: A | N68: A | O68: A | P68: N | Q68: A | R68: N | S68: N
B69: O | C69: O | D69: O | E69: O | F69: O | G69: O | H69: O | I69: O | J69: O | K69: O | L69: F | M69: F | N69: F | O69: F | P69: F | Q69: F | R69: F | S69: O
B70: 6 | C70: 422500009 | D70: 001 | E70: 0001 | F70: 0002 | G70: 001 | H70: 000001300 | I70: 000000715 | J70: 000000000 | K70: 001 | O70: AAZZ2501BC12
A72: TYPE 999 FIN FICHIER | B72: Type d’enregistrement | C72: Type émetteur | D72: Numéro émetteur | E72: FILLER | F72: Type de destinataire | G72: Numéro de destinataire | H72: FILLER | I72: Application | J72: Identification du fichier | K72: Volume du fichier | L72: FILLER | M72: Nombre de lots | N72: FILLER
B73: 1-3 | C73: 4-5 | D73: 6-19 | E73: 20-25 | F73: 26-27 | G73: 28-41 | H73: 42-47 | I73: 48-49 | J73: 50-55 | K73: 56-63 | L73: 64-82 | M73: 83-85 | N73: 86-128
B74: 3 | C74: 2 | D74: 14 | E74: 6 | F74: 2 | G74: 14 | H74: 6 | I74: 2 | J74: 6 | K74: 8 | L74: 19 | M74: 3 | N74: 43
B75: N | C75: A | D75: N | E75: A | F75: A | G75: N | H75: A | I75: A | J75: A | K75: N | L75: A | M75: N | N75: A
B76: O | C76: O | D76: O | E76: F | F76: O | G76: O | H76: F | I76: O | J76: O | K76: O | L76: F | M76: O | N76: F
B77: 999 | C77: TP | D77: 00000422500009 | F77: CT | G77: 00000001000422 | I77: TR | J77: TESTB2 | K77: 00000010 | M77: 001

Sheet CONVENTION CAS 2
A1: Table des matières | B1: CARACTERISTIQUES METIERS DU OU DES TRAJETS FACTURES
A3: SOCIETE DE TAXI DE N° AM : 422500009 SPECIALITE : 56 | D3: CARACTERISTIQUE PATIENT | G3: CARACTERISTIQUES FACTURE | I3: CARACTERISTIQUES TRAJETS | Z3: ASSURE | AG3: PRESCRIPTEUR
A4: N°CAS | B4: NOMBRE DE TRAJETS FACTURES | C4: TRAJET N° : | D4: NATURE D'ASSURANCE | E4: TAUX | F4: C2S ? : O/N | G4: REFUS TRANSPORT PARTAGE | H4: TIERS PAYANT | I4: LIEU DEPART | J4: LIEU ARRIVEE | K4: DATE / HEURE DEPART | L4: DATE / HEURE ARRIVEE | M4: N° IMMATRICULATION VEHICULE | N4: COMMUNE D'ADS | O4: DEPARTEMENT D'ADS | P4: ORGANISME LOCAL D'ADS | Q4: DISTANCE PARCOURUE | R4: CONTEXTE : J, N , F | S4: NOMBRE DE MALADES | T4: SUPPLEMENT FORFAITAIRE ? : O / N | U4: PEAGES ? : O / N | V4: TPMR ? : O / N | W4: TRAJET EN LIEN AVEC HOSPITALISATION ET RETOUR A VIDE ? : O/N | X4: SI T PARTAGE : TRAJET SEUL > X KM ? : O/N | Z4: NIR | AA4: DATE DE NAISSANCE | AB4: RANG | AC4: REGIME | AD4: CAISSE | AE4: CENTRE | AG4: N°AM | AH4: SPECIALITE | AI4: NN°RPPS
A5: ='LISTE DES CAS ANNEXE 30'!A5 -> CONVENTION CAS 2 | B5: ='LISTE DES CAS ANNEXE 30'!B5 -> 1 | C5: ='LISTE DES CAS ANNEXE 30'!C5 -> 1 | D5: ='LISTE DES CAS ANNEXE 30'!D5 -> MALADIE | E5: ='LISTE DES CAS ANNEXE 30'!E5 -> 0.55 | F5: ='LISTE DES CAS ANNEXE 30'!H5 -> NON | G5: ='LISTE DES CAS ANNEXE 30'!I5 -> Sans objet | H5: ='LISTE DES CAS ANNEXE 30'!J5 -> 05 - TP AMO SEUL | I5: ='LISTE DES CAS ANNEXE 30'!K5 -> 69-LYON | J5: ='LISTE DES CAS ANNEXE 30'!L5 -> 69-VILLEURBANNE | K5: ='LISTE DES CAS ANNEXE 30'!M5 -> 01/12/2025 à 10H00 | L5: ='LISTE DES CAS ANNEXE 30'!N5 -> 01/12/2025 à 10H11 | M5: ='LISTE DES CAS ANNEXE 30'!O5 -> EE-003-FF | ... X5: ='LISTE DES CAS ANNEXE 30'!Z5 -> Sans objet | Z5: 1500101001001 | AA5: 500101 | AB5: 1 | AC5: 01 | AD5: 422 | AE5: 0000 | AG5: 421000001 | AH5: 01 | AI5: 11111110118
A7: FACTURE B2 CORRESPONDANT
A9: TYPE 000 DEBUT FICHIER | B9: Type d’enregistrement | C9: Type d’émetteur | D9: Numéro d’émetteur | E9: FILLER | F9: Type de destinataire | G9: N° de destinataire | H9: Date de réception du flux sur le frontal | I9: Application | J9: Identification du fichier | K9: Date de création du fichier | L9: Norme | M9: Version de Norme | N9: FILLER | O9: FILLER | P9: FILLER | Q9: FILLER | R9: Longueur d’enregistrement | S9: FILLER | T9: Zone message
B10: 1-3 | C10: 4-5 | D10: 6-19 | E10: 20-25 | F10: 26-27 | G10: 28-41 | H10: 42-47 | I10: 48-49 | J10: 50-55 | K10: 56-61 | L10: 62-65 | M10: 66-67 | N10: 68 | O10: 69 | P10: 70-72 | Q10: 73-82 | R10: 83-85 | S10: 86-91 | T10: 92-128
B11: 3 | C11: 2 | D11: 14 | E11: 6 | F11: 2 | G11: 14 | H11: 6 | I11: 2 | J11: 6 | K11: 6 | L11: 4 | M11: 2 | N11: 1 | O11: 1 | P11: 3 | Q11: 10 | R11: 3 | S11: 6 | T11: 37
B12: N | C12: A | D12: N | E12: A | F12: A | G12: N | H12: A | I12: A | J12: A | K12: N | L12: A | M12: A | N12: A | O12: A | P12: A | Q12: A | R12: N | S12: A | T12: N
B13: O | C13: O | D13: O | E13: F | F13: O | G13: O | H13: O | I13: O | J13: O | K13: O | L13: O | M13: O | N13: F | O13: F | P13: F | Q13: F | R13: F | S13: F | T13: O
B14: 000 | C14: TP | D14: 00000422500009 | F14: CT | G14: 00000001000422 | H14: 251231 | I14: TR | J14: TESTB2 | K14: 251231 | L14: TA | M14: B2 | R14: 128
A16: TYPE 1 DEBUT LOT | B16: Type d’enregistrement | C16: N° partenaire de santé + clé | D16: Origine du fichier | E16: N° d’organisme destinataire | F16: N° de lot | G16: Catégorie | H16: Statut juridique | I16: Mode de fixation des tarifs | J16: Nom ou raison sociale du partenaire de santé | K16: Version de norme utilisée | L16: Date de création du lot | M16: Filler | N16: Code norme | O16: Top certification du lot | P16: Numéro de version de norme | Q16: Unité monétaire de facturation | R16: Grand régime de la caisse pivot ou de la caisse de paiement unique privés, ou pour les établissements publics et privés antérieurement sous DG | S16: N° de la caisse pivot ou de la caisse de paiement unique | T16: Indication de dispositif Caisse Centralisatrice des Paiements ou de dispositif Caisse de Paiement Unique | U16: FILLER
B17: 1 | C17: 2-10 | D17: 11-16 | E17: 17-19 | F17: 20-22 | G17: 23-25 | H17: 26-27 | I17: 28-29 | J17: 30-69 | K17: 70-71 | L17: 72-77 | M17: 78 | N17: 79-80 | O17: 81 | P17: 82-87 | Q17: 88 | R17: 89-90 | S17: 91-93 | T17: 94 | U17: 95-128
B18: 1 | C18: 9 | D18: 6 | E18: 3 | F18: 3 | G18: 3 | H18: 2 | I18: 2 | J18: 40 | K18: 2 | L18: 6 | M18: 1 | N18: 2 | O18: 1 | P18: 6 | Q18: 1 | R18: 2 | S18: 3 | T18: 1 | U18: 34
B19: N | C19: N | D19: A | E19: N | F19: N | G19: A | H19: A | I19: A | J19: A | K19: A | L19: N | M19: A | N19: A | O19: A | P19: N | Q19: A | R19: A | S19: A | T19: N | U19: A
B20: O | C20: O | D20: F | E20: O | F20: O | G20: F | H20: F | I20: F | J20: O | K20: O | L20: O | M20: F | N20: O | O20: F | P20: O | Q20: F | R20: F | S20: F | T20: F | U20: FILLER
B21: 1 | C21: 422500009 | E21: 422 | F21: 001 | J21: SIMULATEUR B2 NOUVELLE CONVENTION TAXI | K21: B2 | L21: 251231 | N21: TA | P21: 062007 | Q21: U
A23: TYPE 2 DEBUT FACTURE | B23: Type d’enregistrement | C23: N° partenaire de santé + clé | D23: FILLER | E23: N° immatriculation assuré | F23: Clé N° immatriculation | G23: N° facture | H23: Complément du type | I23: Marquage de la facture | J23: Indicateur de forçage de la tarification de la part AMO | K23: Nature d’opération | L23: Date de facturation | M23: Top éclatement des flux par le PS | N23: Type de facture | O23: Facture sécurisée sur un dispositif portable | P23: Code Grand Régime | Q23: N° Caisse gestionnaire | R23: N° Centre gestionnaire | S23: Nature de la pièce justificative des droits | T23: N° prescripteur + clé | U23: Date de prescription | V23: Régime de prestation de l’assuré | W23: Nature d’assurance | X23: Justification d’exonération ou de modulation du ticket modérateur | Y23: Date Maternité | Z23: Numéro accident du travail ou date d’accident de droit commun | AA23: Présence d’une CPS de remplaçant pour sécurisation de la facture | AB23: Date de naissance du bénéficiaire | AC23: Rang de naissance | AD23: Rang de bénéficiaire | AE23: N° d’adhérent | AF23: Spécialité de prescripteur | AG23: Destinataire du règlement | AH23: Type de contrat souscrit auprès d’un organisme complémentaire | AI23: N° d’organisme complémentaire
B24: 1 | C24: 2-10 | D24: 11 | E24: 12-24 | F24: 25-26 | G24: 27-35 | H24: 36 | I24: 37 | J24: 38 | K24: 39 | L24: 40-45 | M24: 46 | N24: 47 | O24: 48 | P24: 49-50 | Q24: 51-53 | R24: 54-57 | S24: 58 | T24: 59-67 | U24: 68-73 | V24: 74-76 | W24: 77-78 | X24: 79 | Y24: 80-85 | Z24: 86-94 | AA24: 95 | AB24: 96-101 | AC24: 102 | AD24: 103-104 | AE24: 105-112 | AF24: 113-114 | AG24: 115-116 | AH24: 117-118 | AI24: 119-128
B25: 1 | C25: 9 | D25: 1 | E25: 13 | F25: 2 | G25: 9 | H25: 1 | I25: 1 | J25: 1 | K25: 1 | L25: 6 | M25: 1 | N25: 1 | O25: 1 | P25: 2 | Q25: 3 | R25: 4 | S25: 1 | T25: 9 | U25: 6 | V25: 3 | W25: 2 | X25: 1 | Y25: 6 | Z25: 9 | AA25: 1 | AB25: 6 | AC25: 1 | AD25: 2 | AE25: 8 | AF25: 2 | AG25: 2 | AH25: 2 | AI25: 10
B26: N | C26: N | D26: A | E26: A | F26: N | G26: N | H26: A | I26: A | J26: A | K26: N | L26: N | M26: A | N26: A | O26: A | P26: N | Q26: N | R26: N | S26: N | T26: N | U26: N | V26: A | W26: N | X26: A | Y26: N | Z26: N | AA26: A | AB26: N | AC26: N | AD26: A | AE26: A | AF26: N | AG26: N | AH26: N | AI26: A
B27: O | C27: O | D27: F | E27: O | F27: O | G27: O | H27: F | I27: F | J27: F | K27: O | L27: O | M27: F | N27: F | O27: F | P27: O | Q27: O | R27: O | S27: O | T27: O | U27: O | V27: F | W27: F | X27: O | Y27: F | Z27: F | AA27: O | AB27: O | AC27: F | AD27: F | AE27: F | AF27: F | AG27: F | AH27: F | AI27: F
B28: 2 | C28: 422500009 | E28: 1500101001001 | F28: 77 | G28: 250000001 | H28: A | K28: 1 | L28: 251231 | P28: 01 | Q28: 422 | R28: 0000 | S28: 2 | T28: 421000001 | U28: 250701 | W28: 10 | X28: 0 | Y28: 000000 | Z28: 000000000 | AB28: 500101 | AC28: 1 | AF28: 01 | AG28: 05 | AH28: 00
A30: TYPE 2E RPPS PRESCRIPTEUR | B30: Type d’enregistrement | C30: N° partenaire de santé + clé | D30: FILLER | E30: N° immatriculation assuré | F30: Clé N° immatriculation | G30: N° de facture | H30: Complément de type | I30: Identfifiant RPPS du prescripteur | J30: N° de la structure dans laquelle le PS a exécuté l’acte | K30: FILLER
B31: 1 | C31: 2-10 | D31: 11 | E31: 12-24 | F31: 25-26 | G31: 27-35 | H31: 36 | I31: 37-47 | J31: 48-61 | K31: 62-128
B32: 1 | C32: 9 | D32: 1 | E32: 13 | F32: 2 | G32: 9 | H32: 1 | I32: 11 | J32: 14 | K32: 67
B33: N | C33: N | D33: A | E33: A | F33: N | G33: N | H33: A | I33: N | J33: N | K33: A
B34: O | C34: O | D34: F | E34: O | F34: O | G34: O | H34: F | I34: F | J34: F | K34: F
B35: 2 | C35: 422500009 | E35: 1500101001001 | F35: 77 | G35: 250000001 | H35: E | I35: 11111110118 | AG35: LIGNE A GENERER
A37: TYPE 4A COMPOSANTE FORFAIT | B37: Type d’enregistrement | C37: N° partenaire de santé + clé | D37: FILLER | E37: N° immatriculation assuré | F37: Clé N° immatriculation | G37: N° de facture | H37: Complément de type | I37: Séquence | J37: Mode de traitement | K37: Discipline de prestations (ex DMT) | L37: Date de la demande d’accord préalable ou date d’accord de prise en charge CMU. | M37: Code accord préalable | N37: Séquence de renouvellement | O37: Code Participation assuré | P37: Justification d’exonération du Ticket Modérateur au niveau de l’acte | Q37: N° exécutant + clé ayant effectué l’acte ou fourni le produit | R37: Zone tarif de l’exécutant | S37: Spécialité de l’exécutant | T37: Date de l’acte, de la délivrance du produit | U37: Code acte | V37: Quantité d'actes | W37: Coefficient | X37: Dénombrement | Y37: Prix unitaire | Z37: Base de remboursement | AA37: Taux applicable à la prestation- | AB37: Montant remboursable par l’organisme d’Assurance Maladie Obligatoire | AC37: Montant des honoraires ou de la dépense (dépassement compris ou après remise pour la norme FR) | AD37: Qualificatif de la dépense | AE37: Code lieu | AF37: Montant remboursable par l’organisme complémentaire
B38: 1 | C38: 2-10 | D38: 11 | E38: 12-24 | F38: 25-26 | G38: 27-35 | H38: 36 | I38: 37-38 | J38: 39-40 | K38: 41-43 | L38: 44-49 | M38: 50 | N38: 51-52 | O38: 53 | P38: 54 | Q38: 55-63 | R38: 64-65 | S38: 66-67 | T38: 68-73 | U38: 74-78 | V38: 79-80 | W38: 81-86 | X38: 87-88 | Y38: 89-95 | Z38: 96-102 | AA38: 103-105 | AB38: 106-112 | AC38: 113-119 | AD38: 120 | AE38: 121 | AF38: 122-128
B39: 1 | C39: 9 | D39: 1 | E39: 13 | F39: 2 | G39: 9 | H39: 1 | I39: 2 | J39: 2 | K39: 3 | L39: 6 | M39: 1 | N39: 2 | O39: 1 | P39: 1 | Q39: 9 | R39: 2 | S39: 2 | T39: 6 | U39: 5 | V39: 2 | W39: 6 | X39: 2 | Y39: 7 | Z39: 7 | AA39: 3 | AB39: 7 | AC39: 7 | AD39: 1 | AE39: 1 | AF39: 7
B40: N | C40: N | D40: A | E40: A | F40: N | G40: N | H40: A | I40: N | J40: N | K40: N | L40: N | M40: N | N40: A | O40: A | P40: A | Q40: N | R40: N | S40: N | T40: N | U40: A | V40: N | W40: N | X40: N | Y40: N | Z40: N | AA40: N | AB40: N | AC40: N | AD40: A | AE40: N | AF40: N
B41: O | C41: O | D41: F | E41: O | F41: O | G41: O | H41: F | I41: F | J41: F | K41: F | L41: F | M41: O | N41: F | O41: F | P41: F | Q41: F | R41: F | S41: OSIMO | T41: O | U41: O | V41: O | W41: O | X41: O | Y41: O | Z41: O | AA41: O | AB41: O | AC41: O | AD41: F | AE41: F | AF41: F
B42: 4 | C42: 422500009 | E42: 1500101001001 | F42: 77 | G42: 250000001 | H42: A | I42: 00 | J42: 00 | K42: 000 | L42: 000000 | M42: 9 | Q42: 422500009 | R42: 00 | S42: 00 | T42: 251201 | U42: FX2 | V42: 01 | W42: 000100 | X42: 01 | Y42: 0002800 | Z42: 0002800 | AA42: 055 | AB42: 0001540 | AC42: 0002800 | AE42: 1 | AF42: 0000000 | AG42: LIGNE A GENERER
A44: TYPE 4T | B44: Type d’enregistrement | C44: N° partenaire de santé + clé | D44: FILLER | E44: N° immatriculation assuré | F44: Clé N° immatriculation | G44: N° de facture | H44: Complément du type | I44: Séquence | J44: Filler | K44: Série (au sens du décret du 6/5/88) | L44: Transport lié à une hospitalisation | M44: Longue distance | N44: Filler | O44: Forfait type de forfait | P44: Prix unitaire du forfait non majoré | Q44: Quantité forfaits | R44: Quantité forfaits majoration de nuit | S44: Quantité forfaits majoration dimanche ou fériés | T44: Prix unitaire du kilomètre non réduit. | U44: SANS MAJORATION : Quantité <ou=150 km | V44: Quantité >150 km | W44: MAJORATION NUIT : Quantité <ou=150 km | X44: Quantité >150 km | Y44: MAJORATION DIMANCHE/FERIE : Quantité <ou=150 km | Z44: Quantité >150 km | AA44: SUPPLEMENT : Type supplément | AB44: Quantité | AC44: Montant | AD44: PEAGES ET VOIES D'EAU Quantité | AE44: Montant | AF44: Montant global des abattements | AG44: Montant global des majorations pour courte distance | AH44: Filler
B45: 1 | C45: 2-10 | D45: 11 | E45: 12-24 | F45: 25-26 | G45: 27-35 | H45: 36 | I45: 37-38 | J45: 39-45 | K45: 46 | L45: 47 | M45: 48 | N45: 49 | O45: 50 | P45: 51-56 | Q45: 57-58 | R45: 59-60 | S45: 61-62 | T45: 63-68 | U45: 69-72 | V45: 73-76 | W45: 77-80 | X45: 81-84 | Y45: 85-88 | Z45: 89-92 | AA45: 93 | AB45: 94-95 | AC45: 96-101 | AD45: 102-103, | AE45: 104-109 | AF45: 110-116 | AG45: 117-123 | AH45: 142-128
B46: 1 | C46: 9 | D46: 1 | E46: 13 | F46: 2 | G46: 9 | H46: 1 | I46: 2 | J46: 7 | K46: 1 | L46: 1 | M46: 1 | N46: 1 | O46: 1 | P46: 6 | Q46: 2 | R46: 2 | S46: 2 | T46: 6 | U46: 4 | V46: 4 | W46: 4 | X46: 4 | Y46: 4 | Z46: 4 | AA46: 1 | AB46: 2 | AC46: 6 | AD46: 2 | AE46: 6 | AF46: 7 | AG46: 7 | AH46: 5
B47: N | C47: N | D47: A | E47: A | F47: N | G47: N | H47: A | I47: N | J47: A | K47: N | L47: N | M47: N | N47: A | O47: N | P47: N | Q47: N | R47: N | S47: N | T47: N | U47: N | V47: N | W47: N | X47: N | Y47: N | Z47: N | AA47: N | AB47: N | AC47: N | AD47: N | AE47: N | AF47: N | AG47: N | AH47: A
B48: O | C48: O | D48: F | E48: O | F48: O | G48: O | H48: O | I48: F | J48: F | K48: O | L48: O | M48: O | N48: F | O48: O | P48: F | Q48: F | R48: F | S48: F | T48: F | U48: F | V48: F | W48: F | X48: F | Y48: F | Z48: F | AA48: F | AB48: F | AC48: F | AD48: F | AE48: F | AF48: F | AG48: F | AH48: F
B49: 4 | C49: 422500009 | E49: 1500101001001 | F49: 77 | G49: 250000001 | H49: T | I49: 01 | K49: 0 | L49: 0 | M49: 0 | O49: 0 | P49: 000000 | Q49: 00 | R49: 00 | S49: 00 | T49: 000000 | U49: 0000 | V49: 0000 | W49: 0000 | X49: 0000 | Y49: 0000 | Z49: 0000 | AA49: 0 | AB49: 00 | AC49: 000000 | AD49: 00 | AE49: 000000 | AF49: 0000000 | AG49: 0000000
A51: TYPE 4U | B51: Type d’enregistrement | C51: N° partenaire de santé + clé | D51: FILLER | E51: N° immatriculation assuré | F51: Clé N° immatriculation | G51: N° de facture | H51: Complément du type | I51: Séquence | J51: Date départ | K51: Heure départ | L51: Lieu départ département commune | M51: N° véhicule | N51: Nom conducteur | O51: Prénom conducteur | P51: Nom accompagnateur | Q51: Prénom accompagnateur | R51: Date arrivée | S51: Heure arrivée | T51: Lieu d’arrivée | U51: Nombre malades | V51: % abattement | W51: Montant abattement | X51: Nombre de km facturés | Y51: Distance réelle parcourue | Z51: Utilisation du distancier | AA51: Niveau de certification | AB51: Montant de la majoration pour courte distance | AC51: Indicateur de période de réalisation du trajet | AD51: Filler
B52: 1 | C52: 2-10 | D52: 11 | E52: 12-24 | F52: 25-26 | G52: 27-35 | H52: 36 | I52: 37-38 | J52: 39-44 | K52: 45-48 | L52: 49-53 | M52: 54-62 | N52: 63-70 | O52: 71-73 | P52: 74-81 | Q52: 82-84 | R52: 85-90 | S52: 91-94 | T52: 95-99 | U52: 100 | V52: 101-102 | W52: 103-108 | X52: 109-112 | Y52: 113-116 | Z52: 117 | AA52: 118 | AB52: 119-124 | AC52: 125 | AD52: 126-128
B53: 1 | C53: 9 | D53: 1 | E53: 13 | F53: 2 | G53: 9 | H53: 1 | I53: 2 | J53: 6 | K53: 4 | L53: 5 | M53: 9 | N53: 8 | O53: 3 | P53: 8 | Q53: 3 | R53: 6 | S53: 4 | T53: 5 | U53: 1 | V53: 2 | W53: 6 | X53: 4 | Y53: 4 | Z53: 1 | AA53: 1 | AB53: 6 | AC53: 1 | AD53: 3
B54: N | C54: N | D54: A | E54: A | F54: N | G54: N | H54: A | I54: N | J54: N | K54: N | L54: N | M54: A | N54: A | O54: A | P54: A | Q54: A | R54: N | S54: N | T54: N | U54: N | V54: N | W54: N | X54: N | Y54: N | Z54: A | AA54: A | AB54: N | AC54: A | AD54: A
B55: O | C55: O | D55: F | E55: O | F55: O | G55: O | H55: O | I55: O | J55: O | K55: P | L55: O | M55: O | N55: O | O55: O | P55: F | Q55: F | R55: O | S55: O | T55: O | U55: O | V55: F | W55: F | X55: F | Y55: O | Z55: F | AA55: F | AB55: F | AC55: F | AD55: F
B56: 4 | C56: 422500009 | E56: 1500101001001 | F56: 77 | G56: 250000001 | H56: U | I56: 01 | J56: 251201 | K56: 1000 | L56: 69123 | M56: EE-003-FF | N56: NCONDUCA | O56: PRA | R56: 251201 | S56: 1011 | T56: 69266 | U56: 1 | V56: 00 | W56: 000000 | X56: 0000 | Y56: 0003 | AB56: 000000 | AE56: LIGNE A GENERER
A58: TYPE 5 FIN FACTURE | B58: Type d’enregistrement | C58: N° partenaire de santé + clé | D58: FILLER | E58: N° immatriculation assuré | F58: Clé N° immatriculation | G58: N° de facture | H58: FILLER | I58: Nombre d’enregistrements de Type 4 | J58: Zone réservée SESAM | K58: Total des montants facturés | L58: Total remboursable par la Caisse | M58: Total participation assuré avant participation de l’organisme complémentaire | N58: Total remboursable par l’organisme complémentaire | O58: Top éclatement des flux par l’OCT | P58: Zone réservée SESAM | Q58: Liste d’opposition | R58: FILLER | S58: Zone de certification
B59: 1 | C59: 2-10 | D59: 11 | E59: 12-24 | F59: 25-26 | G59: 27-35 | H59: 36-38 | I59: 39-41 | J59: 42-57 | K59: 58-65 | L59: 66-73 | M59: 74-81 | N59: 82-89 | O59: 90 | P59: 91-93 | Q59: 94 | R59: 95-96 | S59: 97-128
B60: 1 | C60: 9 | D60: 1 | E60: 13 | F60: 2 | G60: 9 | H60: 3 | I60: 3 | J60: 16 | K60: 8 | L60: 8 | M60: 8 | N60: 8 | O60: 1 | P60: 3 | Q60: 1 | R60: 2 | S60: 32
B61: N | C61: N | D61: A | E61: A | F61: N | G61: N | H61: A | I61: N | J61: A | K61: N | L61: N | M61: N | N61: N | O61: A | P61: A | Q61: A | R61: A | S61: A
B62: O | C62: O | D62: F | E62: O | F62: O | G62: O | H62: F | I62: O | J62: O | K62: O | L62: O | M62: O | N62: F | O62: F | P62: O | Q62: O | R62: F | S62: F
B63: 5 | C63: 422500009 | E63: 1500101001001 | F63: 77 | G63: 250000001 | I63: 003 | K63: 00002800 | L63: 00001540 | M63: 00001260 | N63: 00000000
A65: TYPE 6 FIN LOT | B65: Type d’enregistrement | C65: N° partenaire de santé + clé | D65: Nombre de factures | E65: Nombre de lignes actes | F65: Comptabilisation des enregistrements des types 2 | G65: Total de tous les enregistrements de type 5 | H65: Montant total général du lot prestations facturées | I65: Montant total général du lot prestations remboursables par l’organisme d’Ass. Maladie | J65: Montant total général du lot prestations remboursables par les organismes complémentaires | K65: N° de lot | L65: indicateur de marquage des factures du lot. | M65: Type de facture | N65: FILLER | O65: N° agrément progiciel de santé ou n° de certificat pour les logiciels établissements ou raison sociale éditeur | P65: N° agrément du dispositif portable | Q65: FILLER | R65: N° d’identification du PS remplaçant | S65: Zone de certification
B66: 1 | C66: 2-10 | D66: 11-13 | E66: 14-17 | F66: 18-21 | G66: 22-24 | H66: 25-33 | I66: 34-42 | J66: 43-51 | K66: 52-54 | L66: 55 | M66: 56 | N66: 57-60 | O66: 61-72 | P66: 73-84 | Q66: 85-87 | R66: 88-96 | S66: 97-128
B67: 1 | C67: 9 | D67: 3 | E67: 4 | F67: 4 | G67: 3 | H67: 9 | I67: 9 | J67: 9 | K67: 3 | L67: 1 | M67: 1 | N67: 4 | O67: 12 | P67: 12 | Q67: 3 | R67: 9 | S67: 32
B68: N | C68: N | D68: N | E68: N | F68: N | G68: N | H68: N | I68: N | J68: N | K68: N | L68: A | M68: A | N68: A | O68: A | P68: N | Q68: A | R68: N | S68: N
B69: O | C69: O | D69: O | E69: O | F69: O | G69: O | H69: O | I69: O | J69: O | K69: O | L69: F | M69: F | N69: F | O69: F | P69: F | Q69: F | R69: F | S69: O
B70: 6 | C70: 422500009 | D70: 001 | E70: 0001 | F70: 0002 | G70: 001 | H70: 000002800 | I70: 000001540 | J70: 000000000 | K70: 001 | O70: AAZZ2501BC12
A72: TYPE 999 FIN FICHIER | B72: Type d’enregistrement | C72: Type émetteur | D72: Numéro émetteur | E72: FILLER | F72: Type de destinataire | G72: Numéro de destinataire | H72: FILLER | I72: Application | J72: Identification du fichier | K72: Volume du fichier | L72: FILLER | M72: Nombre de lots | N72: FILLER
B73: 1-3 | C73: 4-5 | D73: 6-19 | E73: 20-25 | F73: 26-27 | G73: 28-41 | H73: 42-47 | I73: 48-49 | J73: 50-55 | K73: 56-63 | L73: 64-82 | M73: 83-85 | N73: 86-128
B74: 3 | C74: 2 | D74: 14 | E74: 6 | F74: 2 | G74: 14 | H74: 6 | I74: 2 | J74: 6 | K74: 8 | L74: 19 | M74: 3 | N74: 43
B75: N | C75: A | D75: N | E75: A | F75: A | G75: N | H75: A | I75: A | J75: A | K75: N | L75: A | M75: N | N75: A
B76: O | C76: O | D76: O | E76: F | F76: O | G76: O | H76: F | I76: O | J76: O | K76: O | L76: F | M76: O | N76: F
B77: 999 | C77: TP | D77: 00000422500009 | F77: CT | G77: 00000001000422 | I77: TR | J77: TESTB2 | K77: 00000010 | M77: 001

Sheet CONVENTION CAS 3
A1: Table des matières | B1: CARACTERISTIQUES METIERS DU OU DES TRAJETS FACTURES
A3: SOCIETE DE TAXI DE N° AM : 422500009 SPECIALITE : 56 | D3: CARACTERISTIQUE PATIENT | G3: CARACTERISTIQUES FACTURE | I3: CARACTERISTIQUES TRAJETS | Z3: ASSURE | AG3: PRESCRIPTEUR
A4: N°CAS | B4: NOMBRE DE TRAJETS FACTURES | C4: TRAJET N° : | D4: NATURE D'ASSURANCE | E4: TAUX | F4: C2S ? : O/N | G4: REFUS TRANSPORT PARTAGE | H4: TIERS PAYANT | I4: LIEU DEPART | J4: LIEU ARRIVEE | K4: DATE / HEURE DEPART | L4: DATE / HEURE ARRIVEE | M4: N° IMMATRICULATION VEHICULE | N4: COMMUNE D'ADS | O4: DEPARTEMENT D'ADS | P4: ORGANISME LOCAL D'ADS | Q4: DISTANCE PARCOURUE | R4: CONTEXTE : J, N , F | S4: NOMBRE DE MALADES | T4: SUPPLEMENT FORFAITAIRE ? : O / N | U4: PEAGES ? : O / N | V4: TPMR ? : O / N | W4: TRAJET EN LIEN AVEC HOSPITALISATION ET RETOUR A VIDE ? : O/N | X4: SI T PARTAGE : TRAJET SEUL > X KM ? : O/N | Z4: NIR | AA4: DATE DE NAISSANCE | AB4: RANG | AC4: REGIME | AD4: CAISSE | AE4: CENTRE | AG4: N°AM | AH4: SPECIALITE | AI4: NN°RPPS
A5: ='LISTE DES CAS ANNEXE 30'!A7 -> CONVENTION CAS 3 | B5: ='LISTE DES CAS ANNEXE 30'!B7 -> 1 | C5: ='LISTE DES CAS ANNEXE 30'!C7 -> 1 | D5: ='LISTE DES CAS ANNEXE 30'!D7 -> MALADIE | E5: ='LISTE DES CAS ANNEXE 30'!E7 -> 0.55 | F5: ='LISTE DES CAS ANNEXE 30'!H7 -> NON | G5: ='LISTE DES CAS ANNEXE 30'!I7 -> Sans objet | H5: ='LISTE DES CAS ANNEXE 30'!J7 -> 05 - TP AMO SEUL | I5: ='LISTE DES CAS ANNEXE 30'!K7 -> 69-LYON | J5: ='LISTE DES CAS ANNEXE 30'!L7 -> 42-SAINT-ETIENNE | K5: ='LISTE DES CAS ANNEXE 30'!M7 -> 01/12/2025 à 10H00 | L5: ='LISTE DES CAS ANNEXE 30'!N7 -> 01/12/2025 à 11h15 | M5: ='LISTE DES CAS ANNEXE 30'!O7 -> EE-003-FF | ... X5: ='LISTE DES CAS ANNEXE 30'!Z7 -> Sans objet | Z5: 1500101001001 | AA5: 500101 | AB5: 1 | AC5: 01 | AD5: 422 | AE5: 0000 | AG5: 421000001 | AH5: 01 | AI5: 11111110118
A7: FACTURE B2 CORRESPONDANT
A9: TYPE 000 DEBUT FICHIER | B9: Type d’enregistrement | C9: Type d’émetteur | D9: Numéro d’émetteur | E9: FILLER | F9: Type de destinataire | G9: N° de destinataire | H9: Date de réception du flux sur le frontal | I9: Application | J9: Identification du fichier | K9: Date de création du fichier | L9: Norme | M9: Version de Norme | N9: FILLER | O9: FILLER | P9: FILLER | Q9: FILLER | R9: Longueur d’enregistrement | S9: FILLER | T9: Zone message
B10: 1-3 | C10: 4-5 | D10: 6-19 | E10: 20-25 | F10: 26-27 | G10: 28-41 | H10: 42-47 | I10: 48-49 | J10: 50-55 | K10: 56-61 | L10: 62-65 | M10: 66-67 | N10: 68 | O10: 69 | P10: 70-72 | Q10: 73-82 | R10: 83-85 | S10: 86-91 | T10: 92-128
B11: 3 | C11: 2 | D11: 14 | E11: 6 | F11: 2 | G11: 14 | H11: 6 | I11: 2 | J11: 6 | K11: 6 | L11: 4 | M11: 2 | N11: 1 | O11: 1 | P11: 3 | Q11: 10 | R11: 3 | S11: 6 | T11: 37
B12: N | C12: A | D12: N | E12: A | F12: A | G12: N | H12: A | I12: A | J12: A | K12: N | L12: A | M12: A | N12: A | O12: A | P12: A | Q12: A | R12: N | S12: A | T12: N
B13: O | C13: O | D13: O | E13: F | F13: O | G13: O | H13: O | I13: O | J13: O | K13: O | L13: O | M13: O | N13: F | O13: F | P13: F | Q13: F | R13: F | S13: F | T13: O
B14: 000 | C14: TP | D14: 00000422500009 | F14: CT | G14: 00000001000422 | H14: 251231 | I14: TR | J14: TESTB2 | K14: 251231 | L14: TA | M14: B2 | R14: 128
A16: TYPE 1 DEBUT LOT | B16: Type d’enregistrement | C16: N° partenaire de santé + clé | D16: Origine du fichier | E16: N° d’organisme destinataire | F16: N° de lot | G16: Catégorie | H16: Statut juridique | I16: Mode de fixation des tarifs | J16: Nom ou raison sociale du partenaire de santé | K16: Version de norme utilisée | L16: Date de création du lot | M16: Filler | N16: Code norme | O16: Top certification du lot | P16: Numéro de version de norme | Q16: Unité monétaire de facturation | R16: Grand régime de la caisse pivot ou de la caisse de paiement unique privés, ou pour les établissements publics et privés antérieurement sous DG | S16: N° de la caisse pivot ou de la caisse de paiement unique | T16: Indication de dispositif Caisse Centralisatrice des Paiements ou de dispositif Caisse de Paiement Unique | U16: FILLER
B17: 1 | C17: 2-10 | D17: 11-16 | E17: 17-19 | F17: 20-22 | G17: 23-25 | H17: 26-27 | I17: 28-29 | J17: 30-69 | K17: 70-71 | L17: 72-77 | M17: 78 | N17: 79-80 | O17: 81 | P17: 82-87 | Q17: 88 | R17: 89-90 | S17: 91-93 | T17: 94 | U17: 95-128
B18: 1 | C18: 9 | D18: 6 | E18: 3 | F18: 3 | G18: 3 | H18: 2 | I18: 2 | J18: 40 | K18: 2 | L18: 6 | M18: 1 | N18: 2 | O18: 1 | P18: 6 | Q18: 1 | R18: 2 | S18: 3 | T18: 1 | U18: 34
B19: N | C19: N | D19: A | E19: N | F19: N | G19: A | H19: A | I19: A | J19: A | K19: A | L19: N | M19: A | N19: A | O19: A | P19: N | Q19: A | R19: A | S19: A | T19: N | U19: A
B20: O | C20: O | D20: F | E20: O | F20: O | G20: F | H20: F | I20: F | J20: O | K20: O | L20: O | M20: F | N20: O | O20: F | P20: O | Q20: F | R20: F | S20: F | T20: F | U20: FILLER
B21: 1 | C21: 422500009 | E21: 422 | F21: 001 | J21: SIMULATEUR B2 NOUVELLE CONVENTION TAXI | K21: B2 | L21: 251231 | N21: TA | P21: 062007 | Q21: U
A23: TYPE 2 DEBUT FACTURE | B23: Type d’enregistrement | C23: N° partenaire de santé + clé | D23: FILLER | E23: N° immatriculation assuré | F23: Clé N° immatriculation | G23: N° facture | H23: Complément du type | I23: Marquage de la facture | J23: Indicateur de forçage de la tarification de la part AMO | K23: Nature d’opération | L23: Date de facturation | M23: Top éclatement des flux par le PS | N23: Type de facture | O23: Facture sécurisée sur un dispositif portable | P23: Code Grand Régime | Q23: N° Caisse gestionnaire | R23: N° Centre gestionnaire | S23: Nature de la pièce justificative des droits | T23: N° prescripteur + clé | U23: Date de prescription | V23: Régime de prestation de l’assuré | W23: Nature d’assurance | X23: Justification d’exonération ou de modulation du ticket modérateur | Y23: Date Maternité | Z23: Numéro accident du travail ou date d’accident de droit commun | AA23: Présence d’une CPS de remplaçant pour sécurisation de la facture | AB23: Date de naissance du bénéficiaire | AC23: Rang de naissance | AD23: Rang de bénéficiaire | AE23: N° d’adhérent | AF23: Spécialité de prescripteur | AG23: Destinataire du règlement | AH23: Type de contrat souscrit auprès d’un organisme complémentaire | AI23: N° d’organisme complémentaire
B24: 1 | C24: 2-10 | D24: 11 | E24: 12-24 | F24: 25-26 | G24: 27-35 | H24: 36 | I24: 37 | J24: 38 | K24: 39 | L24: 40-45 | M24: 46 | N24: 47 | O24: 48 | P24: 49-50 | Q24: 51-53 | R24: 54-57 | S24: 58 | T24: 59-67 | U24: 68-73 | V24: 74-76 | W24: 77-78 | X24: 79 | Y24: 80-85 | Z24: 86-94 | AA24: 95 | AB24: 96-101 | AC24: 102 | AD24: 103-104 | AE24: 105-112 | AF24: 113-114 | AG24: 115-116 | AH24: 117-118 | AI24: 119-128
B25: 1 | C25: 9 | D25: 1 | E25: 13 | F25: 2 | G25: 9 | H25: 1 | I25: 1 | J25: 1 | K25: 1 | L25: 6 | M25: 1 | N25: 1 | O25: 1 | P25: 2 | Q25: 3 | R25: 4 | S25: 1 | T25: 9 | U25: 6 | V25: 3 | W25: 2 | X25: 1 | Y25: 6 | Z25: 9 | AA25: 1 | AB25: 6 | AC25: 1 | AD25: 2 | AE25: 8 | AF25: 2 | AG25: 2 | AH25: 2 | AI25: 10
B26: N | C26: N | D26: A | E26: A | F26: N | G26: N | H26: A | I26: A | J26: A | K26: N | L26: N | M26: A | N26: A | O26: A | P26: N | Q26: N | R26: N | S26: N | T26: N | U26: N | V26: A | W26: N | X26: A | Y26: N | Z26: N | AA26: A | AB26: N | AC26: N | AD26: A | AE26: A | AF26: N | AG26: N | AH26: N | AI26: A
B27: O | C27: O | D27: F | E27: O | F27: O | G27: O | H27: F | I27: F | J27: F | K27: O | L27: O | M27: F | N27: F | O27: F | P27: O | Q27: O | R27: O | S27: O | T27: O | U27: O | V27: F | W27: F | X27: O | Y27: F | Z27: F | AA27: O | AB27: O | AC27: F | AD27: F | AE27: F | AF27: F | AG27: F | AH27: F | AI27: F
B28: 2 | C28: 422500009 | E28: 1500101001001 | F28: 77 | G28: 250000001 | H28: A | K28: 1 | L28: 251231 | P28: 01 | Q28: 422 | R28: 0000 | S28: 2 | T28: 421000001 | U28: 250701 | W28: 10 | X28: 0 | Y28: 000000 | Z28: 000000000 | AB28: 500101 | AC28: 1 | AF28: 01 | AG28: 05 | AH28: 00
A30: TYPE 2E RPPS PRESCRIPTEUR | B30: Type d’enregistrement | C30: N° partenaire de santé + clé | D30: FILLER | E30: N° immatriculation assuré | F30: Clé N° immatriculation | G30: N° de facture | H30: Complément de type | I30: Identfifiant RPPS du prescripteur | J30: N° de la structure dans laquelle le PS a exécuté l’acte | K30: FILLER
B31: 1 | C31: 2-10 | D31: 11 | E31: 12-24 | F31: 25-26 | G31: 27-35 | H31: 36 | I31: 37-47 | J31: 48-61 | K31: 62-128
B32: 1 | C32: 9 | D32: 1 | E32: 13 | F32: 2 | G32: 9 | H32: 1 | I32: 11 | J32: 14 | K32: 67
B33: N | C33: N | D33: A | E33: A | F33: N | G33: N | H33: A | I33: N | J33: N | K33: A
B34: O | C34: O | D34: F | E34: O | F34: O | G34: O | H34: F | I34: F | J34: F | K34: F
B35: 2 | C35: 422500009 | E35: 1500101001001 | F35: 77 | G35: 250000001 | H35: E | I35: 11111110118 | AG35: LIGNE A GENERER
A37: TYPE 4A COMPOSANTE FORFAIT | B37: Type d’enregistrement | C37: N° partenaire de santé + clé | D37: FILLER | E37: N° immatriculation assuré | F37: Clé N° immatriculation | G37: N° de facture | H37: Complément de type | I37: Séquence | J37: Mode de traitement | K37: Discipline de prestations (ex DMT) | L37: Date de la demande d’accord préalable ou date d’accord de prise en charge CMU. | M37: Code accord préalable | N37: Séquence de renouvellement | O37: Code Participation assuré | P37: Justification d’exonération du Ticket Modérateur au niveau de l’acte | Q37: N° exécutant + clé ayant effectué l’acte ou fourni le produit | R37: Zone tarif de l’exécutant | S37: Spécialité de l’exécutant | T37: Date de l’acte, de la délivrance du produit | U37: Code acte | V37: Quantité d'actes | W37: Coefficient | X37: Dénombrement | Y37: Prix unitaire | Z37: Base de remboursement | AA37: Taux applicable à la prestation- | AB37: Montant remboursable par l’organisme d’Assurance Maladie Obligatoire | AC37: Montant des honoraires ou de la dépense (dépassement compris ou après remise pour la norme FR) | AD37: Qualificatif de la dépense | AE37: Code lieu | AF37: Montant remboursable par l’organisme complémentaire
B38: 1 | C38: 2-10 | D38: 11 | E38: 12-24 | F38: 25-26 | G38: 27-35 | H38: 36 | I38: 37-38 | J38: 39-40 | K38: 41-43 | L38: 44-49 | M38: 50 | N38: 51-52 | O38: 53 | P38: 54 | Q38: 55-63 | R38: 64-65 | S38: 66-67 | T38: 68-73 | U38: 74-78 | V38: 79-80 | W38: 81-86 | X38: 87-88 | Y38: 89-95 | Z38: 96-102 | AA38: 103-105 | AB38: 106-112 | AC38: 113-119 | AD38: 120 | AE38: 121 | AF38: 122-128
B39: 1 | C39: 9 | D39: 1 | E39: 13 | F39: 2 | G39: 9 | H39: 1 | I39: 2 | J39: 2 | K39: 3 | L39: 6 | M39: 1 | N39: 2 | O39: 1 | P39: 1 | Q39: 9 | R39: 2 | S39: 2 | T39: 6 | U39: 5 | V39: 2 | W39: 6 | X39: 2 | Y39: 7 | Z39: 7 | AA39: 3 | AB39: 7 | AC39: 7 | AD39: 1 | AE39: 1 | AF39: 7
B40: N | C40: N | D40: A | E40: A | F40: N | G40: N | H40: A | I40: N | J40: N | K40: N | L40: N | M40: N | N40: A | O40: A | P40: A | Q40: N | R40: N | S40: N | T40: N | U40: A | V40: N | W40: N | X40: N | Y40: N | Z40: N | AA40: N | AB40: N | AC40: N | AD40: A | AE40: N | AF40: N
B41: O | C41: O | D41: F | E41: O | F41: O | G41: O | H41: F | I41: F | J41: F | K41: F | L41: F | M41: O | N41: F | O41: F | P41: F | Q41: F | R41: F | S41: OSIMO | T41: O | U41: O | V41: O | W41: O | X41: O | Y41: O | Z41: O | AA41: O | AB41: O | AC41: O | AD41: F | AE41: F | AF41: F
B42: 4 | C42: 422500009 | E42: 1500101001001 | F42: 77 | G42: 250000001 | H42: A | I42: 00 | J42: 00 | K42: 000 | L42: 000000 | M42: 9 | Q42: 422500009 | R42: 00 | S42: 00 | T42: 251201 | U42: FX2 | V42: 01 | W42: 000100 | X42: 01 | Y42: 0002800 | Z42: 0002800 | AA42: 055 | AB42: 0001540 | AC42: 0002800 | AE42: 1 | AF42: 0000000 | AG42: LIGNE A GENERER
A44: TYPE 4T | B44: Type d’enregistrement | C44: N° partenaire de santé + clé | D44: FILLER | E44: N° immatriculation assuré | F44: Clé N° immatriculation | G44: N° de facture | H44: Complément du type | I44: Séquence | J44: Filler | K44: Série (au sens du décret du 6/5/88) | L44: Transport lié à une hospitalisation | M44: Longue distance | N44: Filler | O44: Forfait type de forfait | P44: Prix unitaire du forfait non majoré | Q44: Quantité forfaits | R44: Quantité forfaits majoration de nuit | S44: Quantité forfaits majoration dimanche ou fériés | T44: Prix unitaire du kilomètre non réduit. | U44: SANS MAJORATION : Quantité <ou=150 km | V44: Quantité >150 km | W44: MAJORATION NUIT : Quantité <ou=150 km | X44: Quantité >150 km | Y44: MAJORATION DIMANCHE/FERIE : Quantité <ou=150 km | Z44: Quantité >150 km | AA44: SUPPLEMENT : Type supplément | AB44: Quantité | AC44: Montant | AD44: PEAGES ET VOIES D'EAU Quantité | AE44: Montant | AF44: Montant global des abattements | AG44: Montant global des majorations pour courte distance | AH44: Filler
B45: 1 | C45: 2-10 | D45: 11 | E45: 12-24 | F45: 25-26 | G45: 27-35 | H45: 36 | I45: 37-38 | J45: 39-45 | K45: 46 | L45: 47 | M45: 48 | N45: 49 | O45: 50 | P45: 51-56 | Q45: 57-58 | R45: 59-60 | S45: 61-62 | T45: 63-68 | U45: 69-72 | V45: 73-76 | W45: 77-80 | X45: 81-84 | Y45: 85-88 | Z45: 89-92 | AA45: 93 | AB45: 94-95 | AC45: 96-101 | AD45: 102-103, | AE45: 104-109 | AF45: 110-116 | AG45: 117-123 | AH45: 142-128
B46: 1 | C46: 9 | D46: 1 | E46: 13 | F46: 2 | G46: 9 | H46: 1 | I46: 2 | J46: 7 | K46: 1 | L46: 1 | M46: 1 | N46: 1 | O46: 1 | P46: 6 | Q46: 2 | R46: 2 | S46: 2 | T46: 6 | U46: 4 | V46: 4 | W46: 4 | X46: 4 | Y46: 4 | Z46: 4 | AA46: 1 | AB46: 2 | AC46: 6 | AD46: 2 | AE46: 6 | AF46: 7 | AG46: 7 | AH46: 5
B47: N | C47: N | D47: A | E47: A | F47: N | G47: N | H47: A | I47: N | J47: A | K47: N | L47: N | M47: N | N47: A | O47: N | P47: N | Q47: N | R47: N | S47: N | T47: N | U47: N | V47: N | W47: N | X47: N | Y47: N | Z47: N | AA47: N | AB47: N | AC47: N | AD47: N | AE47: N | AF47: N | AG47: N | AH47: A
B48: O | C48: O | D48: F | E48: O | F48: O | G48: O | H48: O | I48: F | J48: F | K48: O | L48: O | M48: O | N48: F | O48: O | P48: F | Q48: F | R48: F | S48: F | T48: F | U48: F | V48: F | W48: F | X48: F | Y48: F | Z48: F | AA48: F | AB48: F | AC48: F | AD48: F | AE48: F | AF48: F | AG48: F | AH48: F
B49: 4 | C49: 422500009 | E49: 1500101001001 | F49: 77 | G49: 250000001 | H49: T | I49: 01 | K49: 0 | L49: 0 | M49: 0 | O49: 0 | P49: 000000 | Q49: 00 | R49: 00 | S49: 00 | T49: 000000 | U49: 0000 | V49: 0000 | W49: 0000 | X49: 0000 | Y49: 0000 | Z49: 0000 | AA49: 0 | AB49: 00 | AC49: 000000 | AD49: 00 | AE49: 000000 | AF49: 0000000 | AG49: 0000000
A51: TYPE 4U | B51: Type d’enregistrement | C51: N° partenaire de santé + clé | D51: FILLER | E51: N° immatriculation assuré | F51: Clé N° immatriculation | G51: N° de facture | H51: Complément du type | I51: Séquence | J51: Date départ | K51: Heure départ | L51: Lieu départ département commune | M51: N° véhicule | N51: Nom conducteur | O51: Prénom conducteur | P51: Nom accompagnateur | Q51: Prénom accompagnateur | R51: Date arrivée | S51: Heure arrivée | T51: Lieu d’arrivée | U51: Nombre malades | V51: % abattement | W51: Montant abattement | X51: Nombre de km facturés | Y51: Distance réelle parcourue | Z51: Utilisation du distancier | AA51: Niveau de certification | AB51: Montant de la majoration pour courte distance | AC51: Indicateur de période de réalisation du trajet | AD51: Filler
B52: 1 | C52: 2-10 | D52: 11 | E52: 12-24 | F52: 25-26 | G52: 27-35 | H52: 36 | I52: 37-38 | J52: 39-44 | K52: 45-48 | L52: 49-53 | M52: 54-62 | N52: 63-70 | O52: 71-73 | P52: 74-81 | Q52: 82-84 | R52: 85-90 | S52: 91-94 | T52: 95-99 | U52: 100 | V52: 101-102 | W52: 103-108 | X52: 109-112 | Y52: 113-116 | Z52: 117 | AA52: 118 | AB52: 119-124 | AC52: 125 | AD52: 126-128
B53: 1 | C53: 9 | D53: 1 | E53: 13 | F53: 2 | G53: 9 | H53: 1 | I53: 2 | J53: 6 | K53: 4 | L53: 5 | M53: 9 | N53: 8 | O53: 3 | P53: 8 | Q53: 3 | R53: 6 | S53: 4 | T53: 5 | U53: 1 | V53: 2 | W53: 6 | X53: 4 | Y53: 4 | Z53: 1 | AA53: 1 | AB53: 6 | AC53: 1 | AD53: 3
B54: N | C54: N | D54: A | E54: A | F54: N | G54: N | H54: A | I54: N | J54: N | K54: N | L54: N | M54: A | N54: A | O54: A | P54: A | Q54: A | R54: N | S54: N | T54: N | U54: N | V54: N | W54: N | X54: N | Y54: N | Z54: A | AA54: A | AB54: N | AC54: A | AD54: A
B55: O | C55: O | D55: F | E55: O | F55: O | G55: O | H55: O | I55: O | J55: O | K55: P | L55: O | M55: O | N55: O | O55: O | P55: F | Q55: F | R55: O | S55: O | T55: O | U55: O | V55: F | W55: F | X55: F | Y55: O | Z55: F | AA55: F | AB55: F | AC55: F | AD55: F
B56: 4 | C56: 422500009 | E56: 1500101001001 | F56: 77 | G56: 250000001 | H56: U | I56: 01 | J56: 251201 | K56: 1000 | L56: 69123 | M56: EE-003-FF | N56: NCONDUCA | O56: PRA | R56: 251201 | S56: 1115 | T56: 42218 | U56: 1 | V56: 00 | W56: 000000 | X56: 0000 | Y56: 0063 | AB56: 000000 | AE56: LIGNE A GENERER
A58: TYPE 4 COMPOSANTE "KM" | B58: Type d’enregistrement | C58: N° partenaire de santé + clé | D58: FILLER | E58: N° immatriculation assuré | F58: Clé N° immatriculation | G58: N° de facture | H58: Complément de type | I58: Séquence | J58: Mode de traitement | K58: Discipline de prestations (ex DMT) | L58: Date de la demande d’accord préalable ou date d’accord de prise en charge CMU. | M58: Code accord préalable | N58: Séquence de renouvellement | O58: Code Participation assuré | P58: Justification d’exonération du Ticket Modérateur au niveau de l’acte | Q58: N° exécutant + clé ayant effectué l’acte ou fourni le produit | R58: Zone tarif de l’exécutant | S58: Spécialité de l’exécutant | T58: Date de l’acte, de la délivrance du produit | U58: Code acte | V58: Quantité d'actes | W58: Coefficient | X58: Dénombrement | Y58: Prix unitaire | Z58: Base de remboursement | AA58: Taux applicable à la prestation- | AB58: Montant remboursable par l’organisme d’Assurance Maladie Obligatoire | AC58: Montant des honoraires ou de la dépense (dépassement compris ou après remise pour la norme FR) | AD58: Qualificatif de la dépense | AE58: Code lieu | AF58: Montant remboursable par l’organisme complémentaire
B59: 1 | C59: 2-10 | D59: 11 | E59: 12-24 | F59: 25-26 | G59: 27-35 | H59: 36 | I59: 37-38 | J59: 39-40 | K59: 41-43 | L59: 44-49 | M59: 50 | N59: 51-52 | O59: 53 | P59: 54 | Q59: 55-63 | R59: 64-65 | S59: 66-67 | T59: 68-73 | U59: 74-78 | V59: 79-80 | W59: 81-86 | X59: 87-88 | Y59: 89-95 | Z59: 96-102 | AA59: 103-105 | AB59: 106-112 | AC59: 113-119 | AD59: 120 | AE59: 121 | AF59: 122-128
B60: 1 | C60: 9 | D60: 1 | E60: 13 | F60: 2 | G60: 9 | H60: 1 | I60: 2 | J60: 2 | K60: 3 | L60: 6 | M60: 1 | N60: 2 | O60: 1 | P60: 1 | Q60: 9 | R60: 2 | S60: 2 | T60: 6 | U60: 5 | V60: 2 | W60: 6 | X60: 2 | Y60: 7 | Z60: 7 | AA60: 3 | AB60: 7 | AC60: 7 | AD60: 1 | AE60: 1 | AF60: 7
B61: N | C61: N | D61: A | E61: A | F61: N | G61: N | H61: A | I61: N | J61: N | K61: N | L61: N | M61: N | N61: A | O61: A | P61: A | Q61: N | R61: N | S61: N | T61: N | U61: A | V61: N | W61: N | X61: N | Y61: N | Z61: N | AA61: N | AB61: N | AC61: N | AD61: A | AE61: N | AF61: N
B62: O | C62: O | D62: F | E62: O | F62: O | G62: O | H62: F | I62: F | J62: F | K62: F | L62: F | M62: O | N62: F | O62: F | P62: F | Q62: F | R62: F | S62: OSIMO | T62: O | U62: O | V62: O | W62: O | X62: O | Y62: O | Z62: O | AA62: O | AB62: O | AC62: O | AD62: F | AE62: F | AF62: F
B63: 4 | C63: 422500009 | E63: 1500101001001 | F63: 77 | G63: 250000001 | I63: 00 | J63: 00 | K63: 000 | L63: 000000 | M63: 9 | Q63: 422500009 | R63: 00 | S63: 00 | T63: 251201 | U63: KXN | V63: 01 | W63: 000100 | X63: 01 | Y63: 0006313 | Z63: 0006313 | AA63: 055 | AB63: 0003472 | AC63: 0006313 | AE63: 1 | AF63: 0000000 | AG63: LIGNE A GENERER
A65: TYPE 5 FIN FACTURE | B65: Type d’enregistrement | C65: N° partenaire de santé + clé | D65: FILLER | E65: N° immatriculation assuré | F65: Clé N° immatriculation | G65: N° de facture | H65: FILLER | I65: Nombre d’enregistrements de Type 4 | J65: Zone réservée SESAM | K65: Total des montants facturés | L65: Total remboursable par la Caisse | M65: Total participation assuré avant participation de l’organisme complémentaire | N65: Total remboursable par l’organisme complémentaire | O65: Top éclatement des flux par l’OCT | P65: Zone réservée SESAM | Q65: Liste d’opposition | R65: FILLER | S65: Zone de certification
B66: 1 | C66: 2-10 | D66: 11 | E66: 12-24 | F66: 25-26 | G66: 27-35 | H66: 36-38 | I66: 39-41 | J66: 42-57 | K66: 58-65 | L66: 66-73 | M66: 74-81 | N66: 82-89 | O66: 90 | P66: 91-93 | Q66: 94 | R66: 95-96 | S66: 97-128
B67: 1 | C67: 9 | D67: 1 | E67: 13 | F67: 2 | G67: 9 | H67: 3 | I67: 3 | J67: 16 | K67: 8 | L67: 8 | M67: 8 | N67: 8 | O67: 1 | P67: 3 | Q67: 1 | R67: 2 | S67: 32
B68: N | C68: N | D68: A | E68: A | F68: N | G68: N | H68: A | I68: N | J68: A | K68: N | L68: N | M68: N | N68: N | O68: A | P68: A | Q68: A | R68: A | S68: A
B69: O | C69: O | D69: F | E69: O | F69: O | G69: O | H69: F | I69: O | J69: O | K69: O | L69: O | M69: O | N69: F | O69: F | P69: O | Q69: O | R69: F | S69: F
B70: 5 | C70: 422500009 | E70: 1500101001001 | F70: 77 | G70: 250000001 | I70: 004 | K70: 00009113 | L70: 00005012 | M70: 00004101 | N70: 00000000
A72: TYPE 6 FIN LOT | B72: Type d’enregistrement | C72: N° partenaire de santé + clé | D72: Nombre de factures | E72: Nombre de lignes actes | F72: Comptabilisation des enregistrements des types 2 | G72: Total de tous les enregistrements de type 5 | H72: Montant total général du lot prestations facturées | I72: Montant total général du lot prestations remboursables par l’organisme d’Ass. Maladie | J72: Montant total général du lot prestations remboursables par les organismes complémentaires | K72: N° de lot | L72: indicateur de marquage des factures du lot. | M72: Type de facture | N72: FILLER | O72: N° agrément progiciel de santé ou n° de certificat pour les logiciels établissements ou raison sociale éditeur | P72: N° agrément du dispositif portable | Q72: FILLER | R72: N° d’identification du PS remplaçant | S72: Zone de certification
B73: 1 | C73: 2-10 | D73: 11-13 | E73: 14-17 | F73: 18-21 | G73: 22-24 | H73: 25-33 | I73: 34-42 | J73: 43-51 | K73: 52-54 | L73: 55 | M73: 56 | N73: 57-60 | O73: 61-72 | P73: 73-84 | Q73: 85-87 | R73: 88-96 | S73: 97-128
B74: 1 | C74: 9 | D74: 3 | E74: 4 | F74: 4 | G74: 3 | H74: 9 | I74: 9 | J74: 9 | K74: 3 | L74: 1 | M74: 1 | N74: 4 | O74: 12 | P74: 12 | Q74: 3 | R74: 9 | S74: 32
B75: N | C75: N | D75: N | E75: N | F75: N | G75: N | H75: N | I75: N | J75: N | K75: N | L75: A | M75: A | N75: A | O75: A | P75: N | Q75: A | R75: N | S75: N
B76: O | C76: O | D76: O | E76: O | F76: O | G76: O | H76: O | I76: O | J76: O | K76: O | L76: F | M76: F | N76: F | O76: F | P76: F | Q76: F | R76: F | S76: O
B77: 6 | C77: 422500009 | D77: 001 | E77: 0002 | F77: 0002 | G77: 001 | H77: 000009113 | I77: 000005012 | J77: 000000000 | K77: 001 | O77: AAZZ2501BC12
A79: TYPE 999 FIN FICHIER | B79: Type d’enregistrement | C79: Type émetteur | D79: Numéro émetteur | E79: FILLER | F79: Type de destinataire | G79: Numéro de destinataire | H79: FILLER | I79: Application | J79: Identification du fichier | K79: Volume du fichier | L79: FILLER | M79: Nombre de lots | N79: FILLER
B80: 1-3 | C80: 4-5 | D80: 6-19 | E80: 20-25 | F80: 26-27 | G80: 28-41 | H80: 42-47 | I80: 48-49 | J80: 50-55 | K80: 56-63 | L80: 64-82 | M80: 83-85 | N80: 86-128
B81: 3 | C81: 2 | D81: 14 | E81: 6 | F81: 2 | G81: 14 | H81: 6 | I81: 2 | J81: 6 | K81: 8 | L81: 19 | M81: 3 | N81: 43
B82: N | C82: A | D82: N | E82: A | F82: A | G82: N | H82: A | I82: A | J82: A | K82: N | L82: A | M82: N | N82: A
B83: O | C83: O | D83: O | E83: F | F83: O | G83: O | H83: F | I83: O | J83: O | K83: O | L83: F | M83: O | N83: F
B84: 999 | C84: TP | D84: 00000422500009 | F84: CT | G84: 00000001000422 | I84: TR | J84: TESTB2 | K84: 00000011 | M84: 001

Sheet CONVENTION CAS 4
A1: Table des matières | B1: CARACTERISTIQUES METIERS DU OU DES TRAJETS FACTURES
A3: SOCIETE DE TAXI DE N° AM : 422500009 SPECIALITE : 56 | D3: CARACTERISTIQUE PATIENT | G3: CARACTERISTIQUES FACTURE | I3: CARACTERISTIQUES TRAJETS | Z3: ASSURE | AG3: PRESCRIPTEUR
A4: N°CAS | B4: NOMBRE DE TRAJETS FACTURES | C4: TRAJET N° : | D4: NATURE D'ASSURANCE | E4: TAUX | F4: C2S ? : O/N | G4: REFUS TRANSPORT PARTAGE | H4: TIERS PAYANT | I4: LIEU DEPART | J4: LIEU ARRIVEE | K4: DATE / HEURE DEPART | L4: DATE / HEURE ARRIVEE | M4: N° IMMATRICULATION VEHICULE | N4: COMMUNE D'ADS | O4: DEPARTEMENT D'ADS | P4: ORGANISME LOCAL D'ADS | Q4: DISTANCE PARCOURUE | R4: CONTEXTE : J, N , F | S4: NOMBRE DE MALADES | T4: SUPPLEMENT FORFAITAIRE ? : O / N | U4: PEAGES ? : O / N | V4: TPMR ? : O / N | W4: TRAJET EN LIEN AVEC HOSPITALISATION ET RETOUR A VIDE ? : O/N | X4: SI T PARTAGE : TRAJET SEUL > X KM ? : O/N | Z4: NIR | AA4: DATE DE NAISSANCE | AB4: RANG | AC4: REGIME | AD4: CAISSE | AE4: CENTRE | AG4: N°AM | AH4: SPECIALITE | AI4: NN°RPPS
A5: ='LISTE DES CAS ANNEXE 30'!A9 -> CONVENTION CAS 4 | B5: ='LISTE DES CAS ANNEXE 30'!B9 -> 1 | C5: ='LISTE DES CAS ANNEXE 30'!C9 -> 1 | D5: ='LISTE DES CAS ANNEXE 30'!D9 -> MALADIE | E5: ='LISTE DES CAS ANNEXE 30'!E9 -> 0.55 | F5: ='LISTE DES CAS ANNEXE 30'!H9 -> NON | G5: ='LISTE DES CAS ANNEXE 30'!I9 -> Sans objet | H5: ='LISTE DES CAS ANNEXE 30'!J9 -> 05 - TP AMO SEUL | I5: ='LISTE DES CAS ANNEXE 30'!K9 -> 42-SAINT-ETIENNE | J5: ='LISTE DES CAS ANNEXE 30'!L9 -> 69-LYON | K5: ='LISTE DES CAS ANNEXE 30'!M9 -> 01/12/2025 à 10H00 | L5: ='LISTE DES CAS ANNEXE 30'!N9 -> 01/12/2025 à 11h15 | M5: ='LISTE DES CAS ANNEXE 30'!O9 -> AA-001-BB | ... X5: ='LISTE DES CAS ANNEXE 30'!Z9 -> Sans objet | Z5: 1500101001001 | AA5: 500101 | AB5: 1 | AC5: 01 | AD5: 422 | AE5: 0000 | AG5: 421000001 | AH5: 01 | AI5: 11111110118
A7: FACTURE B2 CORRESPONDANT
A9: TYPE 000 DEBUT FICHIER | B9: Type d’enregistrement | C9: Type d’émetteur | D9: Numéro d’émetteur | E9: FILLER | F9: Type de destinataire | G9: N° de destinataire | H9: Date de réception du flux sur le frontal | I9: Application | J9: Identification du fichier | K9: Date de création du fichier | L9: Norme | M9: Version de Norme | N9: FILLER | O9: FILLER | P9: FILLER | Q9: FILLER | R9: Longueur d’enregistrement | S9: FILLER | T9: Zone message
B10: 1-3 | C10: 4-5 | D10: 6-19 | E10: 20-25 | F10: 26-27 | G10: 28-41 | H10: 42-47 | I10: 48-49 | J10: 50-55 | K10: 56-61 | L10: 62-65 | M10: 66-67 | N10: 68 | O10: 69 | P10: 70-72 | Q10: 73-82 | R10: 83-85 | S10: 86-91 | T10: 92-128
B11: 3 | C11: 2 | D11: 14 | E11: 6 | F11: 2 | G11: 14 | H11: 6 | I11: 2 | J11: 6 | K11: 6 | L11: 4 | M11: 2 | N11: 1 | O11: 1 | P11: 3 | Q11: 10 | R11: 3 | S11: 6 | T11: 37
B12: N | C12: A | D12: N | E12: A | F12: A | G12: N | H12: A | I12: A | J12: A | K12: N | L12: A | M12: A | N12: A | O12: A | P12: A | Q12: A | R12: N | S12: A | T12: N
B13: O | C13: O | D13: O | E13: F | F13: O | G13: O | H13: O | I13: O | J13: O | K13: O | L13: O | M13: O | N13: F | O13: F | P13: F | Q13: F | R13: F | S13: F | T13: O
B14: 000 | C14: TP | D14: 00000422500009 | F14: CT | G14: 00000001000422 | H14: 251231 | I14: TR | J14: TESTB2 | K14: 251231 | L14: TA | M14: B2 | R14: 128
A16: TYPE 1 DEBUT LOT | B16: Type d’enregistrement | C16: N° partenaire de santé + clé | D16: Origine du fichier | E16: N° d’organisme destinataire | F16: N° de lot | G16: Catégorie | H16: Statut juridique | I16: Mode de fixation des tarifs | J16: Nom ou raison sociale du partenaire de santé | K16: Version de norme utilisée | L16: Date de création du lot | M16: Filler | N16: Code norme | O16: Top certification du lot | P16: Numéro de version de norme | Q16: Unité monétaire de facturation | R16: Grand régime de la caisse pivot ou de la caisse de paiement unique privés, ou pour les établissements publics et privés antérieurement sous DG | S16: N° de la caisse pivot ou de la caisse de paiement unique | T16: Indication de dispositif Caisse Centralisatrice des Paiements ou de dispositif Caisse de Paiement Unique | U16: FILLER
B17: 1 | C17: 2-10 | D17: 11-16 | E17: 17-19 | F17: 20-22 | G17: 23-25 | H17: 26-27 | I17: 28-29 | J17: 30-69 | K17: 70-71 | L17: 72-77 | M17: 78 | N17: 79-80 | O17: 81 | P17: 82-87 | Q17: 88 | R17: 89-90 | S17: 91-93 | T17: 94 | U17: 95-128
B18: 1 | C18: 9 | D18: 6 | E18: 3 | F18: 3 | G18: 3 | H18: 2 | I18: 2 | J18: 40 | K18: 2 | L18: 6 | M18: 1 | N18: 2 | O18: 1 | P18: 6 | Q18: 1 | R18: 2 | S18: 3 | T18: 1 | U18: 34
B19: N | C19: N | D19: A | E19: N | F19: N | G19: A | H19: A | I19: A | J19: A | K19: A | L19: N | M19: A | N19: A | O19: A | P19: N | Q19: A | R19: A | S19: A | T19: N | U19: A
B20: O | C20: O | D20: F | E20: O | F20: O | G20: F | H20: F | I20: F | J20: O | K20: O | L20: O | M20: F | N20: O | O20: F | P20: O | Q20: F | R20: F | S20: F | T20: F | U20: FILLER
B21: 1 | C21: 422500009 | E21: 422 | F21: 001 | J21: SIMULATEUR B2 NOUVELLE CONVENTION TAXI | K21: B2 | L21: 251231 | N21: TA | P21: 062007 | Q21: U
A23: TYPE 2 DEBUT FACTURE | B23: Type d’enregistrement | C23: N° partenaire de santé + clé | D23: FILLER | E23: N° immatriculation assuré | F23: Clé N° immatriculation | G23: N° facture | H23: Complément du type | I23: Marquage de la facture | J23: Indicateur de forçage de la tarification de la part AMO | K23: Nature d’opération | L23: Date de facturation | M23: Top éclatement des flux par le PS | N23: Type de facture | O23: Facture sécurisée sur un dispositif portable | P23: Code Grand Régime | Q23: N° Caisse gestionnaire | R23: N° Centre gestionnaire | S23: Nature de la pièce justificative des droits | T23: N° prescripteur + clé | U23: Date de prescription | V23: Régime de prestation de l’assuré | W23: Nature d’assurance | X23: Justification d’exonération ou de modulation du ticket modérateur | Y23: Date Maternité | Z23: Numéro accident du travail ou date d’accident de droit commun | AA23: Présence d’une CPS de remplaçant pour sécurisation de la facture | AB23: Date de naissance du bénéficiaire | AC23: Rang de naissance | AD23: Rang de bénéficiaire | AE23: N° d’adhérent | AF23: Spécialité de prescripteur | AG23: Destinataire du règlement | AH23: Type de contrat souscrit auprès d’un organisme complémentaire | AI23: N° d’organisme complémentaire
B24: 1 | C24: 2-10 | D24: 11 | E24: 12-24 | F24: 25-26 | G24: 27-35 | H24: 36 | I24: 37 | J24: 38 | K24: 39 | L24: 40-45 | M24: 46 | N24: 47 | O24: 48 | P24: 49-50 | Q24: 51-53 | R24: 54-57 | S24: 58 | T24: 59-67 | U24: 68-73 | V24: 74-76 | W24: 77-78 | X24: 79 | Y24: 80-85 | Z24: 86-94 | AA24: 95 | AB24: 96-101 | AC24: 102 | AD24: 103-104 | AE24: 105-112 | AF24: 113-114 | AG24: 115-116 | AH24: 117-118 | AI24: 119-128
B25: 1 | C25: 9 | D25: 1 | E25: 13 | F25: 2 | G25: 9 | H25: 1 | I25: 1 | J25: 1 | K25: 1 | L25: 6 | M25: 1 | N25: 1 | O25: 1 | P25: 2 | Q25: 3 | R25: 4 | S25: 1 | T25: 9 | U25: 6 | V25: 3 | W25: 2 | X25: 1 | Y25: 6 | Z25: 9 | AA25: 1 | AB25: 6 | AC25: 1 | AD25: 2 | AE25: 8 | AF25: 2 | AG25: 2 | AH25: 2 | AI25: 10
B26: N | C26: N | D26: A | E26: A | F26: N | G26: N | H26: A | I26: A | J26: A | K26: N | L26: N | M26: A | N26: A | O26: A | P26: N | Q26: N | R26: N | S26: N | T26: N | U26: N | V26: A | W26: N | X26: A | Y26: N | Z26: N | AA26: A | AB26: N | AC26: N | AD26: A | AE26: A | AF26: N | AG26: N | AH26: N | AI26: A
B27: O | C27: O | D27: F | E27: O | F27: O | G27: O | H27: F | I27: F | J27: F | K27: O | L27: O | M27: F | N27: F | O27: F | P27: O | Q27: O | R27: O | S27: O | T27: O | U27: O | V27: F | W27: F | X27: O | Y27: F | Z27: F | AA27: O | AB27: O | AC27: F | AD27: F | AE27: F | AF27: F | AG27: F | AH27: F | AI27: F
B28: 2 | C28: 422500009 | E28: 1500101001001 | F28: 77 | G28: 250000001 | H28: A | K28: 1 | L28: 251231 | P28: 01 | Q28: 422 | R28: 0000 | S28: 2 | T28: 421000001 | U28: 250701 | W28: 10 | X28: 0 | Y28: 000000 | Z28: 000000000 | AB28: 500101 | AC28: 1 | AF28: 01 | AG28: 05 | AH28: 00
A30: TYPE 2E RPPS PRESCRIPTEUR | B30: Type d’enregistrement | C30: N° partenaire de santé + clé | D30: FILLER | E30: N° immatriculation assuré | F30: Clé N° immatriculation | G30: N° de facture | H30: Complément de type | I30: Identfifiant RPPS du prescripteur | J30: N° de la structure dans laquelle le PS a exécuté l’acte | K30: FILLER
B31: 1 | C31: 2-10 | D31: 11 | E31: 12-24 | F31: 25-26 | G31: 27-35 | H31: 36 | I31: 37-47 | J31: 48-61 | K31: 62-128
B32: 1 | C32: 9 | D32: 1 | E32: 13 | F32: 2 | G32: 9 | H32: 1 | I32: 11 | J32: 14 | K32: 67
B33: N | C33: N | D33: A | E33: A | F33: N | G33: N | H33: A | I33: N | J33: N | K33: A
B34: O | C34: O | D34: F | E34: O | F34: O | G34: O | H34: F | I34: F | J34: F | K34: F
B35: 2 | C35: 422500009 | E35: 1500101001001 | F35: 77 | G35: 250000001 | H35: E | I35: 11111110118 | AG35: LIGNE A GENERER
A37: TYPE 4A COMPOSANTE FORFAIT | B37: Type d’enregistrement | C37: N° partenaire de santé + clé | D37: FILLER | E37: N° immatriculation assuré | F37: Clé N° immatriculation | G37: N° de facture | H37: Complément de type | I37: Séquence | J37: Mode de traitement | K37: Discipline de prestations (ex DMT) | L37: Date de la demande d’accord préalable ou date d’accord de prise en charge CMU. | M37: Code accord préalable | N37: Séquence de renouvellement | O37: Code Participation assuré | P37: Justification d’exonération du Ticket Modérateur au niveau de l’acte | Q37: N° exécutant + clé ayant effectué l’acte ou fourni le produit | R37: Zone tarif de l’exécutant | S37: Spécialité de l’exécutant | T37: Date de l’acte, de la délivrance du produit | U37: Code acte | V37: Quantité d'actes | W37: Coefficient | X37: Dénombrement | Y37: Prix unitaire | Z37: Base de remboursement | AA37: Taux applicable à la prestation- | AB37: Montant remboursable par l’organisme d’Assurance Maladie Obligatoire | AC37: Montant des honoraires ou de la dépense (dépassement compris ou après remise pour la norme FR) | AD37: Qualificatif de la dépense | AE37: Code lieu | AF37: Montant remboursable par l’organisme complémentaire
B38: 1 | C38: 2-10 | D38: 11 | E38: 12-24 | F38: 25-26 | G38: 27-35 | H38: 36 | I38: 37-38 | J38: 39-40 | K38: 41-43 | L38: 44-49 | M38: 50 | N38: 51-52 | O38: 53 | P38: 54 | Q38: 55-63 | R38: 64-65 | S38: 66-67 | T38: 68-73 | U38: 74-78 | V38: 79-80 | W38: 81-86 | X38: 87-88 | Y38: 89-95 | Z38: 96-102 | AA38: 103-105 | AB38: 106-112 | AC38: 113-119 | AD38: 120 | AE38: 121 | AF38: 122-128
B39: 1 | C39: 9 | D39: 1 | E39: 13 | F39: 2 | G39: 9 | H39: 1 | I39: 2 | J39: 2 | K39: 3 | L39: 6 | M39: 1 | N39: 2 | O39: 1 | P39: 1 | Q39: 9 | R39: 2 | S39: 2 | T39: 6 | U39: 5 | V39: 2 | W39: 6 | X39: 2 | Y39: 7 | Z39: 7 | AA39: 3 | AB39: 7 | AC39: 7 | AD39: 1 | AE39: 1 | AF39: 7
B40: N | C40: N | D40: A | E40: A | F40: N | G40: N | H40: A | I40: N | J40: N | K40: N | L40: N | M40: N | N40: A | O40: A | P40: A | Q40: N | R40: N | S40: N | T40: N | U40: A | V40: N | W40: N | X40: N | Y40: N | Z40: N | AA40: N | AB40: N | AC40: N | AD40: A | AE40: N | AF40: N
B41: O | C41: O | D41: F | E41: O | F41: O | G41: O | H41: F | I41: F | J41: F | K41: F | L41: F | M41: O | N41: F | O41: F | P41: F | Q41: F | R41: F | S41: OSIMO | T41: O | U41: O | V41: O | W41: O | X41: O | Y41: O | Z41: O | AA41: O | AB41: O | AC41: O | AD41: F | AE41: F | AF41: F
B42: 4 | C42: 422500009 | E42: 1500101001001 | F42: 77 | G42: 250000001 | H42: A | I42: 00 | J42: 00 | K42: 000 | L42: 000000 | M42: 9 | Q42: 422500009 | R42: 00 | S42: 00 | T42: 251201 | U42: FX2 | V42: 01 | W42: 000100 | X42: 01 | Y42: 0002800 | Z42: 0002800 | AA42: 055 | AB42: 0001540 | AC42: 0002800 | AE42: 1 | AF42: 0000000 | AG42: LIGNE A GENERER
A44: TYPE 4T | B44: Type d’enregistrement | C44: N° partenaire de santé + clé | D44: FILLER | E44: N° immatriculation assuré | F44: Clé N° immatriculation | G44: N° de facture | H44: Complément du type | I44: Séquence | J44: Filler | K44: Série (au sens du décret du 6/5/88) | L44: Transport lié à une hospitalisation | M44: Longue distance | N44: Filler | O44: Forfait type de forfait | P44: Prix unitaire du forfait non majoré | Q44: Quantité forfaits | R44: Quantité forfaits majoration de nuit | S44: Quantité forfaits majoration dimanche ou fériés | T44: Prix unitaire du kilomètre non réduit. | U44: SANS MAJORATION : Quantité <ou=150 km | V44: Quantité >150 km | W44: MAJORATION NUIT : Quantité <ou=150 km | X44: Quantité >150 km | Y44: MAJORATION DIMANCHE/FERIE : Quantité <ou=150 km | Z44: Quantité >150 km | AA44: SUPPLEMENT : Type supplément | AB44: Quantité | AC44: Montant | AD44: PEAGES ET VOIES D'EAU Quantité | AE44: Montant | AF44: Montant global des abattements | AG44: Montant global des majorations pour courte distance | AH44: Filler
B45: 1 | C45: 2-10 | D45: 11 | E45: 12-24 | F45: 25-26 | G45: 27-35 | H45: 36 | I45: 37-38 | J45: 39-45 | K45: 46 | L45: 47 | M45: 48 | N45: 49 | O45: 50 | P45: 51-56 | Q45: 57-58 | R45: 59-60 | S45: 61-62 | T45: 63-68 | U45: 69-72 | V45: 73-76 | W45: 77-80 | X45: 81-84 | Y45: 85-88 | Z45: 89-92 | AA45: 93 | AB45: 94-95 | AC45: 96-101 | AD45: 102-103, | AE45: 104-109 | AF45: 110-116 | AG45: 117-123 | AH45: 142-128
B46: 1 | C46: 9 | D46: 1 | E46: 13 | F46: 2 | G46: 9 | H46: 1 | I46: 2 | J46: 7 | K46: 1 | L46: 1 | M46: 1 | N46: 1 | O46: 1 | P46: 6 | Q46: 2 | R46: 2 | S46: 2 | T46: 6 | U46: 4 | V46: 4 | W46: 4 | X46: 4 | Y46: 4 | Z46: 4 | AA46: 1 | AB46: 2 | AC46: 6 | AD46: 2 | AE46: 6 | AF46: 7 | AG46: 7 | AH46: 5
B47: N | C47: N | D47: A | E47: A | F47: N | G47: N | H47: A | I47: N | J47: A | K47: N | L47: N | M47: N | N47: A | O47: N | P47: N | Q47: N | R47: N | S47: N | T47: N | U47: N | V47: N | W47: N | X47: N | Y47: N | Z47: N | AA47: N | AB47: N | AC47: N | AD47: N | AE47: N | AF47: N | AG47: N | AH47: A
B48: O | C48: O | D48: F | E48: O | F48: O | G48: O | H48: O | I48: F | J48: F | K48: O | L48: O | M48: O | N48: F | O48: O | P48: F | Q48: F | R48: F | S48: F | T48: F | U48: F | V48: F | W48: F | X48: F | Y48: F | Z48: F | AA48: F | AB48: F | AC48: F | AD48: F | AE48: F | AF48: F | AG48: F | AH48: F
B49: 4 | C49: 422500009 | E49: 1500101001001 | F49: 77 | G49: 250000001 | H49: T | I49: 01 | K49: 0 | L49: 0 | M49: 0 | O49: 0 | P49: 000000 | Q49: 00 | R49: 00 | S49: 00 | T49: 000000 | U49: 0000 | V49: 0000 | W49: 0000 | X49: 0000 | Y49: 0000 | Z49: 0000 | AA49: 0 | AB49: 00 | AC49: 000000 | AD49: 00 | AE49: 000000 | AF49: 0000000 | AG49: 0000000
A51: TYPE 4U | B51: Type d’enregistrement | C51: N° partenaire de santé + clé | D51: FILLER | E51: N° immatriculation assuré | F51: Clé N° immatriculation | G51: N° de facture | H51: Complément du type | I51: Séquence | J51: Date départ | K51: Heure départ | L51: Lieu départ département commune | M51: N° véhicule | N51: Nom conducteur | O51: Prénom conducteur | P51: Nom accompagnateur | Q51: Prénom accompagnateur | R51: Date arrivée | S51: Heure arrivée | T51: Lieu d’arrivée | U51: Nombre malades | V51: % abattement | W51: Montant abattement | X51: Nombre de km facturés | Y51: Distance réelle parcourue | Z51: Utilisation du distancier | AA51: Niveau de certification | AB51: Montant de la majoration pour courte distance | AC51: Indicateur de période de réalisation du trajet | AD51: Filler
B52: 1 | C52: 2-10 | D52: 11 | E52: 12-24 | F52: 25-26 | G52: 27-35 | H52: 36 | I52: 37-38 | J52: 39-44 | K52: 45-48 | L52: 49-53 | M52: 54-62 | N52: 63-70 | O52: 71-73 | P52: 74-81 | Q52: 82-84 | R52: 85-90 | S52: 91-94 | T52: 95-99 | U52: 100 | V52: 101-102 | W52: 103-108 | X52: 109-112 | Y52: 113-116 | Z52: 117 | AA52: 118 | AB52: 119-124 | AC52: 125 | AD52: 126-128
B53: 1 | C53: 9 | D53: 1 | E53: 13 | F53: 2 | G53: 9 | H53: 1 | I53: 2 | J53: 6 | K53: 4 | L53: 5 | M53: 9 | N53: 8 | O53: 3 | P53: 8 | Q53: 3 | R53: 6 | S53: 4 | T53: 5 | U53: 1 | V53: 2 | W53: 6 | X53: 4 | Y53: 4 | Z53: 1 | AA53: 1 | AB53: 6 | AC53: 1 | AD53: 3
B54: N | C54: N | D54: A | E54: A | F54: N | G54: N | H54: A | I54: N | J54: N | K54: N | L54: N | M54: A | N54: A | O54: A | P54: A | Q54: A | R54: N | S54: N | T54: N | U54: N | V54: N | W54: N | X54: N | Y54: N | Z54: A | AA54: A | AB54: N | AC54: A | AD54: A
B55: O | C55: O | D55: F | E55: O | F55: O | G55: O | H55: O | I55: O | J55: O | K55: P | L55: O | M55: O | N55: O | O55: O | P55: F | Q55: F | R55: O | S55: O | T55: O | U55: O | V55: F | W55: F | X55: F | Y55: O | Z55: F | AA55: F | AB55: F | AC55: F | AD55: F
B56: 4 | C56: 422500009 | E56: 1500101001001 | F56: 77 | G56: 250000001 | H56: U | I56: 01 | J56: 251201 | K56: 1000 | L56: 42218 | M56: AA-001-BB | N56: NCONDUCA | O56: PRA | R56: 251201 | S56: 1115 | T56: 69123 | U56: 1 | V56: 00 | W56: 000000 | X56: 0000 | Y56: 0063 | AB56: 000000 | AE56: LIGNE A GENERER
A58: TYPE 4 COMPOSANTE "KM" | B58: Type d’enregistrement | C58: N° partenaire de santé + clé | D58: FILLER | E58: N° immatriculation assuré | F58: Clé N° immatriculation | G58: N° de facture | H58: Complément de type | I58: Séquence | J58: Mode de traitement | K58: Discipline de prestations (ex DMT) | L58: Date de la demande d’accord préalable ou date d’accord de prise en charge CMU. | M58: Code accord préalable | N58: Séquence de renouvellement | O58: Code Participation assuré | P58: Justification d’exonération du Ticket Modérateur au niveau de l’acte | Q58: N° exécutant + clé ayant effectué l’acte ou fourni le produit | R58: Zone tarif de l’exécutant | S58: Spécialité de l’exécutant | T58: Date de l’acte, de la délivrance du produit | U58: Code acte | V58: Quantité d'actes | W58: Coefficient | X58: Dénombrement | Y58: Prix unitaire | Z58: Base de remboursement | AA58: Taux applicable à la prestation- | AB58: Montant remboursable par l’organisme d’Assurance Maladie Obligatoire | AC58: Montant des honoraires ou de la dépense (dépassement compris ou après remise pour la norme FR) | AD58: Qualificatif de la dépense | AE58: Code lieu | AF58: Montant remboursable par l’organisme complémentaire
B59: 1 | C59: 2-10 | D59: 11 | E59: 12-24 | F59: 25-26 | G59: 27-35 | H59: 36 | I59: 37-38 | J59: 39-40 | K59: 41-43 | L59: 44-49 | M59: 50 | N59: 51-52 | O59: 53 | P59: 54 | Q59: 55-63 | R59: 64-65 | S59: 66-67 | T59: 68-73 | U59: 74-78 | V59: 79-80 | W59: 81-86 | X59: 87-88 | Y59: 89-95 | Z59: 96-102 | AA59: 103-105 | AB59: 106-112 | AC59: 113-119 | AD59: 120 | AE59: 121 | AF59: 122-128
B60: 1 | C60: 9 | D60: 1 | E60: 13 | F60: 2 | G60: 9 | H60: 1 | I60: 2 | J60: 2 | K60: 3 | L60: 6 | M60: 1 | N60: 2 | O60: 1 | P60: 1 | Q60: 9 | R60: 2 | S60: 2 | T60: 6 | U60: 5 | V60: 2 | W60: 6 | X60: 2 | Y60: 7 | Z60: 7 | AA60: 3 | AB60: 7 | AC60: 7 | AD60: 1 | AE60: 1 | AF60: 7
B61: N | C61: N | D61: A | E61: A | F61: N | G61: N | H61: A | I61: N | J61: N | K61: N | L61: N | M61: N | N61: A | O61: A | P61: A | Q61: N | R61: N | S61: N | T61: N | U61: A | V61: N | W61: N | X61: N | Y61: N | Z61: N | AA61: N | AB61: N | AC61: N | AD61: A | AE61: N | AF61: N
B62: O | C62: O | D62: F | E62: O | F62: O | G62: O | H62: F | I62: F | J62: F | K62: F | L62: F | M62: O | N62: F | O62: F | P62: F | Q62: F | R62: F | S62: OSIMO | T62: O | U62: O | V62: O | W62: O | X62: O | Y62: O | Z62: O | AA62: O | AB62: O | AC62: O | AD62: F | AE62: F | AF62: F
B63: 4 | C63: 422500009 | E63: 1500101001001 | F63: 77 | G63: 250000001 | I63: 00 | J63: 00 | K63: 000 | L63: 000000 | M63: 9 | Q63: 422500009 | R63: 00 | S63: 00 | T63: 251201 | U63: KXN | V63: 01 | W63: 000100 | X63: 01 | Y63: 0009558 | Z63: 0009558 | AA63: 055 | AB63: 0005257 | AC63: 0009558 | AE63: 1 | AF63: 0000000 | AG63: LIGNE A GENERER
A65: TYPE 4 TRACEUR RETOUR A VIDE | B65: Type d’enregistrement | C65: N° partenaire de santé + clé | D65: FILLER | E65: N° immatriculation assuré | F65: Clé N° immatriculation | G65: N° de facture | H65: Complément de type | I65: Séquence | J65: Mode de traitement | K65: Discipline de prestations (ex DMT) | L65: Date de la demande d’accord préalable ou date d’accord de prise en charge CMU. | M65: Code accord préalable | N65: Séquence de renouvellement | O65: Code Participation assuré | P65: Justification d’exonération du Ticket Modérateur au niveau de l’acte | Q65: N° exécutant + clé ayant effectué l’acte ou fourni le produit | R65: Zone tarif de l’exécutant | S65: Spécialité de l’exécutant | T65: Date de l’acte, de la délivrance du produit | U65: Code acte | V65: Quantité d'actes | W65: Coefficient | X65: Dénombrement | Y65: Prix unitaire | Z65: Base de remboursement | AA65: Taux applicable à la prestation- | AB65: Montant remboursable par l’organisme d’Assurance Maladie Obligatoire | AC65: Montant des honoraires ou de la dépense (dépassement compris ou après remise pour la norme FR) | AD65: Qualificatif de la dépense | AE65: Code lieu | AF65: Montant remboursable par l’organisme complémentaire
B66: 1 | C66: 2-10 | D66: 11 | E66: 12-24 | F66: 25-26 | G66: 27-35 | H66: 36 | I66: 37-38 | J66: 39-40 | K66: 41-43 | L66: 44-49 | M66: 50 | N66: 51-52 | O66: 53 | P66: 54 | Q66: 55-63 | R66: 64-65 | S66: 66-67 | T66: 68-73 | U66: 74-78 | V66: 79-80 | W66: 81-86 | X66: 87-88 | Y66: 89-95 | Z66: 96-102 | AA66: 103-105 | AB66: 106-112 | AC66: 113-119 | AD66: 120 | AE66: 121 | AF66: 122-128
B67: 1 | C67: 9 | D67: 1 | E67: 13 | F67: 2 | G67: 9 | H67: 1 | I67: 2 | J67: 2 | K67: 3 | L67: 6 | M67: 1 | N67: 2 | O67: 1 | P67: 1 | Q67: 9 | R67: 2 | S67: 2 | T67: 6 | U67: 5 | V67: 2 | W67: 6 | X67: 2 | Y67: 7 | Z67: 7 | AA67: 3 | AB67: 7 | AC67: 7 | AD67: 1 | AE67: 1 | AF67: 7
B68: N | C68: N | D68: A | E68: A | F68: N | G68: N | H68: A | I68: N | J68: N | K68: N | L68: N | M68: N | N68: A | O68: A | P68: A | Q68: N | R68: N | S68: N | T68: N | U68: A | V68: N | W68: N | X68: N | Y68: N | Z68: N | AA68: N | AB68: N | AC68: N | AD68: A | AE68: N | AF68: N
B69: O | C69: O | D69: F | E69: O | F69: O | G69: O | H69: F | I69: F | J69: F | K69: F | L69: F | M69: O | N69: F | O69: F | P69: F | Q69: F | R69: F | S69: OSIMO | T69: O | U69: O | V69: O | W69: O | X69: O | Y69: O | Z69: O | AA69: O | AB69: O | AC69: O | AD69: F | AE69: F | AF69: F
B70: 4 | C70: 422500009 | E70: 1500101001001 | F70: 77 | G70: 250000001 | I70: 00 | J70: 00 | K70: 000 | L70: 000000 | M70: 9 | Q70: 422500009 | R70: 00 | S70: 00 | T70: 251201 | U70: RX1 | V70: 01 | W70: 000100 | X70: 01 | Y70: 0000002 | Z70: 0000002 | AA70: 000 | AB70: 0000000 | AC70: 0000000 | AD70: G | AE70: 1 | AF70: 0000000 | AG70: LIGNE A GENERER
A72: TYPE 5 FIN FACTURE | B72: Type d’enregistrement | C72: N° partenaire de santé + clé | D72: FILLER | E72: N° immatriculation assuré | F72: Clé N° immatriculation | G72: N° de facture | H72: FILLER | I72: Nombre d’enregistrements de Type 4 | J72: Zone réservée SESAM | K72: Total des montants facturés | L72: Total remboursable par la Caisse | M72: Total participation assuré avant participation de l’organisme complémentaire | N72: Total remboursable par l’organisme complémentaire | O72: Top éclatement des flux par l’OCT | P72: Zone réservée SESAM | Q72: Liste d’opposition | R72: FILLER | S72: Zone de certification
B73: 1 | C73: 2-10 | D73: 11 | E73: 12-24 | F73: 25-26 | G73: 27-35 | H73: 36-38 | I73: 39-41 | J73: 42-57 | K73: 58-65 | L73: 66-73 | M73: 74-81 | N73: 82-89 | O73: 90 | P73: 91-93 | Q73: 94 | R73: 95-96 | S73: 97-128
B74: 1 | C74: 9 | D74: 1 | E74: 13 | F74: 2 | G74: 9 | H74: 3 | I74: 3 | J74: 16 | K74: 8 | L74: 8 | M74: 8 | N74: 8 | O74: 1 | P74: 3 | Q74: 1 | R74: 2 | S74: 32
B75: N | C75: N | D75: A | E75: A | F75: N | G75: N | H75: A | I75: N | J75: A | K75: N | L75: N | M75: N | N75: N | O75: A | P75: A | Q75: A | R75: A | S75: A
B76: O | C76: O | D76: F | E76: O | F76: O | G76: O | H76: F | I76: O | J76: O | K76: O | L76: O | M76: O | N76: F | O76: F | P76: O | Q76: O | R76: F | S76: F
B77: 5 | C77: 422500009 | E77: 1500101001001 | F77: 77 | G77: 250000001 | I77: 005 | K77: 00012358 | L77: 00006797 | M77: 00005561 | N77: 00000000
A79: TYPE 6 FIN LOT | B79: Type d’enregistrement | C79: N° partenaire de santé + clé | D79: Nombre de factures | E79: Nombre de lignes actes | F79: Comptabilisation des enregistrements des types 2 | G79: Total de tous les enregistrements de type 5 | H79: Montant total général du lot prestations facturées | I79: Montant total général du lot prestations remboursables par l’organisme d’Ass. Maladie | J79: Montant total général du lot prestations remboursables par les organismes complémentaires | K79: N° de lot | L79: indicateur de marquage des factures du lot. | M79: Type de facture | N79: FILLER | O79: N° agrément progiciel de santé ou n° de certificat pour les logiciels établissements ou raison sociale éditeur | P79: N° agrément du dispositif portable | Q79: FILLER | R79: N° d’identification du PS remplaçant | S79: Zone de certification
B80: 1 | C80: 2-10 | D80: 11-13 | E80: 14-17 | F80: 18-21 | G80: 22-24 | H80: 25-33 | I80: 34-42 | J80: 43-51 | K80: 52-54 | L80: 55 | M80: 56 | N80: 57-60 | O80: 61-72 | P80: 73-84 | Q80: 85-87 | R80: 88-96 | S80: 97-128
B81: 1 | C81: 9 | D81: 3 | E81: 4 | F81: 4 | G81: 3 | H81: 9 | I81: 9 | J81: 9 | K81: 3 | L81: 1 | M81: 1 | N81: 4 | O81: 12 | P81: 12 | Q81: 3 | R81: 9 | S81: 32
B82: N | C82: N | D82: N | E82: N | F82: N | G82: N | H82: N | I82: N | J82: N | K82: N | L82: A | M82: A | N82: A | O82: A | P82: N | Q82: A | R82: N | S82: N
B83: O | C83: O | D83: O | E83: O | F83: O | G83: O | H83: O | I83: O | J83: O | K83: O | L83: F | M83: F | N83: F | O83: F | P83: F | Q83: F | R83: F | S83: O
B84: 6 | C84: 422500009 | D84: 001 | E84: 0003 | F84: 0002 | G84: 001 | H84: 000012358 | I84: 000006797 | J84: 000000000 | K84: 001 | O84: AAZZ2501BC12
A86: TYPE 999 FIN FICHIER | B86: Type d’enregistrement | C86: Type émetteur | D86: Numéro émetteur | E86: FILLER | F86: Type de destinataire | G86: Numéro de destinataire | H86: FILLER | I86: Application | J86: Identification du fichier | K86: Volume du fichier | L86: FILLER | M86: Nombre de lots | N86: FILLER
B87: 1-3 | C87: 4-5 | D87: 6-19 | E87: 20-25 | F87: 26-27 | G87: 28-41 | H87: 42-47 | I87: 48-49 | J87: 50-55 | K87: 56-63 | L87: 64-82 | M87: 83-85 | N87: 86-128
B88: 3 | C88: 2 | D88: 14 | E88: 6 | F88: 2 | G88: 14 | H88: 6 | I88: 2 | J88: 6 | K88: 8 | L88: 19 | M88: 3 | N88: 43
B89: N | C89: A | D89: N | E89: A | F89: A | G89: N | H89: A | I89: A | J89: A | K89: N | L89: A | M89: N | N89: A
B90: O | C90: O | D90: O | E90: F | F90: O | G90: O | H90: F | I90: O | J90: O | K90: O | L90: F | M90: O | N90: F
B91: 999 | C91: TP | D91: 00000422500009 | F91: CT | G91: 00000001000422 | I91: TR | J91: TESTB2 | K91: 00000012 | M91: 001

Sheet CONVENTION CAS 5
A1: Table des matières | B1: CARACTERISTIQUES METIERS DU OU DES TRAJETS FACTURES
A3: SOCIETE DE TAXI DE N° AM : 422500009 SPECIALITE : 56 | D3: CARACTERISTIQUE PATIENT | G3: CARACTERISTIQUES FACTURE | I3: CARACTERISTIQUES TRAJETS | Z3: ASSURE | AG3: PRESCRIPTEUR
A4: N°CAS | B4: NOMBRE DE TRAJETS FACTURES | C4: TRAJET N° : | D4: NATURE D'ASSURANCE | E4: TAUX | F4: C2S ? : O/N | G4: REFUS TRANSPORT PARTAGE | H4: TIERS PAYANT | I4: LIEU DEPART | J4: LIEU ARRIVEE | K4: DATE / HEURE DEPART | L4: DATE / HEURE ARRIVEE | M4: N° IMMATRICULATION VEHICULE | N4: COMMUNE D'ADS | O4: DEPARTEMENT D'ADS | P4: ORGANISME LOCAL D'ADS | Q4: DISTANCE PARCOURUE | R4: CONTEXTE : J, N , F | S4: NOMBRE DE MALADES | T4: SUPPLEMENT FORFAITAIRE ? : O / N | U4: PEAGES ? : O / N | V4: TPMR ? : O / N | W4: TRAJET EN LIEN AVEC HOSPITALISATION ET RETOUR A VIDE ? : O/N | X4: SI T PARTAGE : TRAJET SEUL > X KM ? : O/N | Z4: NIR | AA4: DATE DE NAISSANCE | AB4: RANG | AC4: REGIME | AD4: CAISSE | AE4: CENTRE | AG4: N°AM | AH4: SPECIALITE | AI4: NN°RPPS
A5: ='LISTE DES CAS ANNEXE 30'!A11 -> CONVENTION CAS 5 | B5: ='LISTE DES CAS ANNEXE 30'!B11 -> 1 | C5: ='LISTE DES CAS ANNEXE 30'!C11 -> 1 | D5: ='LISTE DES CAS ANNEXE 30'!D11 -> MALADIE | E5: ='LISTE DES CAS ANNEXE 30'!E11 -> 0.55 | F5: ='LISTE DES CAS ANNEXE 30'!H11 -> NON | G5: ='LISTE DES CAS ANNEXE 30'!I11 -> Sans objet | H5: ='LISTE DES CAS ANNEXE 30'!J11 -> 05 - TP AMO SEUL | I5: ='LISTE DES CAS ANNEXE 30'!K11 -> 42-SAINT-ETIENNE | J5: ='LISTE DES CAS ANNEXE 30'!L11 -> 42-MONTBRISON | K5: ='LISTE DES CAS ANNEXE 30'!M11 -> 01/12/2025 à 10H00 | L5: ='LISTE DES CAS ANNEXE 30'!N11 -> 01/12/2025 à 10h50 | M5: ='LISTE DES CAS ANNEXE 30'!O11 -> AA-001-BB | ... X5: ='LISTE DES CAS ANNEXE 30'!Z11 -> Sans objet | Z5: 1500101001001 | AA5: 500101 | AB5: 1 | AC5: 01 | AD5: 422 | AE5: 0000 | AG5: 421000001 | AH5: 01 | AI5: 11111110118
A7: FACTURE B2 CORRESPONDANT
A9: TYPE 000 DEBUT FICHIER | B9: Type d’enregistrement | C9: Type d’émetteur | D9: Numéro d’émetteur | E9: FILLER | F9: Type de destinataire | G9: N° de destinataire | H9: Date de réception du flux sur le frontal | I9: Application | J9: Identification du fichier | K9: Date de création du fichier | L9: Norme | M9: Version de Norme | N9: FILLER | O9: FILLER | P9: FILLER | Q9: FILLER | R9: Longueur d’enregistrement | S9: FILLER | T9: Zone message
B10: 1-3 | C10: 4-5 | D10: 6-19 | E10: 20-25 | F10: 26-27 | G10: 28-41 | H10: 42-47 | I10: 48-49 | J10: 50-55 | K10: 56-61 | L10: 62-65 | M10: 66-67 | N10: 68 | O10: 69 | P10: 70-72 | Q10: 73-82 | R10: 83-85 | S10: 86-91 | T10: 92-128
B11: 3 | C11: 2 | D11: 14 | E11: 6 | F11: 2 | G11: 14 | H11: 6 | I11: 2 | J11: 6 | K11: 6 | L11: 4 | M11: 2 | N11: 1 | O11: 1 | P11: 3 | Q11: 10 | R11: 3 | S11: 6 | T11: 37
B12: N | C12: A | D12: N | E12: A | F12: A | G12: N | H12: A | I12: A | J12: A | K12: N | L12: A | M12: A | N12: A | O12: A | P12: A | Q12: A | R12: N | S12: A | T12: N
B13: O | C13: O | D13: O | E13: F | F13: O | G13: O | H13: O | I13: O | J13: O | K13: O | L13: O | M13: O | N13: F | O13: F | P13: F | Q13: F | R13: F | S13: F | T13: O
B14: 000 | C14: TP | D14: 00000422500009 | F14: CT | G14: 00000001000422 | H14: 251231 | I14: TR | J14: TESTB2 | K14: 251231 | L14: TA | M14: B2 | R14: 128
A16: TYPE 1 DEBUT LOT | B16: Type d’enregistrement | C16: N° partenaire de santé + clé | D16: Origine du fichier | E16: N° d’organisme destinataire | F16: N° de lot | G16: Catégorie | H16: Statut juridique | I16: Mode de fixation des tarifs | J16: Nom ou raison sociale du partenaire de santé | K16: Version de norme utilisée | L16: Date de création du lot | M16: Filler | N16: Code norme | O16: Top certification du lot | P16: Numéro de version de norme | Q16: Unité monétaire de facturation | R16: Grand régime de la caisse pivot ou de la caisse de paiement unique privés, ou pour les établissements publics et privés antérieurement sous DG | S16: N° de la caisse pivot ou de la caisse de paiement unique | T16: Indication de dispositif Caisse Centralisatrice des Paiements ou de dispositif Caisse de Paiement Unique | U16: FILLER
B17: 1 | C17: 2-10 | D17: 11-16 | E17: 17-19 | F17: 20-22 | G17: 23-25 | H17: 26-27 | I17: 28-29 | J17: 30-69 | K17: 70-71 | L17: 72-77 | M17: 78 | N17: 79-80 | O17: 81 | P17: 82-87 | Q17: 88 | R17: 89-90 | S17: 91-93 | T17: 94 | U17: 95-128
B18: 1 | C18: 9 | D18: 6 | E18: 3 | F18: 3 | G18: 3 | H18: 2 | I18: 2 | J18: 40 | K18: 2 | L18: 6 | M18: 1 | N18: 2 | O18: 1 | P18: 6 | Q18: 1 | R18: 2 | S18: 3 | T18: 1 | U18: 34
B19: N | C19: N | D19: A | E19: N | F19: N | G19: A | H19: A | I19: A | J19: A | K19: A | L19: N | M19: A | N19: A | O19: A | P19: N | Q19: A | R19: A | S19: A | T19: N | U19: A
B20: O | C20: O | D20: F | E20: O | F20: O | G20: F | H20: F | I20: F | J20: O | K20: O | L20: O | M20: F | N20: O | O20: F | P20: O | Q20: F | R20: F | S20: F | T20: F | U20: FILLER
B21: 1 | C21: 422500009 | E21: 422 | F21: 001 | J21: SIMULATEUR B2 NOUVELLE CONVENTION TAXI | K21: B2 | L21: 251231 | N21: TA | P21: 062007 | Q21: U
A23: TYPE 2 DEBUT FACTURE | B23: Type d’enregistrement | C23: N° partenaire de santé + clé | D23: FILLER | E23: N° immatriculation assuré | F23: Clé N° immatriculation | G23: N° facture | H23: Complément du type | I23: Marquage de la facture | J23: Indicateur de forçage de la tarification de la part AMO | K23: Nature d’opération | L23: Date de facturation | M23: Top éclatement des flux par le PS | N23: Type de facture | O23: Facture sécurisée sur un dispositif portable | P23: Code Grand Régime | Q23: N° Caisse gestionnaire | R23: N° Centre gestionnaire | S23: Nature de la pièce justificative des droits | T23: N° prescripteur + clé | U23: Date de prescription | V23: Régime de prestation de l’assuré | W23: Nature d’assurance | X23: Justification d’exonération ou de modulation du ticket modérateur | Y23: Date Maternité | Z23: Numéro accident du travail ou date d’accident de droit commun | AA23: Présence d’une CPS de remplaçant pour sécurisation de la facture | AB23: Date de naissance du bénéficiaire | AC23: Rang de naissance | AD23: Rang de bénéficiaire | AE23: N° d’adhérent | AF23: Spécialité de prescripteur | AG23: Destinataire du règlement | AH23: Type de contrat souscrit auprès d’un organisme complémentaire | AI23: N° d’organisme complémentaire
B24: 1 | C24: 2-10 | D24: 11 | E24: 12-24 | F24: 25-26 | G24: 27-35 | H24: 36 | I24: 37 | J24: 38 | K24: 39 | L24: 40-45 | M24: 46 | N24: 47 | O24: 48 | P24: 49-50 | Q24: 51-53 | R24: 54-57 | S24: 58 | T24: 59-67 | U24: 68-73 | V24: 74-76 | W24: 77-78 | X24: 79 | Y24: 80-85 | Z24: 86-94 | AA24: 95 | AB24: 96-101 | AC24: 102 | AD24: 103-104 | AE24: 105-112 | AF24: 113-114 | AG24: 115-116 | AH24: 117-118 | AI24: 119-128
B25: 1 | C25: 9 | D25: 1 | E25: 13 | F25: 2 | G25: 9 | H25: 1 | I25: 1 | J25: 1 | K25: 1 | L25: 6 | M25: 1 | N25: 1 | O25: 1 | P25: 2 | Q25: 3 | R25: 4 | S25: 1 | T25: 9 | U25: 6 | V25: 3 | W25: 2 | X25: 1 | Y25: 6 | Z25: 9 | AA25: 1 | AB25: 6 | AC25: 1 | AD25: 2 | AE25: 8 | AF25: 2 | AG25: 2 | AH25: 2 | AI25: 10
B26: N | C26: N | D26: A | E26: A | F26: N | G26: N | H26: A | I26: A | J26: A | K26: N | L26: N | M26: A | N26: A | O26: A | P26: N | Q26: N | R26: N | S26: N | T26: N | U26: N | V26: A | W26: N | X26: A | Y26: N | Z26: N | AA26: A | AB26: N | AC26: N | AD26: A | AE26: A | AF26: N | AG26: N | AH26: N | AI26: A
B27: O | C27: O | D27: F | E27: O | F27: O | G27: O | H27: F | I27: F | J27: F | K27: O | L27: O | M27: F | N27: F | O27: F | P27: O | Q27: O | R27: O | S27: O | T27: O | U27: O | V27: F | W27: F | X27: O | Y27: F | Z27: F | AA27: O | AB27: O | AC27: F | AD27: F | AE27: F | AF27: F | AG27: F | AH27: F | AI27: F
B28: 2 | C28: 422500009 | E28: 1500101001001 | F28: 77 | G28: 250000001 | H28: A | K28: 1 | L28: 251231 | P28: 01 | Q28: 422 | R28: 0000 | S28: 2 | T28: 421000001 | U28: 250701 | W28: 10 | X28: 0 | Y28: 000000 | Z28: 000000000 | AB28: 500101 | AC28: 1 | AF28: 01 | AG28: 05 | AH28: 00
A30: TYPE 2E RPPS PRESCRIPTEUR | B30: Type d’enregistrement | C30: N° partenaire de santé + clé | D30: FILLER | E30: N° immatriculation assuré | F30: Clé N° immatriculation | G30: N° de facture | H30: Complément de type | I30: Identfifiant RPPS du prescripteur | J30: N° de la structure dans laquelle le PS a exécuté l’acte | K30: FILLER
B31: 1 | C31: 2-10 | D31: 11 | E31: 12-24 | F31: 25-26 | G31: 27-35 | H31: 36 | I31: 37-47 | J31: 48-61 | K31: 62-128
B32: 1 | C32: 9 | D32: 1 | E32: 13 | F32: 2 | G32: 9 | H32: 1 | I32: 11 | J32: 14 | K32: 67
B33: N | C33: N | D33: A | E33: A | F33: N | G33: N | H33: A | I33: N | J33: N | K33: A
B34: O | C34: O | D34: F | E34: O | F34: O | G34: O | H34: F | I34: F | J34: F | K34: F
B35: 2 | C35: 422500009 | E35: 1500101001001 | F35: 77 | G35: 250000001 | H35: E | I35: 11111110118 | AG35: LIGNE A GENERER
A37: TYPE 4A COMPOSANTE FORFAIT | B37: Type d’enregistrement | C37: N° partenaire de santé + clé | D37: FILLER | E37: N° immatriculation assuré | F37: Clé N° immatriculation | G37: N° de facture | H37: Complément de type | I37: Séquence | J37: Mode de traitement | K37: Discipline de prestations (ex DMT) | L37: Date de la demande d’accord préalable ou date d’accord de prise en charge CMU. | M37: Code accord préalable | N37: Séquence de renouvellement | O37: Code Participation assuré | P37: Justification d’exonération du Ticket Modérateur au niveau de l’acte | Q37: N° exécutant + clé ayant effectué l’acte ou fourni le produit | R37: Zone tarif de l’exécutant | S37: Spécialité de l’exécutant | T37: Date de l’acte, de la délivrance du produit | U37: Code acte | V37: Quantité d'actes | W37: Coefficient | X37: Dénombrement | Y37: Prix unitaire | Z37: Base de remboursement | AA37: Taux applicable à la prestation- | AB37: Montant remboursable par l’organisme d’Assurance Maladie Obligatoire | AC37: Montant des honoraires ou de la dépense (dépassement compris ou après remise pour la norme FR) | AD37: Qualificatif de la dépense | AE37: Code lieu | AF37: Montant remboursable par l’organisme complémentaire
B38: 1 | C38: 2-10 | D38: 11 | E38: 12-24 | F38: 25-26 | G38: 27-35 | H38: 36 | I38: 37-38 | J38: 39-40 | K38: 41-43 | L38: 44-49 | M38: 50 | N38: 51-52 | O38: 53 | P38: 54 | Q38: 55-63 | R38: 64-65 | S38: 66-67 | T38: 68-73 | U38: 74-78 | V38: 79-80 | W38: 81-86 | X38: 87-88 | Y38: 89-95 | Z38: 96-102 | AA38: 103-105 | AB38: 106-112 | AC38: 113-119 | AD38: 120 | AE38: 121 | AF38: 122-128
B39: 1 | C39: 9 | D39: 1 | E39: 13 | F39: 2 | G39: 9 | H39: 1 | I39: 2 | J39: 2 | K39: 3 | L39: 6 | M39: 1 | N39: 2 | O39: 1 | P39: 1 | Q39: 9 | R39: 2 | S39: 2 | T39: 6 | U39: 5 | V39: 2 | W39: 6 | X39: 2 | Y39: 7 | Z39: 7 | AA39: 3 | AB39: 7 | AC39: 7 | AD39: 1 | AE39: 1 | AF39: 7
B40: N | C40: N | D40: A | E40: A | F40: N | G40: N | H40: A | I40: N | J40: N | K40: N | L40: N | M40: N | N40: A | O40: A | P40: A | Q40: N | R40: N | S40: N | T40: N | U40: A | V40: N | W40: N | X40: N | Y40: N | Z40: N | AA40: N | AB40: N | AC40: N | AD40: A | AE40: N | AF40: N
B41: O | C41: O | D41: F | E41: O | F41: O | G41: O | H41: F | I41: F | J41: F | K41: F | L41: F | M41: O | N41: F | O41: F | P41: F | Q41: F | R41: F | S41: OSIMO | T41: O | U41: O | V41: O | W41: O | X41: O | Y41: O | Z41: O | AA41: O | AB41: O | AC41: O | AD41: F | AE41: F | AF41: F
B42: 4 | C42: 422500009 | E42: 1500101001001 | F42: 77 | G42: 250000001 | H42: A | I42: 00 | J42: 00 | K42: 000 | L42: 000000 | M42: 9 | Q42: 422500009 | R42: 00 | S42: 00 | T42: 251201 | U42: FX1 | V42: 01 | W42: 000100 | X42: 01 | Y42: 0001300 | Z42: 0001300 | AA42: 055 | AB42: 0000715 | AC42: 0001300 | AE42: 1 | AF42: 0000000 | AG42: LIGNE A GENERER
A44: TYPE 4T | B44: Type d’enregistrement | C44: N° partenaire de santé + clé | D44: FILLER | E44: N° immatriculation assuré | F44: Clé N° immatriculation | G44: N° de facture | H44: Complément du type | I44: Séquence | J44: Filler | K44: Série (au sens du décret du 6/5/88) | L44: Transport lié à une hospitalisation | M44: Longue distance | N44: Filler | O44: Forfait type de forfait | P44: Prix unitaire du forfait non majoré | Q44: Quantité forfaits | R44: Quantité forfaits majoration de nuit | S44: Quantité forfaits majoration dimanche ou fériés | T44: Prix unitaire du kilomètre non réduit. | U44: SANS MAJORATION : Quantité <ou=150 km | V44: Quantité >150 km | W44: MAJORATION NUIT : Quantité <ou=150 km | X44: Quantité >150 km | Y44: MAJORATION DIMANCHE/FERIE : Quantité <ou=150 km | Z44: Quantité >150 km | AA44: SUPPLEMENT : Type supplément | AB44: Quantité | AC44: Montant | AD44: PEAGES ET VOIES D'EAU Quantité | AE44: Montant | AF44: Montant global des abattements | AG44: Montant global des majorations pour courte distance | AH44: Filler
B45: 1 | C45: 2-10 | D45: 11 | E45: 12-24 | F45: 25-26 | G45: 27-35 | H45: 36 | I45: 37-38 | J45: 39-45 | K45: 46 | L45: 47 | M45: 48 | N45: 49 | O45: 50 | P45: 51-56 | Q45: 57-58 | R45: 59-60 | S45: 61-62 | T45: 63-68 | U45: 69-72 | V45: 73-76 | W45: 77-80 | X45: 81-84 | Y45: 85-88 | Z45: 89-92 | AA45: 93 | AB45: 94-95 | AC45: 96-101 | AD45: 102-103, | AE45: 104-109 | AF45: 110-116 | AG45: 117-123 | AH45: 142-128
B46: 1 | C46: 9 | D46: 1 | E46: 13 | F46: 2 | G46: 9 | H46: 1 | I46: 2 | J46: 7 | K46: 1 | L46: 1 | M46: 1 | N46: 1 | O46: 1 | P46: 6 | Q46: 2 | R46: 2 | S46: 2 | T46: 6 | U46: 4 | V46: 4 | W46: 4 | X46: 4 | Y46: 4 | Z46: 4 | AA46: 1 | AB46: 2 | AC46: 6 | AD46: 2 | AE46: 6 | AF46: 7 | AG46: 7 | AH46: 5
B47: N | C47: N | D47: A | E47: A | F47: N | G47: N | H47: A | I47: N | J47: A | K47: N | L47: N | M47: N | N47: A | O47: N | P47: N | Q47: N | R47: N | S47: N | T47: N | U47: N | V47: N | W47: N | X47: N | Y47: N | Z47: N | AA47: N | AB47: N | AC47: N | AD47: N | AE47: N | AF47: N | AG47: N | AH47: A
B48: O | C48: O | D48: F | E48: O | F48: O | G48: O | H48: O | I48: F | J48: F | K48: O | L48: O | M48: O | N48: F | O48: O | P48: F | Q48: F | R48: F | S48: F | T48: F | U48: F | V48: F | W48: F | X48: F | Y48: F | Z48: F | AA48: F | AB48: F | AC48: F | AD48: F | AE48: F | AF48: F | AG48: F | AH48: F
B49: 4 | C49: 422500009 | E49: 1500101001001 | F49: 77 | G49: 250000001 | H49: T | I49: 01 | K49: 0 | L49: 0 | M49: 0 | O49: 0 | P49: 000000 | Q49: 00 | R49: 00 | S49: 00 | T49: 000000 | U49: 0000 | V49: 0000 | W49: 0000 | X49: 0000 | Y49: 0000 | Z49: 0000 | AA49: 0 | AB49: 00 | AC49: 000000 | AD49: 00 | AE49: 000000 | AF49: 0000000 | AG49: 0000000
A51: TYPE 4U | B51: Type d’enregistrement | C51: N° partenaire de santé + clé | D51: FILLER | E51: N° immatriculation assuré | F51: Clé N° immatriculation | G51: N° de facture | H51: Complément du type | I51: Séquence | J51: Date départ | K51: Heure départ | L51: Lieu départ département commune | M51: N° véhicule | N51: Nom conducteur | O51: Prénom conducteur | P51: Nom accompagnateur | Q51: Prénom accompagnateur | R51: Date arrivée | S51: Heure arrivée | T51: Lieu d’arrivée | U51: Nombre malades | V51: % abattement | W51: Montant abattement | X51: Nombre de km facturés | Y51: Distance réelle parcourue | Z51: Utilisation du distancier | AA51: Niveau de certification | AB51: Montant de la majoration pour courte distance | AC51: Indicateur de période de réalisation du trajet | AD51: Filler
B52: 1 | C52: 2-10 | D52: 11 | E52: 12-24 | F52: 25-26 | G52: 27-35 | H52: 36 | I52: 37-38 | J52: 39-44 | K52: 45-48 | L52: 49-53 | M52: 54-62 | N52: 63-70 | O52: 71-73 | P52: 74-81 | Q52: 82-84 | R52: 85-90 | S52: 91-94 | T52: 95-99 | U52: 100 | V52: 101-102 | W52: 103-108 | X52: 109-112 | Y52: 113-116 | Z52: 117 | AA52: 118 | AB52: 119-124 | AC52: 125 | AD52: 126-128
B53: 1 | C53: 9 | D53: 1 | E53: 13 | F53: 2 | G53: 9 | H53: 1 | I53: 2 | J53: 6 | K53: 4 | L53: 5 | M53: 9 | N53: 8 | O53: 3 | P53: 8 | Q53: 3 | R53: 6 | S53: 4 | T53: 5 | U53: 1 | V53: 2 | W53: 6 | X53: 4 | Y53: 4 | Z53: 1 | AA53: 1 | AB53: 6 | AC53: 1 | AD53: 3
B54: N | C54: N | D54: A | E54: A | F54: N | G54: N | H54: A | I54: N | J54: N | K54: N | L54: N | M54: A | N54: A | O54: A | P54: A | Q54: A | R54: N | S54: N | T54: N | U54: N | V54: N | W54: N | X54: N | Y54: N | Z54: A | AA54: A | AB54: N | AC54: A | AD54: A
B55: O | C55: O | D55: F | E55: O | F55: O | G55: O | H55: O | I55: O | J55: O | K55: P | L55: O | M55: O | N55: O | O55: O | P55: F | Q55: F | R55: O | S55: O | T55: O | U55: O | V55: F | W55: F | X55: F | Y55: O | Z55: F | AA55: F | AB55: F | AC55: F | AD55: F
B56: 4 | C56: 422500009 | E56: 1500101001001 | F56: 77 | G56: 250000001 | H56: U | I56: 01 | J56: 251201 | K56: 1000 | L56: 42218 | M56: AA-001-BB | N56: NCONDUCA | O56: PRA | R56: 251201 | S56: 1050 | T56: 42147 | U56: 1 | V56: 00 | W56: 000000 | X56: 0000 | Y56: 0040 | AB56: 000000 | AE56: LIGNE A GENERER
A58: TYPE 4 COMPOSANTE "KM" | B58: Type d’enregistrement | C58: N° partenaire de santé + clé | D58: FILLER | E58: N° immatriculation assuré | F58: Clé N° immatriculation | G58: N° de facture | H58: Complément de type | I58: Séquence | J58: Mode de traitement | K58: Discipline de prestations (ex DMT) | L58: Date de la demande d’accord préalable ou date d’accord de prise en charge CMU. | M58: Code accord préalable | N58: Séquence de renouvellement | O58: Code Participation assuré | P58: Justification d’exonération du Ticket Modérateur au niveau de l’acte | Q58: N° exécutant + clé ayant effectué l’acte ou fourni le produit | R58: Zone tarif de l’exécutant | S58: Spécialité de l’exécutant | T58: Date de l’acte, de la délivrance du produit | U58: Code acte | V58: Quantité d'actes | W58: Coefficient | X58: Dénombrement | Y58: Prix unitaire | Z58: Base de remboursement | AA58: Taux applicable à la prestation- | AB58: Montant remboursable par l’organisme d’Assurance Maladie Obligatoire | AC58: Montant des honoraires ou de la dépense (dépassement compris ou après remise pour la norme FR) | AD58: Qualificatif de la dépense | AE58: Code lieu | AF58: Montant remboursable par l’organisme complémentaire
B59: 1 | C59: 2-10 | D59: 11 | E59: 12-24 | F59: 25-26 | G59: 27-35 | H59: 36 | I59: 37-38 | J59: 39-40 | K59: 41-43 | L59: 44-49 | M59: 50 | N59: 51-52 | O59: 53 | P59: 54 | Q59: 55-63 | R59: 64-65 | S59: 66-67 | T59: 68-73 | U59: 74-78 | V59: 79-80 | W59: 81-86 | X59: 87-88 | Y59: 89-95 | Z59: 96-102 | AA59: 103-105 | AB59: 106-112 | AC59: 113-119 | AD59: 120 | AE59: 121 | AF59: 122-128
B60: 1 | C60: 9 | D60: 1 | E60: 13 | F60: 2 | G60: 9 | H60: 1 | I60: 2 | J60: 2 | K60: 3 | L60: 6 | M60: 1 | N60: 2 | O60: 1 | P60: 1 | Q60: 9 | R60: 2 | S60: 2 | T60: 6 | U60: 5 | V60: 2 | W60: 6 | X60: 2 | Y60: 7 | Z60: 7 | AA60: 3 | AB60: 7 | AC60: 7 | AD60: 1 | AE60: 1 | AF60: 7
B61: N | C61: N | D61: A | E61: A | F61: N | G61: N | H61: A | I61: N | J61: N | K61: N | L61: N | M61: N | N61: A | O61: A | P61: A | Q61: N | R61: N | S61: N | T61: N | U61: A | V61: N | W61: N | X61: N | Y61: N | Z61: N | AA61: N | AB61: N | AC61: N | AD61: A | AE61: N | AF61: N
B62: O | C62: O | D62: F | E62: O | F62: O | G62: O | H62: F | I62: F | J62: F | K62: F | L62: F | M62: O | N62: F | O62: F | P62: F | Q62: F | R62: F | S62: OSIMO | T62: O | U62: O | V62: O | W62: O | X62: O | Y62: O | Z62: O | AA62: O | AB62: O | AC62: O | AD62: F | AE62: F | AF62: F
B63: 4 | C63: 422500009 | E63: 1500101001001 | F63: 77 | G63: 250000001 | I63: 00 | J63: 00 | K63: 000 | L63: 000000 | M63: 9 | Q63: 422500009 | R63: 00 | S63: 00 | T63: 251201 | U63: KXN | V63: 01 | W63: 000100 | X63: 01 | Y63: 0003888 | Z63: 0003888 | AA63: 055 | AB63: 0002138 | AC63: 0003888 | AE63: 1 | AF63: 0000000 | AG63: LIGNE A GENERER
A65: TYPE 4 COMPOSANTE "SUPPLEMENT" | B65: Type d’enregistrement | C65: N° partenaire de santé + clé | D65: FILLER | E65: N° immatriculation assuré | F65: Clé N° immatriculation | G65: N° de facture | H65: Complément de type | I65: Séquence | J65: Mode de traitement | K65: Discipline de prestations (ex DMT) | L65: Date de la demande d’accord préalable ou date d’accord de prise en charge CMU. | M65: Code accord préalable | N65: Séquence de renouvellement | O65: Code Participation assuré | P65: Justification d’exonération du Ticket Modérateur au niveau de l’acte | Q65: N° exécutant + clé ayant effectué l’acte ou fourni le produit | R65: Zone tarif de l’exécutant | S65: Spécialité de l’exécutant | T65: Date de l’acte, de la délivrance du produit | U65: Code acte | V65: Quantité d'actes | W65: Coefficient | X65: Dénombrement | Y65: Prix unitaire | Z65: Base de remboursement | AA65: Taux applicable à la prestation- | AB65: Montant remboursable par l’organisme d’Assurance Maladie Obligatoire | AC65: Montant des honoraires ou de la dépense (dépassement compris ou après remise pour la norme FR) | AD65: Qualificatif de la dépense | AE65: Code lieu | AF65: Montant remboursable par l’organisme complémentaire
B66: 1 | C66: 2-10 | D66: 11 | E66: 12-24 | F66: 25-26 | G66: 27-35 | H66: 36 | I66: 37-38 | J66: 39-40 | K66: 41-43 | L66: 44-49 | M66: 50 | N66: 51-52 | O66: 53 | P66: 54 | Q66: 55-63 | R66: 64-65 | S66: 66-67 | T66: 68-73 | U66: 74-78 | V66: 79-80 | W66: 81-86 | X66: 87-88 | Y66: 89-95 | Z66: 96-102 | AA66: 103-105 | AB66: 106-112 | AC66: 113-119 | AD66: 120 | AE66: 121 | AF66: 122-128
B67: 1 | C67: 9 | D67: 1 | E67: 13 | F67: 2 | G67: 9 | H67: 1 | I67: 2 | J67: 2 | K67: 3 | L67: 6 | M67: 1 | N67: 2 | O67: 1 | P67: 1 | Q67: 9 | R67: 2 | S67: 2 | T67: 6 | U67: 5 | V67: 2 | W67: 6 | X67: 2 | Y67: 7 | Z67: 7 | AA67: 3 | AB67: 7 | AC67: 7 | AD67: 1 | AE67: 1 | AF67: 7
B68: N | C68: N | D68: A | E68: A | F68: N | G68: N | H68: A | I68: N | J68: N | K68: N | L68: N | M68: N | N68: A | O68: A | P68: A | Q68: N | R68: N | S68: N | T68: N | U68: A | V68: N | W68: N | X68: N | Y68: N | Z68: N | AA68: N | AB68: N | AC68: N | AD68: A | AE68: N | AF68: N
B69: O | C69: O | D69: F | E69: O | F69: O | G69: O | H69: F | I69: F | J69: F | K69: F | L69: F | M69: O | N69: F | O69: F | P69: F | Q69: F | R69: F | S69: OSIMO | T69: O | U69: O | V69: O | W69: O | X69: O | Y69: O | Z69: O | AA69: O | AB69: O | AC69: O | AD69: F | AE69: F | AF69: F
B70: 4 | C70: 422500009 | E70: 1500101001001 | F70: 77 | G70: 250000001 | I70: 00 | J70: 00 | K70: 000 | L70: 000000 | M70: 9 | Q70: 422500009 | R70: 00 | S70: 00 | T70: 251201 | U70: SX1 | V70: 01 | W70: 000100 | X70: 01 | Y70: 0000800 | Z70: 0000800 | AA70: 055 | AB70: 0000440 | AC70: 0000800 | AE70: 1 | AF70: 0000000 | AG70: LIGNE A GENERER
A72: TYPE 5 FIN FACTURE | B72: Type d’enregistrement | C72: N° partenaire de santé + clé | D72: FILLER | E72: N° immatriculation assuré | F72: Clé N° immatriculation | G72: N° de facture | H72: FILLER | I72: Nombre d’enregistrements de Type 4 | J72: Zone réservée SESAM | K72: Total des montants facturés | L72: Total remboursable par la Caisse | M72: Total participation assuré avant participation de l’organisme complémentaire | N72: Total remboursable par l’organisme complémentaire | O72: Top éclatement des flux par l’OCT | P72: Zone réservée SESAM | Q72: Liste d’opposition | R72: FILLER | S72: Zone de certification
B73: 1 | C73: 2-10 | D73: 11 | E73: 12-24 | F73: 25-26 | G73: 27-35 | H73: 36-38 | I73: 39-41 | J73: 42-57 | K73: 58-65 | L73: 66-73 | M73: 74-81 | N73: 82-89 | O73: 90 | P73: 91-93 | Q73: 94 | R73: 95-96 | S73: 97-128
B74: 1 | C74: 9 | D74: 1 | E74: 13 | F74: 2 | G74: 9 | H74: 3 | I74: 3 | J74: 16 | K74: 8 | L74: 8 | M74: 8 | N74: 8 | O74: 1 | P74: 3 | Q74: 1 | R74: 2 | S74: 32
B75: N | C75: N | D75: A | E75: A | F75: N | G75: N | H75: A | I75: N | J75: A | K75: N | L75: N | M75: N | N75: N | O75: A | P75: A | Q75: A | R75: A | S75: A
B76: O | C76: O | D76: F | E76: O | F76: O | G76: O | H76: F | I76: O | J76: O | K76: O | L76: O | M76: O | N76: F | O76: F | P76: O | Q76: O | R76: F | S76: F
B77: 5 | C77: 422500009 | E77: 1500101001001 | F77: 77 | G77: 250000001 | I77: 005 | K77: 00005988 | L77: 00003293 | M77: 00002695 | N77: 00000000
A79: TYPE 6 FIN LOT | B79: Type d’enregistrement | C79: N° partenaire de santé + clé | D79: Nombre de factures | E79: Nombre de lignes actes | F79: Comptabilisation des enregistrements des types 2 | G79: Total de tous les enregistrements de type 5 | H79: Montant total général du lot prestations facturées | I79: Montant total général du lot prestations remboursables par l’organisme d’Ass. Maladie | J79: Montant total général du lot prestations remboursables par les organismes complémentaires | K79: N° de lot | L79: indicateur de marquage des factures du lot. | M79: Type de facture | N79: FILLER | O79: N° agrément progiciel de santé ou n° de certificat pour les logiciels établissements ou raison sociale éditeur | P79: N° agrément du dispositif portable | Q79: FILLER | R79: N° d’identification du PS remplaçant | S79: Zone de certification
B80: 1 | C80: 2-10 | D80: 11-13 | E80: 14-17 | F80: 18-21 | G80: 22-24 | H80: 25-33 | I80: 34-42 | J80: 43-51 | K80: 52-54 | L80: 55 | M80: 56 | N80: 57-60 | O80: 61-72 | P80: 73-84 | Q80: 85-87 | R80: 88-96 | S80: 97-128
B81: 1 | C81: 9 | D81: 3 | E81: 4 | F81: 4 | G81: 3 | H81: 9 | I81: 9 | J81: 9 | K81: 3 | L81: 1 | M81: 1 | N81: 4 | O81: 12 | P81: 12 | Q81: 3 | R81: 9 | S81: 32
B82: N | C82: N | D82: N | E82: N | F82: N | G82: N | H82: N | I82: N | J82: N | K82: N | L82: A | M82: A | N82: A | O82: A | P82: N | Q82: A | R82: N | S82: N
B83: O | C83: O | D83: O | E83: O | F83: O | G83: O | H83: O | I83: O | J83: O | K83: O | L83: F | M83: F | N83: F | O83: F | P83: F | Q83: F | R83: F | S83: O
B84: 6 | C84: 422500009 | D84: 001 | E84: 0003 | F84: 0002 | G84: 001 | H84: 000005988 | I84: 000003293 | J84: 000000000 | K84: 001 | O84: AAZZ2501BC12
A86: TYPE 999 FIN FICHIER | B86: Type d’enregistrement | C86: Type émetteur | D86: Numéro émetteur | E86: FILLER | F86: Type de destinataire | G86: Numéro de destinataire | H86: FILLER | I86: Application | J86: Identification du fichier | K86: Volume du fichier | L86: FILLER | M86: Nombre de lots | N86: FILLER
B87: 1-3 | C87: 4-5 | D87: 6-19 | E87: 20-25 | F87: 26-27 | G87: 28-41 | H87: 42-47 | I87: 48-49 | J87: 50-55 | K87: 56-63 | L87: 64-82 | M87: 83-85 | N87: 86-128
B88: 3 | C88: 2 | D88: 14 | E88: 6 | F88: 2 | G88: 14 | H88: 6 | I88: 2 | J88: 6 | K88: 8 | L88: 19 | M88: 3 | N88: 43
B89: N | C89: A | D89: N | E89: A | F89: A | G89: N | H89: A | I89: A | J89: A | K89: N | L89: A | M89: N | N89: A
B90: O | C90: O | D90: O | E90: F | F90: O | G90: O | H90: F | I90: O | J90: O | K90: O | L90: F | M90: O | N90: F
B91: 999 | C91: TP | D91: 00000422500009 | F91: CT | G91: 00000001000422 | I91: TR | J91: TESTB2 | K91: 00000012 | M91: 001

Sheet CONVENTION CAS 6
A1: Table des matières | B1: CARACTERISTIQUES METIERS DU OU DES TRAJETS FACTURES
A3: SOCIETE DE TAXI DE N° AM : 422500009 SPECIALITE : 56 | D3: CARACTERISTIQUE PATIENT | G3: CARACTERISTIQUES FACTURE | I3: CARACTERISTIQUES TRAJETS | Z3: ASSURE | AG3: PRESCRIPTEUR
A4: N°CAS | B4: NOMBRE DE TRAJETS FACTURES | C4: TRAJET N° : | D4: NATURE D'ASSURANCE | E4: TAUX | F4: C2S ? : O/N | G4: REFUS TRANSPORT PARTAGE | H4: TIERS PAYANT | I4: LIEU DEPART | J4: LIEU ARRIVEE | K4: DATE / HEURE DEPART | L4: DATE / HEURE ARRIVEE | M4: N° IMMATRICULATION VEHICULE | N4: COMMUNE D'ADS | O4: DEPARTEMENT D'ADS | P4: ORGANISME LOCAL D'ADS | Q4: DISTANCE PARCOURUE | R4: CONTEXTE : J, N , F | S4: NOMBRE DE MALADES | T4: SUPPLEMENT FORFAITAIRE ? : O / N | U4: PEAGES ? : O / N | V4: TPMR ? : O / N | W4: TRAJET EN LIEN AVEC HOSPITALISATION ET RETOUR A VIDE ? : O/N | X4: SI T PARTAGE : TRAJET SEUL > X KM ? : O/N | Z4: NIR | AA4: DATE DE NAISSANCE | AB4: RANG | AC4: REGIME | AD4: CAISSE | AE4: CENTRE | AG4: N°AM | AH4: SPECIALITE | AI4: NN°RPPS
A5: ='LISTE DES CAS ANNEXE 30'!A13 -> CONVENTION CAS 6 | B5: ='LISTE DES CAS ANNEXE 30'!B13 -> 1 | C5: ='LISTE DES CAS ANNEXE 30'!C13 -> 1 | D5: ='LISTE DES CAS ANNEXE 30'!D13 -> MALADIE | E5: ='LISTE DES CAS ANNEXE 30'!E13 -> 0.55 | F5: ='LISTE DES CAS ANNEXE 30'!H13 -> NON | G5: ='LISTE DES CAS ANNEXE 30'!I13 -> Sans objet | H5: ='LISTE DES CAS ANNEXE 30'!J13 -> 05 - TP AMO SEUL | I5: ='LISTE DES CAS ANNEXE 30'!K13 -> 42-SAINT-ETIENNE | J5: ='LISTE DES CAS ANNEXE 30'!L13 -> 42-MONTBRISON | K5: ='LISTE DES CAS ANNEXE 30'!M13 -> 01/12/2025 à 10H00 | L5: ='LISTE DES CAS ANNEXE 30'!N13 -> 01/12/2025 à 10h40 | M5: ='LISTE DES CAS ANNEXE 30'!O13 -> AA-001-BB | ... X5: ='LISTE DES CAS ANNEXE 30'!Z13 -> Sans objet | Z5: 1500101001001 | AA5: 500101 | AB5: 1 | AC5: 01 | AD5: 422 | AE5: 0000 | AG5: 421000001 | AH5: 01 | AI5: 11111110118
A7: FACTURE B2 CORRESPONDANT
A9: TYPE 000 DEBUT FICHIER | B9: Type d’enregistrement | C9: Type d’émetteur | D9: Numéro d’émetteur | E9: FILLER | F9: Type de destinataire | G9: N° de destinataire | H9: Date de réception du flux sur le frontal | I9: Application | J9: Identification du fichier | K9: Date de création du fichier | L9: Norme | M9: Version de Norme | N9: FILLER | O9: FILLER | P9: FILLER | Q9: FILLER | R9: Longueur d’enregistrement | S9: FILLER | T9: Zone message
B10: 1-3 | C10: 4-5 | D10: 6-19 | E10: 20-25 | F10: 26-27 | G10: 28-41 | H10: 42-47 | I10: 48-49 | J10: 50-55 | K10: 56-61 | L10: 62-65 | M10: 66-67 | N10: 68 | O10: 69 | P10: 70-72 | Q10: 73-82 | R10: 83-85 | S10: 86-91 | T10: 92-128
B11: 3 | C11: 2 | D11: 14 | E11: 6 | F11: 2 | G11: 14 | H11: 6 | I11: 2 | J11: 6 | K11: 6 | L11: 4 | M11: 2 | N11: 1 | O11: 1 | P11: 3 | Q11: 10 | R11: 3 | S11: 6 | T11: 37
B12: N | C12: A | D12: N | E12: A | F12: A | G12: N | H12: A | I12: A | J12: A | K12: N | L12: A | M12: A | N12: A | O12: A | P12: A | Q12: A | R12: N | S12: A | T12: N
B13: O | C13: O | D13: O | E13: F | F13: O | G13: O | H13: O | I13: O | J13: O | K13: O | L13: O | M13: O | N13: F | O13: F | P13: F | Q13: F | R13: F | S13: F | T13: O
B14: 000 | C14: TP | D14: 00000422500009 | F14: CT | G14: 00000001000422 | H14: 251231 | I14: TR | J14: TESTB2 | K14: 251231 | L14: TA | M14: B2 | R14: 128
A16: TYPE 1 DEBUT LOT | B16: Type d’enregistrement | C16: N° partenaire de santé + clé | D16: Origine du fichier | E16: N° d’organisme destinataire | F16: N° de lot | G16: Catégorie | H16: Statut juridique | I16: Mode de fixation des tarifs | J16: Nom ou raison sociale du partenaire de santé | K16: Version de norme utilisée | L16: Date de création du lot | M16: Filler | N16: Code norme | O16: Top certification du lot | P16: Numéro de version de norme | Q16: Unité monétaire de facturation | R16: Grand régime de la caisse pivot ou de la caisse de paiement unique privés, ou pour les établissements publics et privés antérieurement sous DG | S16: N° de la caisse pivot ou de la caisse de paiement unique | T16: Indication de dispositif Caisse Centralisatrice des Paiements ou de dispositif Caisse de Paiement Unique | U16: FILLER
B17: 1 | C17: 2-10 | D17: 11-16 | E17: 17-19 | F17: 20-22 | G17: 23-25 | H17: 26-27 | I17: 28-29 | J17: 30-69 | K17: 70-71 | L17: 72-77 | M17: 78 | N17: 79-80 | O17: 81 | P17: 82-87 | Q17: 88 | R17: 89-90 | S17: 91-93 | T17: 94 | U17: 95-128
B18: 1 | C18: 9 | D18: 6 | E18: 3 | F18: 3 | G18: 3 | H18: 2 | I18: 2 | J18: 40 | K18: 2 | L18: 6 | M18: 1 | N18: 2 | O18: 1 | P18: 6 | Q18: 1 | R18: 2 | S18: 3 | T18: 1 | U18: 34
B19: N | C19: N | D19: A | E19: N | F19: N | G19: A | H19: A | I19: A | J19: A | K19: A | L19: N | M19: A | N19: A | O19: A | P19: N | Q19: A | R19: A | S19: A | T19: N | U19: A
B20: O | C20: O | D20: F | E20: O | F20: O | G20: F | H20: F | I20: F | J20: O | K20: O | L20: O | M20: F | N20: O | O20: F | P20: O | Q20: F | R20: F | S20: F | T20: F | U20: FILLER
B21: 1 | C21: 422500009 | E21: 422 | F21: 001 | J21: SIMULATEUR B2 NOUVELLE CONVENTION TAXI | K21: B2 | L21: 251231 | N21: TA | P21: 062007 | Q21: U
A23: TYPE 2 DEBUT FACTURE | B23: Type d’enregistrement | C23: N° partenaire de santé + clé | D23: FILLER | E23: N° immatriculation assuré | F23: Clé N° immatriculation | G23: N° facture | H23: Complément du type | I23: Marquage de la facture | J23: Indicateur de forçage de la tarification de la part AMO | K23: Nature d’opération | L23: Date de facturation | M23: Top éclatement des flux par le PS | N23: Type de facture | O23: Facture sécurisée sur un dispositif portable | P23: Code Grand Régime | Q23: N° Caisse gestionnaire | R23: N° Centre gestionnaire | S23: Nature de la pièce justificative des droits | T23: N° prescripteur + clé | U23: Date de prescription | V23: Régime de prestation de l’assuré | W23: Nature d’assurance | X23: Justification d’exonération ou de modulation du ticket modérateur | Y23: Date Maternité | Z23: Numéro accident du travail ou date d’accident de droit commun | AA23: Présence d’une CPS de remplaçant pour sécurisation de la facture | AB23: Date de naissance du bénéficiaire | AC23: Rang de naissance | AD23: Rang de bénéficiaire | AE23: N° d’adhérent | AF23: Spécialité de prescripteur | AG23: Destinataire du règlement | AH23: Type de contrat souscrit auprès d’un organisme complémentaire | AI23: N° d’organisme complémentaire
B24: 1 | C24: 2-10 | D24: 11 | E24: 12-24 | F24: 25-26 | G24: 27-35 | H24: 36 | I24: 37 | J24: 38 | K24: 39 | L24: 40-45 | M24: 46 | N24: 47 | O24: 48 | P24: 49-50 | Q24: 51-53 | R24: 54-57 | S24: 58 | T24: 59-67 | U24: 68-73 | V24: 74-76 | W24: 77-78 | X24: 79 | Y24: 80-85 | Z24: 86-94 | AA24: 95 | AB24: 96-101 | AC24: 102 | AD24: 103-104 | AE24: 105-112 | AF24: 113-114 | AG24: 115-116 | AH24: 117-118 | AI24: 119-128
B25: 1 | C25: 9 | D25: 1 | E25: 13 | F25: 2 | G25: 9 | H25: 1 | I25: 1 | J25: 1 | K25: 1 | L25: 6 | M25: 1 | N25: 1 | O25: 1 | P25: 2 | Q25: 3 | R25: 4 | S25: 1 | T25: 9 | U25: 6 | V25: 3 | W25: 2 | X25: 1 | Y25: 6 | Z25: 9 | AA25: 1 | AB25: 6 | AC25: 1 | AD25: 2 | AE25: 8 | AF25: 2 | AG25: 2 | AH25: 2 | AI25: 10
B26: N | C26: N | D26: A | E26: A | F26: N | G26: N | H26: A | I26: A | J26: A | K26: N | L26: N | M26: A | N26: A | O26: A | P26: N | Q26: N | R26: N | S26: N | T26: N | U26: N | V26: A | W26: N | X26: A | Y26: N | Z26: N | AA26: A | AB26: N | AC26: N | AD26: A | AE26: A | AF26: N | AG26: N | AH26: N | AI26: A
B27: O | C27: O | D27: F | E27: O | F27: O | G27: O | H27: F | I27: F | J27: F | K27: O | L27: O | M27: F | N27: F | O27: F | P27: O | Q27: O | R27: O | S27: O | T27: O | U27: O | V27: F | W27: F | X27: O | Y27: F | Z27: F | AA27: O | AB27: O | AC27: F | AD27: F | AE27: F | AF27: F | AG27: F | AH27: F | AI27: F
B28: 2 | C28: 422500009 | E28: 1500101001001 | F28: 77 | G28: 250000001 | H28: A | K28: 1 | L28: 251231 | P28: 01 | Q28: 422 | R28: 0000 | S28: 2 | T28: 421000001 | U28: 250701 | W28: 10 | X28: 0 | Y28: 000000 | Z28: 000000000 | AB28: 500101 | AC28: 1 | AF28: 01 | AG28: 05 | AH28: 00
A30: TYPE 2E RPPS PRESCRIPTEUR | B30: Type d’enregistrement | C30: N° partenaire de santé + clé | D30: FILLER | E30: N° immatriculation assuré | F30: Clé N° immatriculation | G30: N° de facture | H30: Complément de type | I30: Identfifiant RPPS du prescripteur | J30: N° de la structure dans laquelle le PS a exécuté l’acte | K30: FILLER
B31: 1 | C31: 2-10 | D31: 11 | E31: 12-24 | F31: 25-26 | G31: 27-35 | H31: 36 | I31: 37-47 | J31: 48-61 | K31: 62-128
B32: 1 | C32: 9 | D32: 1 | E32: 13 | F32: 2 | G32: 9 | H32: 1 | I32: 11 | J32: 14 | K32: 67
B33: N | C33: N | D33: A | E33: A | F33: N | G33: N | H33: A | I33: N | J33: N | K33: A
B34: O | C34: O | D34: F | E34: O | F34: O | G34: O | H34: F | I34: F | J34: F | K34: F
B35: 2 | C35: 422500009 | E35: 1500101001001 | F35: 77 | G35: 250000001 | H35: E | I35: 11111110118 | AG35: LIGNE A GENERER
A37: TYPE 4A COMPOSANTE FORFAIT | B37: Type d’enregistrement | C37: N° partenaire de santé + clé | D37: FILLER | E37: N° immatriculation assuré | F37: Clé N° immatriculation | G37: N° de facture | H37: Complément de type | I37: Séquence | J37: Mode de traitement | K37: Discipline de prestations (ex DMT) | L37: Date de la demande d’accord préalable ou date d’accord de prise en charge CMU. | M37: Code accord préalable | N37: Séquence de renouvellement | O37: Code Participation assuré | P37: Justification d’exonération du Ticket Modérateur au niveau de l’acte | Q37: N° exécutant + clé ayant effectué l’acte ou fourni le produit | R37: Zone tarif de l’exécutant | S37: Spécialité de l’exécutant | T37: Date de l’acte, de la délivrance du produit | U37: Code acte | V37: Quantité d'actes | W37: Coefficient | X37: Dénombrement | Y37: Prix unitaire | Z37: Base de remboursement | AA37: Taux applicable à la prestation- | AB37: Montant remboursable par l’organisme d’Assurance Maladie Obligatoire | AC37: Montant des honoraires ou de la dépense (dépassement compris ou après remise pour la norme FR) | AD37: Qualificatif de la dépense | AE37: Code lieu | AF37: Montant remboursable par l’organisme complémentaire
B38: 1 | C38: 2-10 | D38: 11 | E38: 12-24 | F38: 25-26 | G38: 27-35 | H38: 36 | I38: 37-38 | J38: 39-40 | K38: 41-43 | L38: 44-49 | M38: 50 | N38: 51-52 | O38: 53 | P38: 54 | Q38: 55-63 | R38: 64-65 | S38: 66-67 | T38: 68-73 | U38: 74-78 | V38: 79-80 | W38: 81-86 | X38: 87-88 | Y38: 89-95 | Z38: 96-102 | AA38: 103-105 | AB38: 106-112 | AC38: 113-119 | AD38: 120 | AE38: 121 | AF38: 122-128
B39: 1 | C39: 9 | D39: 1 | E39: 13 | F39: 2 | G39: 9 | H39: 1 | I39: 2 | J39: 2 | K39: 3 | L39: 6 | M39: 1 | N39: 2 | O39: 1 | P39: 1 | Q39: 9 | R39: 2 | S39: 2 | T39: 6 | U39: 5 | V39: 2 | W39: 6 | X39: 2 | Y39: 7 | Z39: 7 | AA39: 3 | AB39: 7 | AC39: 7 | AD39: 1 | AE39: 1 | AF39: 7
B40: N | C40: N | D40: A | E40: A | F40: N | G40: N | H40: A | I40: N | J40: N | K40: N | L40: N | M40: N | N40: A | O40: A | P40: A | Q40: N | R40: N | S40: N | T40: N | U40: A | V40: N | W40: N | X40: N | Y40: N | Z40: N | AA40: N | AB40: N | AC40: N | AD40: A | AE40: N | AF40: N
B41: O | C41: O | D41: F | E41: O | F41: O | G41: O | H41: F | I41: F | J41: F | K41: F | L41: F | M41: O | N41: F | O41: F | P41: F | Q41: F | R41: F | S41: OSIMO | T41: O | U41: O | V41: O | W41: O | X41: O | Y41: O | Z41: O | AA41: O | AB41: O | AC41: O | AD41: F | AE41: F | AF41: F
B42: 4 | C42: 422500009 | E42: 1500101001001 | F42: 77 | G42: 250000001 | H42: A | I42: 00 | J42: 00 | K42: 000 | L42: 000000 | M42: 9 | Q42: 422500009 | R42: 00 | S42: 00 | T42: 251201 | U42: FX1 | V42: 01 | W42: 000100 | X42: 01 | Y42: 0001300 | Z42: 0001300 | AA42: 055 | AB42: 0000715 | AC42: 0001300 | AE42: 1 | AF42: 0000000 | AG42: LIGNE A GENERER
A44: TYPE 4T | B44: Type d’enregistrement | C44: N° partenaire de santé + clé | D44: FILLER | E44: N° immatriculation assuré | F44: Clé N° immatriculation | G44: N° de facture | H44: Complément du type | I44: Séquence | J44: Filler | K44: Série (au sens du décret du 6/5/88) | L44: Transport lié à une hospitalisation | M44: Longue distance | N44: Filler | O44: Forfait type de forfait | P44: Prix unitaire du forfait non majoré | Q44: Quantité forfaits | R44: Quantité forfaits majoration de nuit | S44: Quantité forfaits majoration dimanche ou fériés | T44: Prix unitaire du kilomètre non réduit. | U44: SANS MAJORATION : Quantité <ou=150 km | V44: Quantité >150 km | W44: MAJORATION NUIT : Quantité <ou=150 km | X44: Quantité >150 km | Y44: MAJORATION DIMANCHE/FERIE : Quantité <ou=150 km | Z44: Quantité >150 km | AA44: SUPPLEMENT : Type supplément | AB44: Quantité | AC44: Montant | AD44: PEAGES ET VOIES D'EAU Quantité | AE44: Montant | AF44: Montant global des abattements | AG44: Montant global des majorations pour courte distance | AH44: Filler
B45: 1 | C45: 2-10 | D45: 11 | E45: 12-24 | F45: 25-26 | G45: 27-35 | H45: 36 | I45: 37-38 | J45: 39-45 | K45: 46 | L45: 47 | M45: 48 | N45: 49 | O45: 50 | P45: 51-56 | Q45: 57-58 | R45: 59-60 | S45: 61-62 | T45: 63-68 | U45: 69-72 | V45: 73-76 | W45: 77-80 | X45: 81-84 | Y45: 85-88 | Z45: 89-92 | AA45: 93 | AB45: 94-95 | AC45: 96-101 | AD45: 102-103, | AE45: 104-109 | AF45: 110-116 | AG45: 117-123 | AH45: 142-128
B46: 1 | C46: 9 | D46: 1 | E46: 13 | F46: 2 | G46: 9 | H46: 1 | I46: 2 | J46: 7 | K46: 1 | L46: 1 | M46: 1 | N46: 1 | O46: 1 | P46: 6 | Q46: 2 | R46: 2 | S46: 2 | T46: 6 | U46: 4 | V46: 4 | W46: 4 | X46: 4 | Y46: 4 | Z46: 4 | AA46: 1 | AB46: 2 | AC46: 6 | AD46: 2 | AE46: 6 | AF46: 7 | AG46: 7 | AH46: 5
B47: N | C47: N | D47: A | E47: A | F47: N | G47: N | H47: A | I47: N | J47: A | K47: N | L47: N | M47: N | N47: A | O47: N | P47: N | Q47: N | R47: N | S47: N | T47: N | U47: N | V47: N | W47: N | X47: N | Y47: N | Z47: N | AA47: N | AB47: N | AC47: N | AD47: N | AE47: N | AF47: N | AG47: N | AH47: A
B48: O | C48: O | D48: F | E48: O | F48: O | G48: O | H48: O | I48: F | J48: F | K48: O | L48: O | M48: O | N48: F | O48: O | P48: F | Q48: F | R48: F | S48: F | T48: F | U48: F | V48: F | W48: F | X48: F | Y48: F | Z48: F | AA48: F | AB48: F | AC48: F | AD48: F | AE48: F | AF48: F | AG48: F | AH48: F
B49: 4 | C49: 422500009 | E49: 1500101001001 | F49: 77 | G49: 250000001 | H49: T | I49: 01 | K49: 0 | L49: 0 | M49: 0 | O49: 0 | P49: 000000 | Q49: 00 | R49: 00 | S49: 00 | T49: 000000 | U49: 0000 | V49: 0000 | W49: 0000 | X49: 0000 | Y49: 0000 | Z49: 0000 | AA49: 0 | AB49: 00 | AC49: 000000 | AD49: 00 | AE49: 000000 | AF49: 0000000 | AG49: 0000000
A51: TYPE 4U | B51: Type d’enregistrement | C51: N° partenaire de santé + clé | D51: FILLER | E51: N° immatriculation assuré | F51: Clé N° immatriculation | G51: N° de facture | H51: Complément du type | I51: Séquence | J51: Date départ | K51: Heure départ | L51: Lieu départ département commune | M51: N° véhicule | N51: Nom conducteur | O51: Prénom conducteur | P51: Nom accompagnateur | Q51: Prénom accompagnateur | R51: Date arrivée | S51: Heure arrivée | T51: Lieu d’arrivée | U51: Nombre malades | V51: % abattement | W51: Montant abattement | X51: Nombre de km facturés | Y51: Distance réelle parcourue | Z51: Utilisation du distancier | AA51: Niveau de certification | AB51: Montant de la majoration pour courte distance | AC51: Indicateur de période de réalisation du trajet | AD51: Filler
B52: 1 | C52: 2-10 | D52: 11 | E52: 12-24 | F52: 25-26 | G52: 27-35 | H52: 36 | I52: 37-38 | J52: 39-44 | K52: 45-48 | L52: 49-53 | M52: 54-62 | N52: 63-70 | O52: 71-73 | P52: 74-81 | Q52: 82-84 | R52: 85-90 | S52: 91-94 | T52: 95-99 | U52: 100 | V52: 101-102 | W52: 103-108 | X52: 109-112 | Y52: 113-116 | Z52: 117 | AA52: 118 | AB52: 119-124 | AC52: 125 | AD52: 126-128
B53: 1 | C53: 9 | D53: 1 | E53: 13 | F53: 2 | G53: 9 | H53: 1 | I53: 2 | J53: 6 | K53: 4 | L53: 5 | M53: 9 | N53: 8 | O53: 3 | P53: 8 | Q53: 3 | R53: 6 | S53: 4 | T53: 5 | U53: 1 | V53: 2 | W53: 6 | X53: 4 | Y53: 4 | Z53: 1 | AA53: 1 | AB53: 6 | AC53: 1 | AD53: 3
B54: N | C54: N | D54: A | E54: A | F54: N | G54: N | H54: A | I54: N | J54: N | K54: N | L54: N | M54: A | N54: A | O54: A | P54: A | Q54: A | R54: N | S54: N | T54: N | U54: N | V54: N | W54: N | X54: N | Y54: N | Z54: A | AA54: A | AB54: N | AC54: A | AD54: A
B55: O | C55: O | D55: F | E55: O | F55: O | G55: O | H55: O | I55: O | J55: O | K55: P | L55: O | M55: O | N55: O | O55: O | P55: F | Q55: F | R55: O | S55: O | T55: O | U55: O | V55: F | W55: F | X55: F | Y55: O | Z55: F | AA55: F | AB55: F | AC55: F | AD55: F
B56: 4 | C56: 422500009 | E56: 1500101001001 | F56: 77 | G56: 250000001 | H56: U | I56: 01 | J56: 251201 | K56: 1000 | L56: 42218 | M56: AA-001-BB | N56: NCONDUCA | O56: PRA | R56: 251201 | S56: 1040 | T56: 42147 | U56: 1 | V56: 00 | W56: 000000 | X56: 0000 | Y56: 0043 | AB56: 000000 | AE56: LIGNE A GENERER
A58: TYPE 4 COMPOSANTE "KM" | B58: Type d’enregistrement | C58: N° partenaire de santé + clé | D58: FILLER | E58: N° immatriculation assuré | F58: Clé N° immatriculation | G58: N° de facture | H58: Complément de type | I58: Séquence | J58: Mode de traitement | K58: Discipline de prestations (ex DMT) | L58: Date de la demande d’accord préalable ou date d’accord de prise en charge CMU. | M58: Code accord préalable | N58: Séquence de renouvellement | O58: Code Participation assuré | P58: Justification d’exonération du Ticket Modérateur au niveau de l’acte | Q58: N° exécutant + clé ayant effectué l’acte ou fourni le produit | R58: Zone tarif de l’exécutant | S58: Spécialité de l’exécutant | T58: Date de l’acte, de la délivrance du produit | U58: Code acte | V58: Quantité d'actes | W58: Coefficient | X58: Dénombrement | Y58: Prix unitaire | Z58: Base de remboursement | AA58: Taux applicable à la prestation- | AB58: Montant remboursable par l’organisme d’Assurance Maladie Obligatoire | AC58: Montant des honoraires ou de la dépense (dépassement compris ou après remise pour la norme FR) | AD58: Qualificatif de la dépense | AE58: Code lieu | AF58: Montant remboursable par l’organisme complémentaire
B59: 1 | C59: 2-10 | D59: 11 | E59: 12-24 | F59: 25-26 | G59: 27-35 | H59: 36 | I59: 37-38 | J59: 39-40 | K59: 41-43 | L59: 44-49 | M59: 50 | N59: 51-52 | O59: 53 | P59: 54 | Q59: 55-63 | R59: 64-65 | S59: 66-67 | T59: 68-73 | U59: 74-78 | V59: 79-80 | W59: 81-86 | X59: 87-88 | Y59: 89-95 | Z59: 96-102 | AA59: 103-105 | AB59: 106-112 | AC59: 113-119 | AD59: 120 | AE59: 121 | AF59: 122-128
B60: 1 | C60: 9 | D60: 1 | E60: 13 | F60: 2 | G60: 9 | H60: 1 | I60: 2 | J60: 2 | K60: 3 | L60: 6 | M60: 1 | N60: 2 | O60: 1 | P60: 1 | Q60: 9 | R60: 2 | S60: 2 | T60: 6 | U60: 5 | V60: 2 | W60: 6 | X60: 2 | Y60: 7 | Z60: 7 | AA60: 3 | AB60: 7 | AC60: 7 | AD60: 1 | AE60: 1 | AF60: 7
B61: N | C61: N | D61: A | E61: A | F61: N | G61: N | H61: A | I61: N | J61: N | K61: N | L61: N | M61: N | N61: A | O61: A | P61: A | Q61: N | R61: N | S61: N | T61: N | U61: A | V61: N | W61: N | X61: N | Y61: N | Z61: N | AA61: N | AB61: N | AC61: N | AD61: A | AE61: N | AF61: N
B62: O | C62: O | D62: F | E62: O | F62: O | G62: O | H62: F | I62: F | J62: F | K62: F | L62: F | M62: O | N62: F | O62: F | P62: F | Q62: F | R62: F | S62: OSIMO | T62: O | U62: O | V62: O | W62: O | X62: O | Y62: O | Z62: O | AA62: O | AB62: O | AC62: O | AD62: F | AE62: F | AF62: F
B63: 4 | C63: 422500009 | E63: 1500101001001 | F63: 77 | G63: 250000001 | I63: 00 | J63: 00 | K63: 000 | L63: 000000 | M63: 9 | Q63: 422500009 | R63: 00 | S63: 00 | T63: 251201 | U63: KXN | V63: 01 | W63: 000100 | X63: 01 | Y63: 0004212 | Z63: 0004212 | AA63: 055 | AB63: 0002317 | AC63: 0004212 | AE63: 1 | AF63: 0000000 | AG63: LIGNE A GENERER
A65: TYPE 4 COMPOSANTE "PEAGE" | B65: Type d’enregistrement | C65: N° partenaire de santé + clé | D65: FILLER | E65: N° immatriculation assuré | F65: Clé N° immatriculation | G65: N° de facture | H65: Complément de type | I65: Séquence | J65: Mode de traitement | K65: Discipline de prestations (ex DMT) | L65: Date de la demande d’accord préalable ou date d’accord de prise en charge CMU. | M65: Code accord préalable | N65: Séquence de renouvellement | O65: Code Participation assuré | P65: Justification d’exonération du Ticket Modérateur au niveau de l’acte | Q65: N° exécutant + clé ayant effectué l’acte ou fourni le produit | R65: Zone tarif de l’exécutant | S65: Spécialité de l’exécutant | T65: Date de l’acte, de la délivrance du produit | U65: Code acte | V65: Quantité d'actes | W65: Coefficient | X65: Dénombrement | Y65: Prix unitaire | Z65: Base de remboursement | AA65: Taux applicable à la prestation- | AB65: Montant remboursable par l’organisme d’Assurance Maladie Obligatoire | AC65: Montant des honoraires ou de la dépense (dépassement compris ou après remise pour la norme FR) | AD65: Qualificatif de la dépense | AE65: Code lieu | AF65: Montant remboursable par l’organisme complémentaire
B66: 1 | C66: 2-10 | D66: 11 | E66: 12-24 | F66: 25-26 | G66: 27-35 | H66: 36 | I66: 37-38 | J66: 39-40 | K66: 41-43 | L66: 44-49 | M66: 50 | N66: 51-52 | O66: 53 | P66: 54 | Q66: 55-63 | R66: 64-65 | S66: 66-67 | T66: 68-73 | U66: 74-78 | V66: 79-80 | W66: 81-86 | X66: 87-88 | Y66: 89-95 | Z66: 96-102 | AA66: 103-105 | AB66: 106-112 | AC66: 113-119 | AD66: 120 | AE66: 121 | AF66: 122-128
B67: 1 | C67: 9 | D67: 1 | E67: 13 | F67: 2 | G67: 9 | H67: 1 | I67: 2 | J67: 2 | K67: 3 | L67: 6 | M67: 1 | N67: 2 | O67: 1 | P67: 1 | Q67: 9 | R67: 2 | S67: 2 | T67: 6 | U67: 5 | V67: 2 | W67: 6 | X67: 2 | Y67: 7 | Z67: 7 | AA67: 3 | AB67: 7 | AC67: 7 | AD67: 1 | AE67: 1 | AF67: 7
B68: N | C68: N | D68: A | E68: A | F68: N | G68: N | H68: A | I68: N | J68: N | K68: N | L68: N | M68: N | N68: A | O68: A | P68: A | Q68: N | R68: N | S68: N | T68: N | U68: A | V68: N | W68: N | X68: N | Y68: N | Z68: N | AA68: N | AB68: N | AC68: N | AD68: A | AE68: N | AF68: N
B69: O | C69: O | D69: F | E69: O | F69: O | G69: O | H69: F | I69: F | J69: F | K69: F | L69: F | M69: O | N69: F | O69: F | P69: F | Q69: F | R69: F | S69: OSIMO | T69: O | U69: O | V69: O | W69: O | X69: O | Y69: O | Z69: O | AA69: O | AB69: O | AC69: O | AD69: F | AE69: F | AF69: F
B70: 4 | C70: 422500009 | E70: 1500101001001 | F70: 77 | G70: 250000001 | I70: 00 | J70: 00 | K70: 000 | L70: 000000 | M70: 9 | Q70: 422500009 | R70: 00 | S70: 00 | T70: 251201 | U70: PEA | V70: 01 | W70: 000100 | X70: 01 | Y70: 0000120 | Z70: 0000120 | AA70: 055 | AB70: 0000066 | AC70: 0000120 | AE70: 1 | AF70: 0000000 | AG70: LIGNE A GENERER
A72: TYPE 5 FIN FACTURE | B72: Type d’enregistrement | C72: N° partenaire de santé + clé | D72: FILLER | E72: N° immatriculation assuré | F72: Clé N° immatriculation | G72: N° de facture | H72: FILLER | I72: Nombre d’enregistrements de Type 4 | J72: Zone réservée SESAM | K72: Total des montants facturés | L72: Total remboursable par la Caisse | M72: Total participation assuré avant participation de l’organisme complémentaire | N72: Total remboursable par l’organisme complémentaire | O72: Top éclatement des flux par l’OCT | P72: Zone réservée SESAM | Q72: Liste d’opposition | R72: FILLER | S72: Zone de certification
B73: 1 | C73: 2-10 | D73: 11 | E73: 12-24 | F73: 25-26 | G73: 27-35 | H73: 36-38 | I73: 39-41 | J73: 42-57 | K73: 58-65 | L73: 66-73 | M73: 74-81 | N73: 82-89 | O73: 90 | P73: 91-93 | Q73: 94 | R73: 95-96 | S73: 97-128
B74: 1 | C74: 9 | D74: 1 | E74: 13 | F74: 2 | G74: 9 | H74: 3 | I74: 3 | J74: 16 | K74: 8 | L74: 8 | M74: 8 | N74: 8 | O74: 1 | P74: 3 | Q74: 1 | R74: 2 | S74: 32
B75: N | C75: N | D75: A | E75: A | F75: N | G75: N | H75: A | I75: N | J75: A | K75: N | L75: N | M75: N | N75: N | O75: A | P75: A | Q75: A | R75: A | S75: A
B76: O | C76: O | D76: F | E76: O | F76: O | G76: O | H76: F | I76: O | J76: O | K76: O | L76: O | M76: O | N76: F | O76: F | P76: O | Q76: O | R76: F | S76: F
B77: 5 | C77: 422500009 | E77: 1500101001001 | F77: 77 | G77: 250000001 | I77: 005 | K77: 00005632 | L77: 00003098 | M77: 00002534 | N77: 00000000
A79: TYPE 6 FIN LOT | B79: Type d’enregistrement | C79: N° partenaire de santé + clé | D79: Nombre de factures | E79: Nombre de lignes actes | F79: Comptabilisation des enregistrements des types 2 | G79: Total de tous les enregistrements de type 5 | H79: Montant total général du lot prestations facturées | I79: Montant total général du lot prestations remboursables par l’organisme d’Ass. Maladie | J79: Montant total général du lot prestations remboursables par les organismes complémentaires | K79: N° de lot | L79: indicateur de marquage des factures du lot. | M79: Type de facture | N79: FILLER | O79: N° agrément progiciel de santé ou n° de certificat pour les logiciels établissements ou raison sociale éditeur | P79: N° agrément du dispositif portable | Q79: FILLER | R79: N° d’identification du PS remplaçant | S79: Zone de certification
B80: 1 | C80: 2-10 | D80: 11-13 | E80: 14-17 | F80: 18-21 | G80: 22-24 | H80: 25-33 | I80: 34-42 | J80: 43-51 | K80: 52-54 | L80: 55 | M80: 56 | N80: 57-60 | O80: 61-72 | P80: 73-84 | Q80: 85-87 | R80: 88-96 | S80: 97-128
B81: 1 | C81: 9 | D81: 3 | E81: 4 | F81: 4 | G81: 3 | H81: 9 | I81: 9 | J81: 9 | K81: 3 | L81: 1 | M81: 1 | N81: 4 | O81: 12 | P81: 12 | Q81: 3 | R81: 9 | S81: 32
B82: N | C82: N | D82: N | E82: N | F82: N | G82: N | H82: N | I82: N | J82: N | K82: N | L82: A | M82: A | N82: A | O82: A | P82: N | Q82: A | R82: N | S82: N
B83: O | C83: O | D83: O | E83: O | F83: O | G83: O | H83: O | I83: O | J83: O | K83: O | L83: F | M83: F | N83: F | O83: F | P83: F | Q83: F | R83: F | S83: O
B84: 6 | C84: 422500009 | D84: 001 | E84: 0003 | F84: 0002 | G84: 001 | H84: 000005632 | I84: 000003098 | J84: 000000000 | K84: 001 | O84: AAZZ2501BC12
A86: TYPE 999 FIN FICHIER | B86: Type d’enregistrement | C86: Type émetteur | D86: Numéro émetteur | E86: FILLER | F86: Type de destinataire | G86: Numéro de destinataire | H86: FILLER | I86: Application | J86: Identification du fichier | K86: Volume du fichier | L86: FILLER | M86: Nombre de lots | N86: FILLER
B87: 1-3 | C87: 4-5 | D87: 6-19 | E87: 20-25 | F87: 26-27 | G87: 28-41 | H87: 42-47 | I87: 48-49 | J87: 50-55 | K87: 56-63 | L87: 64-82 | M87: 83-85 | N87: 86-128
B88: 3 | C88: 2 | D88: 14 | E88: 6 | F88: 2 | G88: 14 | H88: 6 | I88: 2 | J88: 6 | K88: 8 | L88: 19 | M88: 3 | N88: 43
B89: N | C89: A | D89: N | E89: A | F89: A | G89: N | H89: A | I89: A | J89: A | K89: N | L89: A | M89: N | N89: A
B90: O | C90: O | D90: O | E90: F | F90: O | G90: O | H90: F | I90: O | J90: O | K90: O | L90: F | M90: O | N90: F
B91: 999 | C91: TP | D91: 00000422500009 | F91: CT | G91: 00000001000422 | I91: TR | J91: TESTB2 | K91: 00000012 | M91: 001

Sheet CONVENTION CAS 7
A1: Table des matières | B1: CARACTERISTIQUES METIERS DU OU DES TRAJETS FACTURES
A3: SOCIETE DE TAXI DE N° AM : 422500009 SPECIALITE : 56 | D3: CARACTERISTIQUE PATIENT | G3: CARACTERISTIQUES FACTURE | I3: CARACTERISTIQUES TRAJETS | Z3: ASSURE | AG3: PRESCRIPTEUR
A4: N°CAS | B4: NOMBRE DE TRAJETS FACTURES | C4: TRAJET N° : | D4: NATURE D'ASSURANCE | E4: TAUX | F4: C2S ? : O/N | G4: REFUS TRANSPORT PARTAGE | H4: TIERS PAYANT | I4: LIEU DEPART | J4: LIEU ARRIVEE | K4: DATE / HEURE DEPART | L4: DATE / HEURE ARRIVEE | M4: N° IMMATRICULATION VEHICULE | N4: COMMUNE D'ADS | O4: DEPARTEMENT D'ADS | P4: ORGANISME LOCAL D'ADS | Q4: DISTANCE PARCOURUE | R4: CONTEXTE : J, N , F | S4: NOMBRE DE MALADES | T4: SUPPLEMENT FORFAITAIRE ? : O / N | U4: PEAGES ? : O / N | V4: TPMR ? : O / N | W4: TRAJET EN LIEN AVEC HOSPITALISATION ET RETOUR A VIDE ? : O/N | X4: SI T PARTAGE : TRAJET SEUL > X KM ? : O/N | Z4: NIR | AA4: DATE DE NAISSANCE | AB4: RANG | AC4: REGIME | AD4: CAISSE | AE4: CENTRE | AG4: N°AM | AH4: SPECIALITE | AI4: NN°RPPS
A5: ='LISTE DES CAS ANNEXE 30'!A15 -> CONVENTION CAS 7 | B5: ='LISTE DES CAS ANNEXE 30'!B15 -> 2 | C5: ='LISTE DES CAS ANNEXE 30'!C15 -> 1 | D5: ='LISTE DES CAS ANNEXE 30'!D15 -> MALADIE | E5: ='LISTE DES CAS ANNEXE 30'!E15 -> 0.55 | F5: ='LISTE DES CAS ANNEXE 30'!H15 -> NON | G5: ='LISTE DES CAS ANNEXE 30'!I15 -> Sans objet | H5: ='LISTE DES CAS ANNEXE 30'!J15 -> 05 - TP AMO SEUL | I5: ='LISTE DES CAS ANNEXE 30'!K15 -> 42-SAINT-ETIENNE | J5: ='LISTE DES CAS ANNEXE 30'!L15 -> 42-MONTBRISON | K5: ='LISTE DES CAS ANNEXE 30'!M15 -> 01/12/2025 à 10H00 | L5: ='LISTE DES CAS ANNEXE 30'!N15 -> 01/12/2025 à 10h50 | M5: ='LISTE DES CAS ANNEXE 30'!O15 -> AA-001-BB | ... X5: ='LISTE DES CAS ANNEXE 30'!Z15 -> Sans objet | Z5: 1500101001001 | AA5: 500101 | AB5: 1 | AC5: 01 | AD5: 422 | AE5: 0000 | AG5: 421000001 | AH5: 01 | AI5: 11111110118
C6: ='LISTE DES CAS ANNEXE 30'!C16 -> 2 | G6: ='LISTE DES CAS ANNEXE 30'!I16 -> Sans objet | I6: ='LISTE DES CAS ANNEXE 30'!K16 -> 42-MONTBRISON | J6: ='LISTE DES CAS ANNEXE 30'!L16 -> 42-SAINT-ETIENNE | K6: ='LISTE DES CAS ANNEXE 30'!M16 -> 01/12/2025 à 13H00 | L6: ='LISTE DES CAS ANNEXE 30'!N16 -> 01/12/2025 à 13h50 | M6: ='LISTE DES CAS ANNEXE 30'!O16 -> AA-001-BB | N6: ='LISTE DES CAS ANNEXE 30'!P16 -> 42218 (SAINT-ETIENNE) | O6: ='LISTE DES CAS ANNEXE 30'!Q16 -> 042 | P6: ='LISTE DES CAS ANNEXE 30'!R16 -> 422 - CPAM DE LA LOIRE | ... X6: ='LISTE DES CAS ANNEXE 30'!Z16 -> Sans objet
A8: FACTURE B2 CORRESPONDANT
A10: TYPE 000 DEBUT FICHIER | B10: Type d’enregistrement | C10: Type d’émetteur | D10: Numéro d’émetteur | E10: FILLER | F10: Type de destinataire | G10: N° de destinataire | H10: Date de réception du flux sur le frontal | I10: Application | J10: Identification du fichier | K10: Date de création du fichier | L10: Norme | M10: Version de Norme | N10: FILLER | O10: FILLER | P10: FILLER | Q10: FILLER | R10: Longueur d’enregistrement | S10: FILLER | T10: Zone message
B11: 1-3 | C11: 4-5 | D11: 6-19 | E11: 20-25 | F11: 26-27 | G11: 28-41 | H11: 42-47 | I11: 48-49 | J11: 50-55 | K11: 56-61 | L11: 62-65 | M11: 66-67 | N11: 68 | O11: 69 | P11: 70-72 | Q11: 73-82 | R11: 83-85 | S11: 86-91 | T11: 92-128
B12: 3 | C12: 2 | D12: 14 | E12: 6 | F12: 2 | G12: 14 | H12: 6 | I12: 2 | J12: 6 | K12: 6 | L12: 4 | M12: 2 | N12: 1 | O12: 1 | P12: 3 | Q12: 10 | R12: 3 | S12: 6 | T12: 37
B13: N | C13: A | D13: N | E13: A | F13: A | G13: N | H13: A | I13: A | J13: A | K13: N | L13: A | M13: A | N13: A | O13: A | P13: A | Q13: A | R13: N | S13: A | T13: N
B14: O | C14: O | D14: O | E14: F | F14: O | G14: O | H14: O | I14: O | J14: O | K14: O | L14: O | M14: O | N14: F | O14: F | P14: F | Q14: F | R14: F | S14: F | T14: O
B15: 000 | C15: TP | D15: 00000422500009 | F15: CT | G15: 00000001000422 | H15: 251231 | I15: TR | J15: TESTB2 | K15: 251231 | L15: TA | M15: B2 | R15: 128
A17: TYPE 1 DEBUT LOT | B17: Type d’enregistrement | C17: N° partenaire de santé + clé | D17: Origine du fichier | E17: N° d’organisme destinataire | F17: N° de lot | G17: Catégorie | H17: Statut juridique | I17: Mode de fixation des tarifs | J17: Nom ou raison sociale du partenaire de santé | K17: Version de norme utilisée | L17: Date de création du lot | M17: Filler | N17: Code norme | O17: Top certification du lot | P17: Numéro de version de norme | Q17: Unité monétaire de facturation | R17: Grand régime de la caisse pivot ou de la caisse de paiement unique privés, ou pour les établissements publics et privés antérieurement sous DG | S17: N° de la caisse pivot ou de la caisse de paiement unique | T17: Indication de dispositif Caisse Centralisatrice des Paiements ou de dispositif Caisse de Paiement Unique | U17: FILLER
B18: 1 | C18: 2-10 | D18: 11-16 | E18: 17-19 | F18: 20-22 | G18: 23-25 | H18: 26-27 | I18: 28-29 | J18: 30-69 | K18: 70-71 | L18: 72-77 | M18: 78 | N18: 79-80 | O18: 81 | P18: 82-87 | Q18: 88 | R18: 89-90 | S18: 91-93 | T18: 94 | U18: 95-128
B19: 1 | C19: 9 | D19: 6 | E19: 3 | F19: 3 | G19: 3 | H19: 2 | I19: 2 | J19: 40 | K19: 2 | L19: 6 | M19: 1 | N19: 2 | O19: 1 | P19: 6 | Q19: 1 | R19: 2 | S19: 3 | T19: 1 | U19: 34
B20: N | C20: N | D20: A | E20: N | F20: N | G20: A | H20: A | I20: A | J20: A | K20: A | L20: N | M20: A | N20: A | O20: A | P20: N | Q20: A | R20: A | S20: A | T20: N | U20: A
B21: O | C21: O | D21: F | E21: O | F21: O | G21: F | H21: F | I21: F | J21: O | K21: O | L21: O | M21: F | N21: O | O21: F | P21: O | Q21: F | R21: F | S21: F | T21: F | U21: FILLER
B22: 1 | C22: 422500009 | E22: 422 | F22: 001 | J22: SIMULATEUR B2 NOUVELLE CONVENTION TAXI | K22: B2 | L22: 251231 | N22: TA | P22: 062007 | Q22: U
A24: TYPE 2 DEBUT FACTURE | B24: Type d’enregistrement | C24: N° partenaire de santé + clé | D24: FILLER | E24: N° immatriculation assuré | F24: Clé N° immatriculation | G24: N° facture | H24: Complément du type | I24: Marquage de la facture | J24: Indicateur de forçage de la tarification de la part AMO | K24: Nature d’opération | L24: Date de facturation | M24: Top éclatement des flux par le PS | N24: Type de facture | O24: Facture sécurisée sur un dispositif portable | P24: Code Grand Régime | Q24: N° Caisse gestionnaire | R24: N° Centre gestionnaire | S24: Nature de la pièce justificative des droits | T24: N° prescripteur + clé | U24: Date de prescription | V24: Régime de prestation de l’assuré | W24: Nature d’assurance | X24: Justification d’exonération ou de modulation du ticket modérateur | Y24: Date Maternité | Z24: Numéro accident du travail ou date d’accident de droit commun | AA24: Présence d’une CPS de remplaçant pour sécurisation de la facture | AB24: Date de naissance du bénéficiaire | AC24: Rang de naissance | AD24: Rang de bénéficiaire | AE24: N° d’adhérent | AF24: Spécialité de prescripteur | AG24: Destinataire du règlement | AH24: Type de contrat souscrit auprès d’un organisme complémentaire | AI24: N° d’organisme complémentaire
B25: 1 | C25: 2-10 | D25: 11 | E25: 12-24 | F25: 25-26 | G25: 27-35 | H25: 36 | I25: 37 | J25: 38 | K25: 39 | L25: 40-45 | M25: 46 | N25: 47 | O25: 48 | P25: 49-50 | Q25: 51-53 | R25: 54-57 | S25: 58 | T25: 59-67 | U25: 68-73 | V25: 74-76 | W25: 77-78 | X25: 79 | Y25: 80-85 | Z25: 86-94 | AA25: 95 | AB25: 96-101 | AC25: 102 | AD25: 103-104 | AE25: 105-112 | AF25: 113-114 | AG25: 115-116 | AH25: 117-118 | AI25: 119-128
B26: 1 | C26: 9 | D26: 1 | E26: 13 | F26: 2 | G26: 9 | H26: 1 | I26: 1 | J26: 1 | K26: 1 | L26: 6 | M26: 1 | N26: 1 | O26: 1 | P26: 2 | Q26: 3 | R26: 4 | S26: 1 | T26: 9 | U26: 6 | V26: 3 | W26: 2 | X26: 1 | Y26: 6 | Z26: 9 | AA26: 1 | AB26: 6 | AC26: 1 | AD26: 2 | AE26: 8 | AF26: 2 | AG26: 2 | AH26: 2 | AI26: 10
B27: N | C27: N | D27: A | E27: A | F27: N | G27: N | H27: A | I27: A | J27: A | K27: N | L27: N | M27: A | N27: A | O27: A | P27: N | Q27: N | R27: N | S27: N | T27: N | U27: N | V27: A | W27: N | X27: A | Y27: N | Z27: N | AA27: A | AB27: N | AC27: N | AD27: A | AE27: A | AF27: N | AG27: N | AH27: N | AI27: A
B28: O | C28: O | D28: F | E28: O | F28: O | G28: O | H28: F | I28: F | J28: F | K28: O | L28: O | M28: F | N28: F | O28: F | P28: O | Q28: O | R28: O | S28: O | T28: O | U28: O | V28: F | W28: F | X28: O | Y28: F | Z28: F | AA28: O | AB28: O | AC28: F | AD28: F | AE28: F | AF28: F | AG28: F | AH28: F | AI28: F
B29: 2 | C29: 422500009 | E29: 1500101001001 | F29: 77 | G29: 250000001 | H29: A | K29: 1 | L29: 251231 | P29: 01 | Q29: 422 | R29: 0000 | S29: 2 | T29: 421000001 | U29: 250701 | W29: 10 | X29: 0 | Y29: 000000 | Z29: 000000000 | AB29: 500101 | AC29: 1 | AF29: 01 | AG29: 05 | AH29: 00
A31: TYPE 2E RPPS PRESCRIPTEUR | B31: Type d’enregistrement | C31: N° partenaire de santé + clé | D31: FILLER | E31: N° immatriculation assuré | F31: Clé N° immatriculation | G31: N° de facture | H31: Complément de type | I31: Identfifiant RPPS du prescripteur | J31: N° de la structure dans laquelle le PS a exécuté l’acte | K31: FILLER
B32: 1 | C32: 2-10 | D32: 11 | E32: 12-24 | F32: 25-26 | G32: 27-35 | H32: 36 | I32: 37-47 | J32: 48-61 | K32: 62-128
B33: 1 | C33: 9 | D33: 1 | E33: 13 | F33: 2 | G33: 9 | H33: 1 | I33: 11 | J33: 14 | K33: 67
B34: N | C34: N | D34: A | E34: A | F34: N | G34: N | H34: A | I34: N | J34: N | K34: A
B35: O | C35: O | D35: F | E35: O | F35: O | G35: O | H35: F | I35: F | J35: F | K35: F
B36: 2 | C36: 422500009 | E36: 1500101001001 | F36: 77 | G36: 250000001 | H36: E | I36: 11111110118 | AG36: LIGNE A GENERER
A38: TYPE 4A COMPOSANTE FORFAIT | B38: Type d’enregistrement | C38: N° partenaire de santé + clé | D38: FILLER | E38: N° immatriculation assuré | F38: Clé N° immatriculation | G38: N° de facture | H38: Complément de type | I38: Séquence | J38: Mode de traitement | K38: Discipline de prestations (ex DMT) | L38: Date de la demande d’accord préalable ou date d’accord de prise en charge CMU. | M38: Code accord préalable | N38: Séquence de renouvellement | O38: Code Participation assuré | P38: Justification d’exonération du Ticket Modérateur au niveau de l’acte | Q38: 55-63 | R38: Zone tarif de l’exécutant | S38: Spécialité de l’exécutant | T38: Date de l’acte, de la délivrance du produit | U38: Code acte | V38: Quantité d'actes | W38: Coefficient | X38: Dénombrement | Y38: Prix unitaire | Z38: Base de remboursement | AA38: Taux applicable à la prestation- | AB38: Montant remboursable par l’organisme d’Assurance Maladie Obligatoire | AC38: Montant des honoraires ou de la dépense (dépassement compris ou après remise pour la norme FR) | AD38: Qualificatif de la dépense | AE38: Code lieu | AF38: Montant remboursable par l’organisme complémentaire
B39: 1 | C39: 2-10 | D39: 11 | E39: 12-24 | F39: 25-26 | G39: 27-35 | H39: 36 | I39: 37-38 | J39: 39-40 | K39: 41-43 | L39: 44-49 | M39: 50 | N39: 51-52 | O39: 53 | P39: 54 | Q39: 55-63 | R39: 64-65 | S39: 66-67 | T39: 68-73 | U39: 74-78 | V39: 79-80 | W39: 81-86 | X39: 87-88 | Y39: 89-95 | Z39: 96-102 | AA39: 103-105 | AB39: 106-112 | AC39: 113-119 | AD39: 120 | AE39: 121 | AF39: 122-128
B40: 1 | C40: 9 | D40: 1 | E40: 13 | F40: 2 | G40: 9 | H40: 1 | I40: 2 | J40: 2 | K40: 3 | L40: 6 | M40: 1 | N40: 2 | O40: 1 | P40: 1 | Q40: 9 | R40: 2 | S40: 2 | T40: 6 | U40: 5 | V40: 2 | W40: 6 | X40: 2 | Y40: 7 | Z40: 7 | AA40: 3 | AB40: 7 | AC40: 7 | AD40: 1 | AE40: 1 | AF40: 7
B41: N | C41: N | D41: A | E41: A | F41: N | G41: N | H41: A | I41: N | J41: N | K41: N | L41: N | M41: N | N41: A | O41: A | P41: A | Q41: N | R41: N | S41: N | T41: N | U41: A | V41: N | W41: N | X41: N | Y41: N | Z41: N | AA41: N | AB41: N | AC41: N | AD41: A | AE41: N | AF41: N
B42: O | C42: O | D42: F | E42: O | F42: O | G42: O | H42: F | I42: F | J42: F | K42: F | L42: F | M42: O | N42: F | O42: F | P42: F | Q42: F | R42: F | S42: OSIMO | T42: O | U42: O | V42: O | W42: O | X42: O | Y42: O | Z42: O | AA42: O | AB42: O | AC42: O | AD42: F | AE42: F | AF42: F
B43: 4 | C43: 422500009 | E43: 1500101001001 | F43: 77 | G43: 250000001 | H43: A | I43: 00 | J43: 00 | K43: 000 | L43: 000000 | M43: 9 | Q43: 422500009 | R43: 00 | S43: 00 | T43: 251201 | U43: FX1 | V43: 01 | W43: 000100 | X43: 02 | Y43: 0002600 | Z43: 0002600 | AA43: 055 | AB43: 0001430 | AC43: 0002600 | AE43: 1 | AF43: 0000000 | AG43: LIGNE A GENERER
A45: TYPE 4T | B45: Type d’enregistrement | C45: N° partenaire de santé + clé | D45: FILLER | E45: N° immatriculation assuré | F45: Clé N° immatriculation | G45: N° de facture | H45: Complément du type | I45: Séquence | J45: Filler | K45: Série (au sens du décret du 6/5/88) | L45: Transport lié à une hospitalisation | M45: Longue distance | N45: Filler | O45: Forfait type de forfait | P45: Prix unitaire du forfait non majoré | Q45: Quantité forfaits | R45: Quantité forfaits majoration de nuit | S45: Quantité forfaits majoration dimanche ou fériés | T45: Prix unitaire du kilomètre non réduit. | U45: SANS MAJORATION : Quantité <ou=150 km | V45: Quantité >150 km | W45: MAJORATION NUIT : Quantité <ou=150 km | X45: Quantité >150 km | Y45: MAJORATION DIMANCHE/FERIE : Quantité <ou=150 km | Z45: Quantité >150 km | AA45: SUPPLEMENT : Type supplément | AB45: Quantité | AC45: Montant | AD45: PEAGES ET VOIES D'EAU Quantité | AE45: Montant | AF45: Montant global des abattements | AG45: Montant global des majorations pour courte distance | AH45: Filler
B46: 1 | C46: 2-10 | D46: 11 | E46: 12-24 | F46: 25-26 | G46: 27-35 | H46: 36 | I46: 37-38 | J46: 39-45 | K46: 46 | L46: 47 | M46: 48 | N46: 49 | O46: 50 | P46: 51-56 | Q46: 57-58 | R46: 59-60 | S46: 61-62 | T46: 63-68 | U46: 69-72 | V46: 73-76 | W46: 77-80 | X46: 81-84 | Y46: 85-88 | Z46: 89-92 | AA46: 93 | AB46: 94-95 | AC46: 96-101 | AD46: 102-103, | AE46: 104-109 | AF46: 110-116 | AG46: 117-123 | AH46: 142-128
B47: 1 | C47: 9 | D47: 1 | E47: 13 | F47: 2 | G47: 9 | H47: 1 | I47: 2 | J47: 7 | K47: 1 | L47: 1 | M47: 1 | N47: 1 | O47: 1 | P47: 6 | Q47: 2 | R47: 2 | S47: 2 | T47: 6 | U47: 4 | V47: 4 | W47: 4 | X47: 4 | Y47: 4 | Z47: 4 | AA47: 1 | AB47: 2 | AC47: 6 | AD47: 2 | AE47: 6 | AF47: 7 | AG47: 7 | AH47: 5
B48: N | C48: N | D48: A | E48: A | F48: N | G48: N | H48: A | I48: N | J48: A | K48: N | L48: N | M48: N | N48: A | O48: N | P48: N | Q48: N | R48: N | S48: N | T48: N | U48: N | V48: N | W48: N | X48: N | Y48: N | Z48: N | AA48: N | AB48: N | AC48: N | AD48: N | AE48: N | AF48: N | AG48: N | AH48: A
B49: O | C49: O | D49: F | E49: O | F49: O | G49: O | H49: O | I49: F | J49: F | K49: O | L49: O | M49: O | N49: F | O49: O | P49: F | Q49: F | R49: F | S49: F | T49: F | U49: F | V49: F | W49: F | X49: F | Y49: F | Z49: F | AA49: F | AB49: F | AC49: F | AD49: F | AE49: F | AF49: F | AG49: F | AH49: F
B50: 4 | C50: 422500009 | E50: 1500101001001 | F50: 77 | G50: 250000001 | H50: T | I50: 01 | K50: 0 | L50: 0 | M50: 0 | O50: 0 | P50: 000000 | Q50: 00 | R50: 00 | S50: 00 | T50: 000000 | U50: 0000 | V50: 0000 | W50: 0000 | X50: 0000 | Y50: 0000 | Z50: 0000 | AA50: 0 | AB50: 00 | AC50: 000000 | AD50: 00 | AE50: 000000 | AF50: 0000000 | AG50: 0000000
A52: TYPE 4U | B52: Type d’enregistrement | C52: N° partenaire de santé + clé | D52: FILLER | E52: N° immatriculation assuré | F52: Clé N° immatriculation | G52: N° de facture | H52: Complément du type | I52: Séquence | J52: Date départ | K52: Heure départ | L52: Lieu départ département commune | M52: N° véhicule | N52: Nom conducteur | O52: Prénom conducteur | P52: Nom accompagnateur | Q52: Prénom accompagnateur | R52: Date arrivée | S52: Heure arrivée | T52: Lieu d’arrivée | U52: Nombre malades | V52: % abattement | W52: Montant abattement | X52: Nombre de km facturés | Y52: Distance réelle parcourue | Z52: Utilisation du distancier | AA52: Niveau de certification | AB52: Montant de la majoration pour courte distance | AC52: Indicateur de période de réalisation du trajet | AD52: Filler
B53: 1 | C53: 2-10 | D53: 11 | E53: 12-24 | F53: 25-26 | G53: 27-35 | H53: 36 | I53: 37-38 | J53: 39-44 | K53: 45-48 | L53: 49-53 | M53: 54-62 | N53: 63-70 | O53: 71-73 | P53: 74-81 | Q53: 82-84 | R53: 85-90 | S53: 91-94 | T53: 95-99 | U53: 100 | V53: 101-102 | W53: 103-108 | X53: 109-112 | Y53: 113-116 | Z53: 117 | AA53: 118 | AB53: 119-124 | AC53: 125 | AD53: 126-128
B54: 1 | C54: 9 | D54: 1 | E54: 13 | F54: 2 | G54: 9 | H54: 1 | I54: 2 | J54: 6 | K54: 4 | L54: 5 | M54: 9 | N54: 8 | O54: 3 | P54: 8 | Q54: 3 | R54: 6 | S54: 4 | T54: 5 | U54: 1 | V54: 2 | W54: 6 | X54: 4 | Y54: 4 | Z54: 1 | AA54: 1 | AB54: 6 | AC54: 1 | AD54: 3
B55: N | C55: N | D55: A | E55: A | F55: N | G55: N | H55: A | I55: N | J55: N | K55: N | L55: N | M55: A | N55: A | O55: A | P55: A | Q55: A | R55: N | S55: N | T55: N | U55: N | V55: N | W55: N | X55: N | Y55: N | Z55: A | AA55: A | AB55: N | AC55: A | AD55: A
B56: O | C56: O | D56: F | E56: O | F56: O | G56: O | H56: O | I56: O | J56: O | K56: P | L56: O | M56: O | N56: O | O56: O | P56: F | Q56: F | R56: O | S56: O | T56: O | U56: O | V56: F | W56: F | X56: F | Y56: O | Z56: F | AA56: F | AB56: F | AC56: F | AD56: F
B57: 4 | C57: 422500009 | E57: 1500101001001 | F57: 77 | G57: 250000001 | H57: U | I57: 01 | J57: 251201 | K57: 1000 | L57: 42218 | M57: AA-001-BB | N57: NCONDUCA | O57: PRA | R57: 251201 | S57: 1050 | T57: 42147 | U57: 1 | V57: 00 | W57: 000000 | X57: 0000 | Y57: 0040 | AB57: 000000 | AE57: LIGNE A GENERER
A58: TYPE 4 COMPOSANTE "KM"
A59: TYPE 4U | B59: Type d’enregistrement | C59: N° partenaire de santé + clé | D59: FILLER | E59: N° immatriculation assuré | F59: Clé N° immatriculation | G59: N° de facture | H59: Complément du type | I59: Séquence | J59: Date départ | K59: Heure départ | L59: Lieu départ département commune | M59: N° véhicule | N59: Nom conducteur | O59: Prénom conducteur | P59: Nom accompagnateur | Q59: Prénom accompagnateur | R59: Date arrivée | S59: Heure arrivée | T59: Lieu d’arrivée | U59: Nombre malades | V59: % abattement | W59: Montant abattement | X59: Nombre de km facturés | Y59: Distance réelle parcourue | Z59: Utilisation du distancier | AA59: Niveau de certification | AB59: Montant de la majoration pour courte distance | AC59: Indicateur de période de réalisation du trajet | AD59: Filler
B60: 1 | C60: 2-10 | D60: 11 | E60: 12-24 | F60: 25-26 | G60: 27-35 | H60: 36 | I60: 37-38 | J60: 39-44 | K60: 45-48 | L60: 49-53 | M60: 54-62 | N60: 63-70 | O60: 71-73 | P60: 74-81 | Q60: 82-84 | R60: 85-90 | S60: 91-94 | T60: 95-99 | U60: 100 | V60: 101-102 | W60: 103-108 | X60: 109-112 | Y60: 113-116 | Z60: 117 | AA60: 118 | AB60: 119-124 | AC60: 125 | AD60: 126-128
B61: 1 | C61: 9 | D61: 1 | E61: 13 | F61: 2 | G61: 9 | H61: 1 | I61: 2 | J61: 6 | K61: 4 | L61: 5 | M61: 9 | N61: 8 | O61: 3 | P61: 8 | Q61: 3 | R61: 6 | S61: 4 | T61: 5 | U61: 1 | V61: 2 | W61: 6 | X61: 4 | Y61: 4 | Z61: 1 | AA61: 1 | AB61: 6 | AC61: 1 | AD61: 3
B62: N | C62: N | D62: A | E62: A | F62: N | G62: N | H62: A | I62: N | J62: N | K62: N | L62: N | M62: A | N62: A | O62: A | P62: A | Q62: A | R62: N | S62: N | T62: N | U62: N | V62: N | W62: N | X62: N | Y62: N | Z62: A | AA62: A | AB62: N | AC62: A | AD62: A
B63: O | C63: O | D63: F | E63: O | F63: O | G63: O | H63: O | I63: O | J63: O | K63: P | L63: O | M63: O | N63: O | O63: O | P63: F | Q63: F | R63: O | S63: O | T63: O | U63: O | V63: F | W63: F | X63: F | Y63: O | Z63: F | AA63: F | AB63: F | AC63: F | AD63: F
B64: 4 | C64: 422500009 | E64: 1500101001001 | F64: 77 | G64: 250000001 | H64: U | I64: 02 | J64: 251201 | K64: 1300 | L64: 42147 | M64: AA-001-BB | N64: NCONDUCB | O64: PRB | R64: 251201 | S64: 1350 | T64: 42218 | U64: 1 | V64: 00 | W64: 000000 | X64: 0000 | Y64: 0040 | AB64: 000000 | AE64: LIGNE A GENERER
A66: TYPE 4 COMPOSANTE "KM" | B66: Type d’enregistrement | C66: N° partenaire de santé + clé | D66: FILLER | E66: N° immatriculation assuré | F66: Clé N° immatriculation | G66: N° de facture | H66: Complément de type | I66: Séquence | J66: Mode de traitement | K66: Discipline de prestations (ex DMT) | L66: Date de la demande d’accord préalable ou date d’accord de prise en charge CMU. | M66: Code accord préalable | N66: Séquence de renouvellement | O66: Code Participation assuré | P66: Justification d’exonération du Ticket Modérateur au niveau de l’acte | Q66: N° exécutant + clé ayant effectué l’acte ou fourni le produit | R66: Zone tarif de l’exécutant | S66: Spécialité de l’exécutant | T66: Date de l’acte, de la délivrance du produit | U66: Code acte | V66: Quantité d'actes | W66: Coefficient | X66: Dénombrement | Y66: Prix unitaire | Z66: Base de remboursement | AA66: Taux applicable à la prestation- | AB66: Montant remboursable par l’organisme d’Assurance Maladie Obligatoire | AC66: Montant des honoraires ou de la dépense (dépassement compris ou après remise pour la norme FR) | AD66: Qualificatif de la dépense | AE66: Code lieu | AF66: Montant remboursable par l’organisme complémentaire
B67: 1 | C67: 2-10 | D67: 11 | E67: 12-24 | F67: 25-26 | G67: 27-35 | H67: 36 | I67: 37-38 | J67: 39-40 | K67: 41-43 | L67: 44-49 | M67: 50 | N67: 51-52 | O67: 53 | P67: 54 | Q67: 55-63 | R67: 64-65 | S67: 66-67 | T67: 68-73 | U67: 74-78 | V67: 79-80 | W67: 81-86 | X67: 87-88 | Y67: 89-95 | Z67: 96-102 | AA67: 103-105 | AB67: 106-112 | AC67: 113-119 | AD67: 120 | AE67: 121 | AF67: 122-128
B68: 1 | C68: 9 | D68: 1 | E68: 13 | F68: 2 | G68: 9 | H68: 1 | I68: 2 | J68: 2 | K68: 3 | L68: 6 | M68: 1 | N68: 2 | O68: 1 | P68: 1 | Q68: 9 | R68: 2 | S68: 2 | T68: 6 | U68: 5 | V68: 2 | W68: 6 | X68: 2 | Y68: 7 | Z68: 7 | AA68: 3 | AB68: 7 | AC68: 7 | AD68: 1 | AE68: 1 | AF68: 7
B69: N | C69: N | D69: A | E69: A | F69: N | G69: N | H69: A | I69: N | J69: N | K69: N | L69: N | M69: N | N69: A | O69: A | P69: A | Q69: N | R69: N | S69: N | T69: N | U69: A | V69: N | W69: N | X69: N | Y69: N | Z69: N | AA69: N | AB69: N | AC69: N | AD69: A | AE69: N | AF69: N
B70: O | C70: O | D70: F | E70: O | F70: O | G70: O | H70: F | I70: F | J70: F | K70: F | L70: F | M70: O | N70: F | O70: F | P70: F | Q70: F | R70: F | S70: OSIMO | T70: O | U70: O | V70: O | W70: O | X70: O | Y70: O | Z70: O | AA70: O | AB70: O | AC70: O | AD70: F | AE70: F | AF70: F
B71: 4 | C71: 422500009 | E71: 1500101001001 | F71: 77 | G71: 250000001 | I71: 00 | J71: 00 | K71: 000 | L71: 000000 | M71: 9 | Q71: 422500009 | R71: 00 | S71: 00 | T71: 251201 | U71: KXN | V71: 01 | W71: 000100 | X71: 02 | Y71: 0007776 | Z71: 0007776 | AA71: 055 | AB71: 0004277 | AC71: 0007776 | AE71: 1 | AF71: 0000000 | AG71: LIGNE A GENERER
A73: TYPE 4 COMPOSANTE "TPMR" | B73: Type d’enregistrement | C73: N° partenaire de santé + clé | D73: FILLER | E73: N° immatriculation assuré | F73: Clé N° immatriculation | G73: N° de facture | H73: Complément de type | I73: Séquence | J73: Mode de traitement | K73: Discipline de prestations (ex DMT) | L73: Date de la demande d’accord préalable ou date d’accord de prise en charge CMU. | M73: Code accord préalable | N73: Séquence de renouvellement | O73: Code Participation assuré | P73: Justification d’exonération du Ticket Modérateur au niveau de l’acte | Q73: N° exécutant + clé ayant effectué l’acte ou fourni le produit | R73: Zone tarif de l’exécutant | S73: Spécialité de l’exécutant | T73: Date de l’acte, de la délivrance du produit | U73: Code acte | V73: Quantité d'actes | W73: Coefficient | X73: Dénombrement | Y73: Prix unitaire | Z73: Base de remboursement | AA73: Taux applicable à la prestation- | AB73: Montant remboursable par l’organisme d’Assurance Maladie Obligatoire | AC73: Montant des honoraires ou de la dépense (dépassement compris ou après remise pour la norme FR) | AD73: Qualificatif de la dépense | AE73: Code lieu | AF73: Montant remboursable par l’organisme complémentaire
B74: 1 | C74: 2-10 | D74: 11 | E74: 12-24 | F74: 25-26 | G74: 27-35 | H74: 36 | I74: 37-38 | J74: 39-40 | K74: 41-43 | L74: 44-49 | M74: 50 | N74: 51-52 | O74: 53 | P74: 54 | Q74: 55-63 | R74: 64-65 | S74: 66-67 | T74: 68-73 | U74: 74-78 | V74: 79-80 | W74: 81-86 | X74: 87-88 | Y74: 89-95 | Z74: 96-102 | AA74: 103-105 | AB74: 106-112 | AC74: 113-119 | AD74: 120 | AE74: 121 | AF74: 122-128
B75: 1 | C75: 9 | D75: 1 | E75: 13 | F75: 2 | G75: 9 | H75: 1 | I75: 2 | J75: 2 | K75: 3 | L75: 6 | M75: 1 | N75: 2 | O75: 1 | P75: 1 | Q75: 9 | R75: 2 | S75: 2 | T75: 6 | U75: 5 | V75: 2 | W75: 6 | X75: 2 | Y75: 7 | Z75: 7 | AA75: 3 | AB75: 7 | AC75: 7 | AD75: 1 | AE75: 1 | AF75: 7
B76: N | C76: N | D76: A | E76: A | F76: N | G76: N | H76: A | I76: N | J76: N | K76: N | L76: N | M76: N | N76: A | O76: A | P76: A | Q76: N | R76: N | S76: N | T76: N | U76: A | V76: N | W76: N | X76: N | Y76: N | Z76: N | AA76: N | AB76: N | AC76: N | AD76: A | AE76: N | AF76: N
B77: O | C77: O | D77: F | E77: O | F77: O | G77: O | H77: F | I77: F | J77: F | K77: F | L77: F | M77: O | N77: F | O77: F | P77: F | Q77: F | R77: F | S77: OSIMO | T77: O | U77: O | V77: O | W77: O | X77: O | Y77: O | Z77: O | AA77: O | AB77: O | AC77: O | AD77: F | AE77: F | AF77: F
B78: 4 | C78: 422500009 | E78: 1500101001001 | F78: 77 | G78: 250000001 | I78: 00 | J78: 00 | K78: 000 | L78: 000000 | M78: 9 | Q78: 422500009 | R78: 00 | S78: 00 | T78: 251201 | U78: TMR | V78: 02 | W78: 000100 | X78: 02 | Y78: 0003000 | Z78: 0006000 | AA78: 055 | AB78: 0003300 | AC78: 0006000 | AE78: 1 | AF78: 0000000 | AG78: LIGNE A GENERER
A80: TYPE 5 FIN FACTURE | B80: Type d’enregistrement | C80: N° partenaire de santé + clé | D80: FILLER | E80: N° immatriculation assuré | F80: Clé N° immatriculation | G80: N° de facture | H80: FILLER | I80: Nombre d’enregistrements de Type 4 | J80: Zone réservée SESAM | K80: Total des montants facturés | L80: Total remboursable par la Caisse | M80: Total participation assuré avant participation de l’organisme complémentaire | N80: Total remboursable par l’organisme complémentaire | O80: Top éclatement des flux par l’OCT | P80: Zone réservée SESAM | Q80: Liste d’opposition | R80: FILLER | S80: Zone de certification
B81: 1 | C81: 2-10 | D81: 11 | E81: 12-24 | F81: 25-26 | G81: 27-35 | H81: 36-38 | I81: 39-41 | J81: 42-57 | K81: 58-65 | L81: 66-73 | M81: 74-81 | N81: 82-89 | O81: 90 | P81: 91-93 | Q81: 94 | R81: 95-96 | S81: 97-128
B82: 1 | C82: 9 | D82: 1 | E82: 13 | F82: 2 | G82: 9 | H82: 3 | I82: 3 | J82: 16 | K82: 8 | L82: 8 | M82: 8 | N82: 8 | O82: 1 | P82: 3 | Q82: 1 | R82: 2 | S82: 32
B83: N | C83: N | D83: A | E83: A | F83: N | G83: N | H83: A | I83: N | J83: A | K83: N | L83: N | M83: N | N83: N | O83: A | P83: A | Q83: A | R83: A | S83: A
B84: O | C84: O | D84: F | E84: O | F84: O | G84: O | H84: F | I84: O | J84: O | K84: O | L84: O | M84: O | N84: F | O84: F | P84: O | Q84: O | R84: F | S84: F
B85: 5 | C85: 422500009 | E85: 1500101001001 | F85: 77 | G85: 250000001 | I85: 006 | K85: 00016376 | L85: 00009007 | M85: 00007369 | N85: 00000000
A87: TYPE 6 FIN LOT | B87: Type d’enregistrement | C87: N° partenaire de santé + clé | D87: Nombre de factures | E87: Nombre de lignes actes | F87: Comptabilisation des enregistrements des types 2 | G87: Total de tous les enregistrements de type 5 | H87: Montant total général du lot prestations facturées | I87: Montant total général du lot prestations remboursables par l’organisme d’Ass. Maladie | J87: Montant total général du lot prestations remboursables par les organismes complémentaires | K87: N° de lot | L87: indicateur de marquage des factures du lot. | M87: Type de facture | N87: FILLER | O87: N° agrément progiciel de santé ou n° de certificat pour les logiciels établissements ou raison sociale éditeur | P87: N° agrément du dispositif portable | Q87: FILLER | R87: N° d’identification du PS remplaçant | S87: Zone de certification
B88: 1 | C88: 2-10 | D88: 11-13 | E88: 14-17 | F88: 18-21 | G88: 22-24 | H88: 25-33 | I88: 34-42 | J88: 43-51 | K88: 52-54 | L88: 55 | M88: 56 | N88: 57-60 | O88: 61-72 | P88: 73-84 | Q88: 85-87 | R88: 88-96 | S88: 97-128
B89: 1 | C89: 9 | D89: 3 | E89: 4 | F89: 4 | G89: 3 | H89: 9 | I89: 9 | J89: 9 | K89: 3 | L89: 1 | M89: 1 | N89: 4 | O89: 12 | P89: 12 | Q89: 3 | R89: 9 | S89: 32
B90: N | C90: N | D90: N | E90: N | F90: N | G90: N | H90: N | I90: N | J90: N | K90: N | L90: A | M90: A | N90: A | O90: A | P90: N | Q90: A | R90: N | S90: N
B91: O | C91: O | D91: O | E91: O | F91: O | G91: O | H91: O | I91: O | J91: O | K91: O | L91: F | M91: F | N91: F | O91: F | P91: F | Q91: F | R91: F | S91: O
B92: 6 | C92: 422500009 | D92: 001 | E92: 0003 | F92: 0002 | G92: 001 | H92: 000016376 | I92: 000009007 | J92: 000000000 | K92: 001 | O92: AAZZ2501BC12
A94: TYPE 999 FIN FICHIER | B94: Type d’enregistrement | C94: Type émetteur | D94: Numéro émetteur | E94: FILLER | F94: Type de destinataire | G94: Numéro de destinataire | H94: FILLER | I94: Application | J94: Identification du fichier | K94: Volume du fichier | L94: FILLER | M94: Nombre de lots | N94: FILLER
B95: 1-3 | C95: 4-5 | D95: 6-19 | E95: 20-25 | F95: 26-27 | G95: 28-41 | H95: 42-47 | I95: 48-49 | J95: 50-55 | K95: 56-63 | L95: 64-82 | M95: 83-85 | N95: 86-128
B96: 3 | C96: 2 | D96: 14 | E96: 6 | F96: 2 | G96: 14 | H96: 6 | I96: 2 | J96: 6 | K96: 8 | L96: 19 | M96: 3 | N96: 43
B97: N | C97: A | D97: N | E97: A | F97: A | G97: N | H97: A | I97: A | J97: A | K97: N | L97: A | M97: N | N97: A
B98: O | C98: O | D98: O | E98: F | F98: O | G98: O | H98: F | I98: O | J98: O | K98: O | L98: F | M98: O | N98: F
B99: 999 | C99: TP | D99: 00000422500009 | F99: CT | G99: 00000001000422 | I99: TR | J99: TESTB2 | K99: 00000013 | M99: 001

Sheet CONVENTION CAS 8
A1: Table des matières | B1: CARACTERISTIQUES METIERS DU OU DES TRAJETS FACTURES
A3: SOCIETE DE TAXI DE N° AM : 422500009 SPECIALITE : 56 | D3: CARACTERISTIQUE PATIENT | G3: CARACTERISTIQUES FACTURE | I3: CARACTERISTIQUES TRAJETS | Z3: ASSURE | AG3: PRESCRIPTEUR
A4: N°CAS | B4: NOMBRE DE TRAJETS FACTURES | C4: TRAJET N° : | D4: NATURE D'ASSURANCE | E4: TAUX | F4: C2S ? : O/N | G4: REFUS TRANSPORT PARTAGE | H4: TIERS PAYANT | I4: LIEU DEPART | J4: LIEU ARRIVEE | K4: DATE / HEURE DEPART | L4: DATE / HEURE ARRIVEE | M4: N° IMMATRICULATION VEHICULE | N4: COMMUNE D'ADS | O4: DEPARTEMENT D'ADS | P4: ORGANISME LOCAL D'ADS | Q4: DISTANCE PARCOURUE | R4: CONTEXTE : J, N , F | S4: NOMBRE DE MALADES | T4: SUPPLEMENT FORFAITAIRE ? : O / N | U4: PEAGES ? : O / N | V4: TPMR ? : O / N | W4: TRAJET EN LIEN AVEC HOSPITALISATION ET RETOUR A VIDE ? : O/N | X4: SI T PARTAGE : TRAJET SEUL > X KM ? : O/N | Z4: NIR | AA4: DATE DE NAISSANCE | AB4: RANG | AC4: REGIME | AD4: CAISSE | AE4: CENTRE | AG4: N°AM | AH4: SPECIALITE | AI4: NN°RPPS
A5: ='LISTE DES CAS ANNEXE 30'!A18 -> CONVENTION CAS 8 | B5: ='LISTE DES CAS ANNEXE 30'!B18 -> 1 | C5: ='LISTE DES CAS ANNEXE 30'!C18 -> 1 | D5: ='LISTE DES CAS ANNEXE 30'!D18 -> MALADIE | E5: ='LISTE DES CAS ANNEXE 30'!E18 -> 0.55 | F5: ='LISTE DES CAS ANNEXE 30'!H18 -> NON | G5: ='LISTE DES CAS ANNEXE 30'!I18 -> Sans objet | H5: ='LISTE DES CAS ANNEXE 30'!J18 -> 05 - TP AMO SEUL | I5: ='LISTE DES CAS ANNEXE 30'!K18 -> 42-SAINT-ETIENNE | J5: ='LISTE DES CAS ANNEXE 30'!L18 -> 42-MONTBRISON | K5: ='LISTE DES CAS ANNEXE 30'!M18 -> 01/12/2025 à 20h00 | L5: ='LISTE DES CAS ANNEXE 30'!N18 -> 01/12/2025 à 20h40 | M5: ='LISTE DES CAS ANNEXE 30'!O18 -> AA-001-BB | ... X5: ='LISTE DES CAS ANNEXE 30'!Z18 -> Sans objet | Z5: 1500101001001 | AA5: 500101 | AB5: 1 | AC5: 01 | AD5: 422 | AE5: 0000 | AG5: 421000001 | AH5: 01 | AI5: 11111110118
A7: FACTURE B2 CORRESPONDANT
A9: TYPE 000 DEBUT FICHIER | B9: Type d’enregistrement | C9: Type d’émetteur | D9: Numéro d’émetteur | E9: FILLER | F9: Type de destinataire | G9: N° de destinataire | H9: Date de réception du flux sur le frontal | I9: Application | J9: Identification du fichier | K9: Date de création du fichier | L9: Norme | M9: Version de Norme | N9: FILLER | O9: FILLER | P9: FILLER | Q9: FILLER | R9: Longueur d’enregistrement | S9: FILLER | T9: Zone message
B10: 1-3 | C10: 4-5 | D10: 6-19 | E10: 20-25 | F10: 26-27 | G10: 28-41 | H10: 42-47 | I10: 48-49 | J10: 50-55 | K10: 56-61 | L10: 62-65 | M10: 66-67 | N10: 68 | O10: 69 | P10: 70-72 | Q10: 73-82 | R10: 83-85 | S10: 86-91 | T10: 92-128
B11: 3 | C11: 2 | D11: 14 | E11: 6 | F11: 2 | G11: 14 | H11: 6 | I11: 2 | J11: 6 | K11: 6 | L11: 4 | M11: 2 | N11: 1 | O11: 1 | P11: 3 | Q11: 10 | R11: 3 | S11: 6 | T11: 37
B12: N | C12: A | D12: N | E12: A | F12: A | G12: N | H12: A | I12: A | J12: A | K12: N | L12: A | M12: A | N12: A | O12: A | P12: A | Q12: A | R12: N | S12: A | T12: N
B13: O | C13: O | D13: O | E13: F | F13: O | G13: O | H13: O | I13: O | J13: O | K13: O | L13: O | M13: O | N13: F | O13: F | P13: F | Q13: F | R13: F | S13: F | T13: O
B14: 000 | C14: TP | D14: 00000422500009 | F14: CT | G14: 00000001000422 | H14: 251231 | I14: TR | J14: TESTB2 | K14: 251231 | L14: TA | M14: B2 | R14: 128
A16: TYPE 1 DEBUT LOT | B16: Type d’enregistrement | C16: N° partenaire de santé + clé | D16: Origine du fichier | E16: N° d’organisme destinataire | F16: N° de lot | G16: Catégorie | H16: Statut juridique | I16: Mode de fixation des tarifs | J16: Nom ou raison sociale du partenaire de santé | K16: Version de norme utilisée | L16: Date de création du lot | M16: Filler | N16: Code norme | O16: Top certification du lot | P16: Numéro de version de norme | Q16: Unité monétaire de facturation | R16: Grand régime de la caisse pivot ou de la caisse de paiement unique privés, ou pour les établissements publics et privés antérieurement sous DG | S16: N° de la caisse pivot ou de la caisse de paiement unique | T16: Indication de dispositif Caisse Centralisatrice des Paiements ou de dispositif Caisse de Paiement Unique | U16: FILLER
B17: 1 | C17: 2-10 | D17: 11-16 | E17: 17-19 | F17: 20-22 | G17: 23-25 | H17: 26-27 | I17: 28-29 | J17: 30-69 | K17: 70-71 | L17: 72-77 | M17: 78 | N17: 79-80 | O17: 81 | P17: 82-87 | Q17: 88 | R17: 89-90 | S17: 91-93 | T17: 94 | U17: 95-128
B18: 1 | C18: 9 | D18: 6 | E18: 3 | F18: 3 | G18: 3 | H18: 2 | I18: 2 | J18: 40 | K18: 2 | L18: 6 | M18: 1 | N18: 2 | O18: 1 | P18: 6 | Q18: 1 | R18: 2 | S18: 3 | T18: 1 | U18: 34
B19: N | C19: N | D19: A | E19: N | F19: N | G19: A | H19: A | I19: A | J19: A | K19: A | L19: N | M19: A | N19: A | O19: A | P19: N | Q19: A | R19: A | S19: A | T19: N | U19: A
B20: O | C20: O | D20: F | E20: O | F20: O | G20: F | H20: F | I20: F | J20: O | K20: O | L20: O | M20: F | N20: O | O20: F | P20: O | Q20: F | R20: F | S20: F | T20: F | U20: FILLER
B21: 1 | C21: 422500009 | E21: 422 | F21: 001 | J21: SIMULATEUR B2 NOUVELLE CONVENTION TAXI | K21: B2 | L21: 251231 | N21: TA | P21: 062007 | Q21: U
A23: TYPE 2 DEBUT FACTURE | B23: Type d’enregistrement | C23: N° partenaire de santé + clé | D23: FILLER | E23: N° immatriculation assuré | F23: Clé N° immatriculation | G23: N° facture | H23: Complément du type | I23: Marquage de la facture | J23: Indicateur de forçage de la tarification de la part AMO | K23: Nature d’opération | L23: Date de facturation | M23: Top éclatement des flux par le PS | N23: Type de facture | O23: Facture sécurisée sur un dispositif portable | P23: Code Grand Régime | Q23: N° Caisse gestionnaire | R23: N° Centre gestionnaire | S23: Nature de la pièce justificative des droits | T23: N° prescripteur + clé | U23: Date de prescription | V23: Régime de prestation de l’assuré | W23: Nature d’assurance | X23: Justification d’exonération ou de modulation du ticket modérateur | Y23: Date Maternité | Z23: Numéro accident du travail ou date d’accident de droit commun | AA23: Présence d’une CPS de remplaçant pour sécurisation de la facture | AB23: Date de naissance du bénéficiaire | AC23: Rang de naissance | AD23: Rang de bénéficiaire | AE23: N° d’adhérent | AF23: Spécialité de prescripteur | AG23: Destinataire du règlement | AH23: Type de contrat souscrit auprès d’un organisme complémentaire | AI23: N° d’organisme complémentaire
B24: 1 | C24: 2-10 | D24: 11 | E24: 12-24 | F24: 25-26 | G24: 27-35 | H24: 36 | I24: 37 | J24: 38 | K24: 39 | L24: 40-45 | M24: 46 | N24: 47 | O24: 48 | P24: 49-50 | Q24: 51-53 | R24: 54-57 | S24: 58 | T24: 59-67 | U24: 68-73 | V24: 74-76 | W24: 77-78 | X24: 79 | Y24: 80-85 | Z24: 86-94 | AA24: 95 | AB24: 96-101 | AC24: 102 | AD24: 103-104 | AE24: 105-112 | AF24: 113-114 | AG24: 115-116 | AH24: 117-118 | AI24: 119-128
B25: 1 | C25: 9 | D25: 1 | E25: 13 | F25: 2 | G25: 9 | H25: 1 | I25: 1 | J25: 1 | K25: 1 | L25: 6 | M25: 1 | N25: 1 | O25: 1 | P25: 2 | Q25: 3 | R25: 4 | S25: 1 | T25: 9 | U25: 6 | V25: 3 | W25: 2 | X25: 1 | Y25: 6 | Z25: 9 | AA25: 1 | AB25: 6 | AC25: 1 | AD25: 2 | AE25: 8 | AF25: 2 | AG25: 2 | AH25: 2 | AI25: 10
B26: N | C26: N | D26: A | E26: A | F26: N | G26: N | H26: A | I26: A | J26: A | K26: N | L26: N | M26: A | N26: A | O26: A | P26: N | Q26: N | R26: N | S26: N | T26: N | U26: N | V26: A | W26: N | X26: A | Y26: N | Z26: N | AA26: A | AB26: N | AC26: N | AD26: A | AE26: A | AF26: N | AG26: N | AH26: N | AI26: A
B27: O | C27: O | D27: F | E27: O | F27: O | G27: O | H27: F | I27: F | J27: F | K27: O | L27: O | M27: F | N27: F | O27: F | P27: O | Q27: O | R27: O | S27: O | T27: O | U27: O | V27: F | W27: F | X27: O | Y27: F | Z27: F | AA27: O | AB27: O | AC27: F | AD27: F | AE27: F | AF27: F | AG27: F | AH27: F | AI27: F
